Workbook

Sheet Métadonnées
A1: Nom du fichier xlsx | B1: T_8210
A2: Date de création du fichier | B2: 2025-10-17T09:15:24
A3: Onglet | B3: T_8210 | C3: 8.210 – Compte de patrimoine des ménages (S14)
A4: Source | B4: Comptes nationaux annuels (base 2020)
A6: COD_VAR | B6: LIB_VAR | C6: COD_MOD | D6: LIB_MOD
A7: FREQ | B7: Fréquence | C7: A | D7: Annuel
A8: TIME_PERIOD | B8: Période temporelle | C8: 1978 -> 2024 | D8: 1978 -> 2024
A9: GEO_DATE | B9: Millésime géographique
A10: GEO_SCOPE | B10: Périmètre géographique | C10: FE | D10: France entière
A11: ACCOUNTING_ENTRY | B11: Position de compte | C11: C | D11: Ressource ou crédit
A12: ACCOUNTING_ENTRY | B12: Position de compte | C12: D | D12: Emploi ou débit
A13: ACTIVITY | B13: Activité économique | C13: _T | D13: Total
A14: CONSOLIDATION | B14: Consolidation | C14: N | D14: Non consolidé
A15: COUNTERPART_AREA | B15: Zone de contrepartie | C15: W0 | D15: Monde
A16: COUNTERPART_SECTOR | B16: Secteur institutionnel de contrepartie | C16: S1 | D16: Économie totale
A17: EXPENDITURE | B17: Type de dépense de consommation | C17: _Z | D17: Total
A18: INSTR_ASSET | B18: Classe d'actifs passifs | C18: N111N | D18: Logements (net)
A19: INSTR_ASSET | B19: Classe d'actifs passifs | C19: N1121N | D19: Bâtiments non résidentiels (net)
A20: INSTR_ASSET | B20: Classe d'actifs passifs | C20: N2N | D20: Actifs non financiers non produits (net)
A21: INSTR_ASSET | B21: Classe d'actifs passifs | C21: F511 | D21: Actions cotées
... A69: VALUATION | B69: Valuation | C69: S | D69: Evaluation standard

Sheet Niveau
A1: 8.210 – Compte de patrimoine des ménages (S14)
A2: Unité : Milliards d'euros, en fin d'année
C4: 1978 | D4: 1979 | E4: 1980 | F4: 1981 | G4: 1982 | H4: 1983 | I4: 1984 | J4: 1985 | K4: 1986 | L4: 1987 | M4: 1988 | N4: 1989 | O4: 1990 | P4: 1991 | Q4: 1992 | R4: 1993 | S4: 1994 | T4: 1995 | U4: 1996 | V4: 1997 | W4: 1998 | X4: 1999 | Y4: 2000 | Z4: 2001 | AA4: 2002 | AB4: 2003 | AC4: 2004 | AD4: 2005 | AE4: 2006 | AF4: 2007 | AG4: 2008 | AH4: 2009 | AI4: 2010 | AJ4: 2011 | AK4: 2012 | AL4: 2013 | AM4: 2014 | AN4: 2015 | AO4: 2016 | AP4: 2017 | AQ4: 2018 | AR4: 2019 | AS4: 2020 | AT4: 2021 | AU4: 2022 | AV4: 2023 | AW4: 2024
A6: NN | B6: Total des actifs non financiers (net) | C6: 778.641 | D6: 899.909 | E6: 1026.051 | F6: 1154.598 | G6: 1274.534 | H6: 1399.243 | I6: 1466.728 | J6: 1532.327 | K6: 1620.772 | L6: 1716.474 | M6: 1848.238 | N6: 2005.584 | O6: 2145.773 | P6: 2171.116 | Q6: 2139.5 | R6: 2133.511 | S6: 2186.859 | T6: 2181.869 | U6: 2230.685 | V6: 2270.999 | W6: 2400.399 | X6: 2655.34 | Y6: 2929.644 | Z6: 3215.616 | AA6: 3623.73 | AB6: 4170.775 | AC6: 4897.774 | AD6: 5700.758 | AE6: 6328.283 | AF6: 6769.226 | AG6: 6489.052 | AH6: 6445.14 | AI6: 7012.899 | AJ6: 7286.289 | AK6: 7230.886 | AL6: 7185.659 | AM6: 7106.361 | AN6: 7167.711 | AO6: 7396.974 | AP6: 7725.384 | AQ6: 8059.674 | AR6: 8475.817 | AS6: 9028.041 | AT6: 9736.338 | AU6: 10235.023 | AV6: 9931.491 | AW6: 9867.778
A7: N1N | B7: Actifs non financiers produits (net) | C7: 486.393 | D7: 571.783 | E7: 664.528 | F7: 757.724 | G7: 860.371 | H7: 953.445 | I7: 1021.148 | J7: 1073.869 | K7: 1133.516 | L7: 1202.445 | M7: 1271.235 | N7: 1342.686 | O7: 1422.561 | P7: 1484.298 | Q7: 1523.948 | R7: 1560.813 | S7: 1597.478 | T7: 1646.091 | U7: 1704.501 | V7: 1757.932 | W7: 1807.379 | X7: 1871.167 | Y7: 1959.601 | Z7: 2069.731 | AA7: 2176.625 | AB7: 2299.668 | AC7: 2450.719 | AD7: 2611.205 | AE7: 2781.78 | AF7: 2959.98 | AG7: 3083.646 | AH7: 3166.008 | AI7: 3301.381 | AJ7: 3425.553 | AK7: 3501.676 | AL7: 3580.683 | AM7: 3653.291 | AN7: 3697.152 | AO7: 3784.357 | AP7: 3910.332 | AQ7: 4035.352 | AR7: 4146.477 | AS7: 4313.572 | AT7: 4701.545 | AU7: 5067.126 | AV7: 5206.065 | AW7: 5261.817
A8: N11N | B8: Actifs fixes par type d’actifs (net) | C8: 434.729 | D8: 512.626 | E8: 601.191 | F8: 695.424 | G8: 791.815 | H8: 873.774 | I8: 943.834 | J8: 1002.048 | K8: 1062.048 | L8: 1129.432 | M8: 1200.655 | N8: 1276.883 | O8: 1360.656 | P8: 1425.182 | Q8: 1466.453 | R8: 1502.232 | S8: 1539.694 | T8: 1587.608 | U8: 1645.286 | V8: 1700.239 | W8: 1748.024 | X8: 1803.467 | Y8: 1882.4 | Z8: 1978.018 | AA8: 2076.425 | AB8: 2198.93 | AC8: 2342.262 | AD8: 2487.58 | AE8: 2646.307 | AF8: 2823.968 | AG8: 2957.804 | AH8: 3038.231 | AI8: 3153.919 | AJ8: 3273.221 | AK8: 3354.002 | AL8: 3434.513 | AM8: 3504.772 | AN8: 3550.421 | AO8: 3636.054 | AP8: 3753.914 | AQ8: 3878.106 | AR8: 3991.675 | AS8: 4148.38 | AT8: 4500.558 | AU8: 4843.242 | AV8: 4986.725 | AW8: 5042.603
A9: N11KN | B9: Constructions (net) | C9: 411.214 | D9: 486.378 | E9: 571.114 | F9: 661.152 | G9: 752.762 | H9: 832.511 | I9: 900.946 | J9: 957.791 | K9: 1017.179 | L9: 1083.637 | M9: 1151.866 | N9: 1225.126 | O9: 1307.552 | P9: 1372.637 | Q9: 1415.647 | R9: 1453.348 | S9: 1491.495 | T9: 1540.829 | U9: 1599.979 | V9: 1655.439 | W9: 1703.537 | X9: 1759.329 | Y9: 1837.827 | Z9: 1933.9 | AA9: 2032.861 | AB9: 2155.541 | AC9: 2299.161 | AD9: 2444.805 | AE9: 2604.025 | AF9: 2781.737 | AG9: 2916.439 | AH9: 2997.704 | AI9: 3114.717 | AJ9: 3234.321 | AK9: 3315.185 | AL9: 3396.072 | AM9: 3467.257 | AN9: 3513.96 | AO9: 3600.314 | AP9: 3718.184 | AQ9: 3842.055 | AR9: 3954.577 | AS9: 4110.54 | AT9: 4461.275 | AU9: 4802.204 | AV9: 4945.131 | AW9: 5001.149
A10: N111N | B10: Logements (net) | C10: 366.873 | D10: 434.796 | E10: 511.398 | F10: 593.579 | G10: 677.924 | H10: 752.323 | I10: 817.121 | J10: 871.811 | K10: 928.451 | L10: 991.136 | M10: 1055.23 | N10: 1124.882 | O10: 1205.24 | P10: 1270.27 | Q10: 1314.513 | R10: 1352.529 | S10: 1389.948 | T10: 1438.619 | U10: 1496.424 | V10: 1549.9 | W10: 1595.614 | X10: 1647.497 | Y10: 1723.53 | Z10: 1818.4 | AA10: 1914.747 | AB10: 2034.21 | AC10: 2174.815 | AD10: 2317.159 | AE10: 2472.589 | AF10: 2644.971 | AG10: 2776.254 | AH10: 2855.334 | AI10: 2967.187 | AJ10: 3082.974 | AK10: 3163.058 | AL10: 3245.254 | AM10: 3319.9 | AN10: 3369.604 | AO10: 3454.529 | AP10: 3568.328 | AQ10: 3687.858 | AR10: 3797.345 | AS10: 3948.081 | AT10: 4284.832 | AU10: 4613.448 | AV10: 4752.687 | AW10: 4807.411
A11: N112N | B11: Autres bâtiments et ouvrages de génie civil (net) | C11: 44.341 | D11: 51.582 | E11: 59.716 | F11: 67.572 | G11: 74.839 | H11: 80.188 | I11: 83.825 | J11: 85.98 | K11: 88.728 | L11: 92.501 | M11: 96.636 | N11: 100.244 | O11: 102.313 | P11: 102.368 | Q11: 101.133 | R11: 100.819 | S11: 101.546 | T11: 102.21 | U11: 103.555 | V11: 105.539 | W11: 107.922 | X11: 111.832 | Y11: 114.298 | Z11: 115.499 | AA11: 118.113 | AB11: 121.331 | AC11: 124.347 | AD11: 127.646 | AE11: 131.435 | AF11: 136.766 | AG11: 140.184 | AH11: 142.37 | AI11: 147.53 | AJ11: 151.347 | AK11: 152.127 | AL11: 150.818 | AM11: 147.357 | AN11: 144.356 | AO11: 145.785 | AP11: 149.856 | AQ11: 154.197 | AR11: 157.232 | AS11: 162.459 | AT11: 176.444 | AU11: 188.756 | AV11: 192.444 | AW11: 193.738
A12: N1121N | B12: Bâtiments non résidentiels (net) | C12: 20.119 | D12: 22.581 | E12: 25.415 | F12: 28.102 | G12: 30.458 | H12: 32.086 | I12: 33.223 | J12: 33.504 | K12: 33.729 | L12: 34.274 | M12: 34.752 | N12: 35.318 | O12: 35.758 | P12: 35.838 | Q12: 35.482 | R12: 34.863 | S12: 34.275 | T12: 33.796 | U12: 33.331 | V12: 33.195 | W12: 33.199 | X12: 34.054 | Y12: 34.928 | Z12: 35.124 | AA12: 35.209 | AB12: 35.499 | AC12: 35.846 | AD12: 36.053 | AE12: 36.319 | AF12: 37.016 | AG12: 37.629 | AH12: 37.224 | AI12: 37 | AJ12: 36.985 | AK12: 36.538 | AL12: 35.82 | AM12: 35.18 | AN12: 34.785 | AO12: 35.089 | AP12: 35.828 | AQ12: 37.011 | AR12: 38.332 | AS12: 40.212 | AT12: 43.232 | AU12: 45.595 | AV12: 46.162 | AW12: 45.917
A13: N1122N | B13: Autres ouvrages de génie civil (net) | C13: 24.223 | D13: 29.001 | E13: 34.301 | F13: 39.471 | G13: 44.381 | H13: 48.103 | I13: 50.603 | J13: 52.476 | K13: 54.999 | L13: 58.227 | M13: 61.885 | N13: 64.926 | O13: 66.555 | P13: 66.529 | Q13: 65.651 | R13: 65.956 | S13: 67.271 | T13: 68.414 | U13: 70.224 | V13: 72.344 | W13: 74.723 | X13: 77.778 | Y13: 79.37 | Z13: 80.376 | AA13: 82.904 | AB13: 85.832 | AC13: 88.5 | AD13: 91.593 | AE13: 95.116 | AF13: 99.749 | AG13: 102.555 | AH13: 105.146 | AI13: 110.53 | AJ13: 114.362 | AK13: 115.59 | AL13: 114.997 | AM13: 112.177 | AN13: 109.571 | AO13: 110.697 | AP13: 114.027 | AQ13: 117.186 | AR13: 118.901 | AS13: 122.246 | AT13: 133.212 | AU13: 143.161 | AV13: 146.281 | AW13: 147.821
A14: N113N | B14: Machines et équipements (net) | C14: 12.78 | D14: 14.78 | E14: 17.515 | F14: 20.476 | G14: 22.932 | H14: 24.353 | I14: 25.496 | J14: 26.402 | K14: 27.388 | L14: 28.462 | M14: 29.862 | N14: 31.749 | O14: 33.347 | P14: 33.693 | Q14: 32.601 | R14: 31.396 | S14: 30.982 | T14: 30.982 | U14: 30.786 | V14: 30.404 | W14: 30.261 | X14: 30.705 | Y14: 31.322 | Z14: 31.048 | AA14: 30.632 | AB14: 30.646 | AC14: 30.852 | AD14: 30.883 | AE14: 30.612 | AF14: 30.534 | AG14: 30.449 | AH14: 29.807 | AI14: 28.881 | AJ14: 28.814 | AK14: 28.946 | AL14: 28.678 | AM14: 27.988 | AN14: 27.185 | AO14: 26.624 | AP14: 26.781 | AQ14: 27.127 | AR14: 27.741 | AS14: 28.527 | AT14: 29.582 | AU14: 30.295 | AV14: 30.801 | AW14: 29.8
A15: N1131N | B15: Matériels de transport (net) | C15: 1.443 | D15: 1.626 | E15: 1.85 | F15: 2.063 | G15: 2.28 | H15: 2.407 | I15: 2.49 | J15: 2.617 | K15: 2.785 | L15: 2.94 | M15: 3.132 | N15: 3.423 | O15: 3.623 | P15: 3.535 | Q15: 3.307 | R15: 3.12 | S15: 3.123 | T15: 3.197 | U15: 3.02 | V15: 2.847 | W15: 2.85 | X15: 2.867 | Y15: 3.023 | Z15: 3.178 | AA15: 3.35 | AB15: 3.731 | AC15: 4.053 | AD15: 4.259 | AE15: 4.434 | AF15: 4.619 | AG15: 4.391 | AH15: 4.077 | AI15: 3.828 | AJ15: 3.764 | AK15: 3.599 | AL15: 3.427 | AM15: 3.356 | AN15: 3.278 | AO15: 3.217 | AP15: 3.342 | AQ15: 3.417 | AR15: 3.669 | AS15: 3.883 | AT15: 4.187 | AU15: 3.913 | AV15: 3.726 | AW15: 3.532
A16: N1132N | B16: Équipements TIC (net) | C16: 0.158 | D16: 0.185 | E16: 0.229 | F16: 0.267 | G16: 0.311 | H16: 0.34 | I16: 0.388 | J16: 0.443 | K16: 0.507 | L16: 0.564 | M16: 0.628 | N16: 0.654 | O16: 0.668 | P16: 0.649 | Q16: 0.626 | R16: 0.608 | S16: 0.606 | T16: 0.592 | U16: 0.564 | V16: 0.54 | W16: 0.519 | X16: 0.529 | Y16: 0.504 | Z16: 0.45 | AA16: 0.404 | AB16: 0.399 | AC16: 0.39 | AD16: 0.385 | AE16: 0.364 | AF16: 0.321 | AG16: 0.297 | AH16: 0.268 | AI16: 0.266 | AJ16: 0.269 | AK16: 0.27 | AL16: 0.272 | AM16: 0.283 | AN16: 0.296 | AO16: 0.345 | AP16: 0.371 | AQ16: 0.41 | AR16: 0.409 | AS16: 0.433 | AT16: 0.45 | AU16: 0.43 | AV16: 0.404 | AW16: 0.391
A17: N1139N | B17: Autres machines et équipements (net) | C17: 11.179 | D17: 12.969 | E17: 15.436 | F17: 18.146 | G17: 20.341 | H17: 21.606 | I17: 22.618 | J17: 23.343 | K17: 24.096 | L17: 24.959 | M17: 26.102 | N17: 27.672 | O17: 29.056 | P17: 29.51 | Q17: 28.668 | R17: 27.668 | S17: 27.253 | T17: 27.193 | U17: 27.203 | V17: 27.017 | W17: 26.891 | X17: 27.309 | Y17: 27.795 | Z17: 27.42 | AA17: 26.878 | AB17: 26.517 | AC17: 26.408 | AD17: 26.239 | AE17: 25.814 | AF17: 25.593 | AG17: 25.762 | AH17: 25.462 | AI17: 24.787 | AJ17: 24.781 | AK17: 25.077 | AL17: 24.979 | AM17: 24.349 | AN17: 23.611 | AO17: 23.062 | AP17: 23.068 | AQ17: 23.3 | AR17: 23.663 | AS17: 24.211 | AT17: 24.945 | AU17: 25.953 | AV17: 26.671 | AW17: 25.877
A18: N114N | B18: Systèmes d’armes (net)
A19: N115N | B19: Ressources biologiques cultivées (net) | C19: 9.542 | D19: 10.139 | E19: 11.057 | F19: 12.106 | G19: 14.289 | H19: 14.986 | I19: 15.377 | J19: 15.76 | K19: 15.262 | L19: 15.001 | M19: 16.478 | N19: 17.401 | O19: 17.011 | P19: 16.068 | Q19: 15.428 | R19: 14.768 | S19: 14.461 | T19: 13.004 | U19: 11.747 | V19: 11.637 | W19: 11.434 | X19: 10.552 | Y19: 10.217 | Z19: 9.891 | AA19: 9.746 | AB19: 9.559 | AC19: 9.008 | AD19: 8.58 | AE19: 8.301 | AF19: 8.207 | AG19: 7.434 | AH19: 7.432 | AI19: 7.158 | AJ19: 6.954 | AK19: 6.704 | AL19: 6.591 | AM19: 6.357 | AN19: 6.108 | AO19: 5.919 | AP19: 5.653 | AQ19: 5.449 | AR19: 5.679 | AS19: 5.425 | AT19: 5.229 | AU19: 5.614 | AV19: 4.99 | AW19: 5.215
A20: N117N | B20: Droits de propriété intellectuelle (net) | C20: 1.193 | D20: 1.33 | E20: 1.504 | F20: 1.69 | G20: 1.832 | H20: 1.924 | I20: 2.015 | J20: 2.095 | K20: 2.218 | L20: 2.332 | M20: 2.449 | N20: 2.607 | O20: 2.746 | P20: 2.784 | Q20: 2.777 | R20: 2.719 | S20: 2.757 | T20: 2.792 | U20: 2.774 | V20: 2.759 | W20: 2.793 | X20: 2.882 | Y20: 3.034 | Z20: 3.179 | AA20: 3.186 | AB20: 3.184 | AC20: 3.241 | AD20: 3.312 | AE20: 3.369 | AF20: 3.491 | AG20: 3.482 | AH20: 3.287 | AI20: 3.164 | AJ20: 3.132 | AK20: 3.167 | AL20: 3.173 | AM20: 3.171 | AN20: 3.169 | AO20: 3.197 | AP20: 3.296 | AQ20: 3.474 | AR20: 3.678 | AS20: 3.888 | AT20: 4.472 | AU20: 5.129 | AV20: 5.803 | AW20: 6.439
A21: N1171N | B21: Recherche et développement (net) | C21: 0.889 | D21: 0.967 | E21: 1.087 | F21: 1.232 | G21: 1.348 | H21: 1.413 | I21: 1.449 | J21: 1.465 | K21: 1.472 | L21: 1.488 | M21: 1.517 | N21: 1.566 | O21: 1.611 | P21: 1.629 | Q21: 1.596 | R21: 1.536 | S21: 1.488 | T21: 1.454 | U21: 1.449 | V21: 1.44 | W21: 1.437 | X21: 1.466 | Y21: 1.498 | Z21: 1.495 | AA21: 1.471 | AB21: 1.447 | AC21: 1.449 | AD21: 1.434 | AE21: 1.412 | AF21: 1.417 | AG21: 1.414 | AH21: 1.353 | AI21: 1.297 | AJ21: 1.291 | AK21: 1.277 | AL21: 1.232 | AM21: 1.162 | AN21: 1.088 | AO21: 1.032 | AP21: 0.979 | AQ21: 0.953 | AR21: 0.917 | AS21: 0.874 | AT21: 0.845 | AU21: 0.822 | AV21: 0.805 | AW21: 0.788
A22: N1173N | B22: Logiciels et bases de données (net) | C22: 0.304 | D22: 0.363 | E22: 0.417 | F22: 0.458 | G22: 0.484 | H22: 0.511 | I22: 0.566 | J22: 0.629 | K22: 0.745 | L22: 0.843 | M22: 0.931 | N22: 1.04 | O22: 1.133 | P22: 1.153 | Q22: 1.178 | R22: 1.181 | S22: 1.267 | T22: 1.336 | U22: 1.323 | V22: 1.317 | W22: 1.354 | X22: 1.414 | Y22: 1.532 | Z22: 1.68 | AA22: 1.71 | AB22: 1.733 | AC22: 1.788 | AD22: 1.873 | AE22: 1.952 | AF22: 2.069 | AG22: 2.063 | AH22: 1.929 | AI22: 1.861 | AJ22: 1.838 | AK22: 1.883 | AL22: 1.935 | AM22: 2.005 | AN22: 2.078 | AO22: 2.162 | AP22: 2.314 | AQ22: 2.518 | AR22: 2.758 | AS22: 3.01 | AT22: 3.622 | AU22: 4.301 | AV22: 4.99 | AW22: 5.642
A23: N1174N | B23: Œuvres récréatives, littéraires ou artistiques originales (net) | C23: 0 | D23: 0 | E23: 0 | F23: 0 | G23: 0 | H23: 0 | I23: 0 | J23: 0.001 | K23: 0.001 | L23: 0.001 | M23: 0.001 | N23: 0.001 | O23: 0.002 | P23: 0.002 | Q23: 0.003 | R23: 0.002 | S23: 0.002 | T23: 0.002 | U23: 0.002 | V23: 0.002 | W23: 0.002 | X23: 0.002 | Y23: 0.004 | Z23: 0.004 | AA23: 0.005 | AB23: 0.004 | AC23: 0.004 | AD23: 0.005 | AE23: 0.005 | AF23: 0.005 | AG23: 0.005 | AH23: 0.005 | AI23: 0.006 | AJ23: 0.003 | AK23: 0.007 | AL23: 0.006 | AM23: 0.004 | AN23: 0.003 | AO23: 0.003 | AP23: 0.003 | AQ23: 0.003 | AR23: 0.003 | AS23: 0.004 | AT23: 0.005 | AU23: 0.007 | AV23: 0.009 | AW23: 0.009
A24: N12N | B24: Stocks par type de stocks (net) | C24: 8.086 | D24: 9.352 | E24: 10.957 | F24: 12.288 | G24: 12.668 | H24: 12.933 | I24: 12.688 | J24: 12.676 | K24: 12.034 | L24: 11.489 | M24: 11.81 | N24: 12.457 | O24: 12.731 | P24: 12.821 | Q24: 12.698 | R24: 12.262 | S24: 12.493 | T24: 13.558 | U24: 13.832 | V24: 14.131 | W24: 14.302 | X24: 14.624 | Y24: 14.228 | Z24: 13.572 | AA24: 13.159 | AB24: 12.642 | AC24: 12.854 | AD24: 13.257 | AE24: 14.376 | AF24: 16.239 | AG24: 15.901 | AH24: 13.437 | AI24: 13.525 | AJ24: 13.105 | AK24: 12.609 | AL24: 13.244 | AM24: 14.515 | AN24: 14.481 | AO24: 14.038 | AP24: 13.543 | AQ24: 14.16 | AR24: 13.314 | AS24: 12.675 | AT24: 14.947 | AU24: 18.71 | AV24: 18.146 | AW24: 17.7
A25: N13N | B25: Objets de valeur (net) | C25: 43.579 | D25: 49.805 | E25: 52.38 | F25: 50.012 | G25: 55.888 | H25: 66.738 | I25: 64.626 | J25: 59.145 | K25: 59.435 | L25: 61.525 | M25: 58.771 | N25: 53.346 | O25: 49.174 | P25: 46.296 | Q25: 44.798 | R25: 46.319 | S25: 45.291 | T25: 44.925 | U25: 45.384 | V25: 43.562 | W25: 45.052 | X25: 53.075 | Y25: 62.973 | Z25: 78.141 | AA25: 87.042 | AB25: 88.096 | AC25: 95.603 | AD25: 110.368 | AE25: 121.097 | AF25: 119.772 | AG25: 109.941 | AH25: 114.34 | AI25: 133.937 | AJ25: 139.227 | AK25: 135.065 | AL25: 132.926 | AM25: 134.004 | AN25: 132.25 | AO25: 134.265 | AP25: 142.875 | AQ25: 143.086 | AR25: 141.487 | AS25: 152.517 | AT25: 186.041 | AU25: 205.174 | AV25: 201.194 | AW25: 201.514
A26: N2N | B26: Actifs non financiers non produits (net) | C26: 292.247 | D26: 328.127 | E26: 361.523 | F26: 396.874 | G26: 414.164 | H26: 445.798 | I26: 445.58 | J26: 458.458 | K26: 487.256 | L26: 514.029 | M26: 577.002 | N26: 662.898 | O26: 723.212 | P26: 686.818 | Q26: 615.552 | R26: 572.699 | S26: 589.381 | T26: 535.778 | U26: 526.183 | V26: 513.067 | W26: 593.02 | X26: 784.173 | Y26: 970.043 | Z26: 1145.885 | AA26: 1447.105 | AB26: 1871.108 | AC26: 2447.055 | AD26: 3089.554 | AE26: 3546.503 | AF26: 3809.246 | AG26: 3405.406 | AH26: 3279.131 | AI26: 3711.518 | AJ26: 3860.736 | AK26: 3729.211 | AL26: 3604.976 | AM26: 3453.071 | AN26: 3470.559 | AO26: 3612.616 | AP26: 3815.053 | AQ26: 4024.322 | AR26: 4329.34 | AS26: 4714.469 | AT26: 5034.792 | AU26: 5167.898 | AV26: 4725.426 | AW26: 4605.961
A27: N21N | B27: Ressources naturelles (net) | C27: 279.183 | D27: 313.549 | E27: 345.364 | F27: 379.195 | G27: 395.107 | H27: 425.561 | I27: 424.463 | J27: 436.702 | K27: 465.043 | L27: 491.4 | M27: 553.424 | N27: 637.967 | O27: 697.744 | P27: 661.738 | Q27: 591.151 | R27: 548.815 | S27: 565.345 | T27: 511.284 | U27: 501.346 | V27: 487.878 | W27: 567.411 | X27: 758.05 | Y27: 943.345 | Z27: 1118.58 | AA27: 1418.485 | AB27: 1841.711 | AC27: 2416.045 | AD27: 3059.116 | AE27: 3525.981 | AF27: 3788.713 | AG27: 3386.388 | AH27: 3261.502 | AI27: 3695.155 | AJ27: 3845.538 | AK27: 3714.303 | AL27: 3590.349 | AM27: 3438.163 | AN27: 3456.628 | AO27: 3599.27 | AP27: 3802.258 | AQ27: 4012.237 | AR27: 4317.645 | AS27: 4703.203 | AT27: 5023.748 | AU27: 5157.269 | AV27: 4715.143 | AW27: 4596.012
A28: N211N | B28: Terrains (net) | C28: 279.183 | D28: 313.549 | E28: 345.364 | F28: 379.195 | G28: 395.107 | H28: 425.561 | I28: 424.463 | J28: 436.702 | K28: 465.043 | L28: 491.4 | M28: 553.424 | N28: 637.967 | O28: 697.744 | P28: 661.738 | Q28: 591.151 | R28: 548.815 | S28: 565.345 | T28: 511.284 | U28: 501.346 | V28: 487.878 | W28: 567.411 | X28: 758.05 | Y28: 943.345 | Z28: 1118.58 | AA28: 1418.485 | AB28: 1841.711 | AC28: 2416.045 | AD28: 3059.116 | AE28: 3525.981 | AF28: 3788.713 | AG28: 3386.388 | AH28: 3261.502 | AI28: 3695.155 | AJ28: 3845.538 | AK28: 3714.303 | AL28: 3590.349 | AM28: 3438.163 | AN28: 3456.628 | AO28: 3599.27 | AP28: 3802.258 | AQ28: 4012.237 | AR28: 4317.645 | AS28: 4703.203 | AT28: 5023.748 | AU28: 5157.269 | AV28: 4715.143 | AW28: 4596.012
A29: N2111N | B29: Terrains supportant des bâtiments et des ouvrages de génie civil (net) | C29: 128.64 | D29: 151.127 | E29: 175.616 | F29: 199.454 | G29: 207.615 | H29: 230.612 | I29: 229.598 | J29: 249.632 | K29: 281.169 | L29: 325.365 | M29: 397.403 | N29: 478.081 | O29: 518.867 | P29: 496.361 | Q29: 441.469 | R29: 409.912 | S29: 429.935 | T29: 388.362 | U29: 381.513 | V29: 371.815 | W29: 442.4 | X29: 614.149 | Y29: 779.89 | Z29: 940.179 | AA29: 1211.974 | AB29: 1599.404 | AC29: 2131.453 | AD29: 2730.241 | AE29: 3166.355 | AF29: 3406.434 | AG29: 3032.693 | AH29: 2927.326 | AI29: 3321.371 | AJ29: 3451.359 | AK29: 3325.293 | AL29: 3208.688 | AM29: 3061.784 | AN29: 3077.736 | AO29: 3199.167 | AP29: 3377.141 | AQ29: 3562.891 | AR29: 3811.713 | AS29: 4136.415 | AT29: 4409.369 | AU29: 4526.17 | AV29: 4125.316 | AW29: 3992.805
A30: N2112N | B30: Terrains cultivés (net) | C30: 108.161 | D30: 113.866 | E30: 115.719 | F30: 121.744 | G30: 127.08 | H30: 131.072 | I30: 131.384 | J30: 126.043 | K30: 123.524 | L30: 110.95 | M30: 104.062 | N30: 104.239 | O30: 117.094 | P30: 108.667 | Q30: 98.266 | R30: 90.24 | S30: 87.627 | T30: 81.806 | U30: 79.182 | V30: 76.76 | W30: 80.286 | X30: 86.401 | Y30: 92.277 | Z30: 95.815 | AA30: 105.672 | AB30: 116.873 | AC30: 128.165 | AD30: 136.998 | AE30: 139.318 | AF30: 147.135 | AG30: 138.88 | AH30: 125.56 | AI30: 133.664 | AJ30: 140.576 | AK30: 139.727 | AL30: 140.122 | AM30: 136.854 | AN30: 136.038 | AO30: 140.307 | AP30: 144.188 | AQ30: 147.045 | AR30: 167.626 | AS30: 180.821 | AT30: 190.711 | AU30: 194.808 | AV30: 181.371 | AW30: 185.892
A31: N2113N | B31: Terrains et plans d’eau de loisirs (net)
A32: N2119N | B32: Autres terrains et plans d’eau (net) | C32: 42.382 | D32: 48.556 | E32: 54.029 | F32: 57.997 | G32: 60.411 | H32: 63.877 | I32: 63.482 | J32: 61.027 | K32: 60.35 | L32: 55.085 | M32: 51.96 | N32: 55.648 | O32: 61.783 | P32: 56.71 | Q32: 51.417 | R32: 48.664 | S32: 47.782 | T32: 41.116 | U32: 40.651 | V32: 39.304 | W32: 44.726 | X32: 57.501 | Y32: 71.178 | Z32: 82.587 | AA32: 100.84 | AB32: 125.435 | AC32: 156.427 | AD32: 191.877 | AE32: 220.308 | AF32: 235.145 | AG32: 214.814 | AH32: 208.616 | AI32: 240.119 | AJ32: 253.603 | AK32: 249.283 | AL32: 241.539 | AM32: 239.525 | AN32: 242.854 | AO32: 259.797 | AP32: 280.93 | AQ32: 302.302 | AR32: 338.306 | AS32: 385.968 | AT32: 423.668 | AU32: 436.292 | AV32: 408.457 | AW32: 417.316
A33: N212N | B33: Réserves de minerais et de produits énergétiques (net)
A34: N214N | B34: Ressources en eau (net)
A35: N22N | B35: Contrats, baux et licences (net)
A36: N23N | B36: Achats moins ventes de fonds commerciaux et d’autres actifs commerciaux (net) | C36: 13.065 | D36: 14.578 | E36: 16.159 | F36: 17.68 | G36: 19.057 | H36: 20.237 | I36: 21.116 | J36: 21.756 | K36: 22.213 | L36: 22.629 | M36: 23.578 | N36: 24.93 | O36: 25.468 | P36: 25.08 | Q36: 24.401 | R36: 23.884 | S36: 24.037 | T36: 24.494 | U36: 24.838 | V36: 25.189 | W36: 25.61 | X36: 26.124 | Y36: 26.698 | Z36: 27.305 | AA36: 28.619 | AB36: 29.397 | AC36: 31.01 | AD36: 30.437 | AE36: 20.522 | AF36: 20.533 | AG36: 19.019 | AH36: 17.629 | AI36: 16.363 | AJ36: 15.199 | AK36: 14.907 | AL36: 14.627 | AM36: 14.907 | AN36: 13.93 | AO36: 13.346 | AP36: 12.795 | AQ36: 12.085 | AR36: 11.695 | AS36: 11.266 | AT36: 11.045 | AU36: 10.629 | AV36: 10.283 | AW36: 9.948
A38: F | B38: Total des actifs financiers | T38: 1898.591 | U38: 2035.09 | V38: 2180.133 | W38: 2323.332 | X38: 2620.063 | Y38: 2710.446 | Z38: 2643.19 | AA38: 2658.662 | AB38: 2841.549 | AC38: 3006.153 | AD38: 3241.689 | AE38: 3612.911 | AF38: 3819.032 | AG38: 3544.767 | AH38: 3816.727 | AI38: 4077.863 | AJ38: 4117.697 | AK38: 4278.938 | AL38: 4463.766 | AM38: 4663.605 | AN38: 4888.71 | AO38: 5228.665 | AP38: 5469.428 | AQ38: 5428.446 | AR38: 5926.698 | AS38: 6223.352 | AT38: 6728.711 | AU38: 6393.79 | AV38: 6806.904 | AW38: 6977.156 | AY38: =(AW38-AT38)/AT38*100 -> 3.6923119
A39: F1 | B39: Or monétaire et droits de tirage spéciaux (DTS)
A40: F2 | B40: Numéraire et dépôts | T40: 645.421 | U40: 676.704 | V40: 717.746 | W40: 749.68 | X40: 780.74 | Y40: 772.519 | Z40: 791.219 | AA40: 839.878 | AB40: 878.699 | AC40: 914.625 | AD40: 953.747 | AE40: 973.287 | AF40: 1014.523 | AG40: 1056.051 | AH40: 1077.832 | AI40: 1110.547 | AJ40: 1166.983 | AK40: 1213.712 | AL40: 1246.982 | AM40: 1263.943 | AN40: 1307.157 | AO40: 1364.229 | AP40: 1423 | AQ40: 1492.054 | AR40: 1574.227 | AS40: 1728.925 | AT40: 1843.063 | AU40: 1930.408 | AV40: 1982.019 | AW40: 2012.321 | AY40: =(AW40-AT40)/AT40*100 -> 9.1835168
A41: F3 | B41: Titres de créance | T41: 109.351 | U41: 101.379 | V41: 88.386 | W41: 87.657 | X41: 74.113 | Y41: 90.526 | Z41: 95.263 | AA41: 82.623 | AB41: 70.709 | AC41: 68.41 | AD41: 69.148 | AE41: 63.983 | AF41: 68.046 | AG41: 71.658 | AH41: 83.423 | AI41: 76.493 | AJ41: 75.685 | AK41: 83.962 | AL41: 83.098 | AM41: 72.428 | AN41: 59.989 | AO41: 54.308 | AP41: 47.334 | AQ41: 40.726 | AR41: 39.341 | AS41: 34.369 | AT41: 32.95 | AU41: 34.653 | AV41: 45.438 | AW41: 50.208
A42: F4 | B42: Crédits | T42: 26.59 | U42: 26.831 | V42: 33.974 | W42: 24.579 | X42: 19.178 | Y42: 20.765 | Z42: 20.455 | AA42: 18.915 | AB42: 21.235 | AC42: 19.503 | AD42: 20.144 | AE42: 23.292 | AF42: 22.85 | AG42: 32.324 | AH42: 25.822 | AI42: 26.49 | AJ42: 27.78 | AK42: 28.604 | AL42: 29.362 | AM42: 30.392 | AN42: 31.413 | AO42: 10.238 | AP42: 10.531 | AQ42: 10.638 | AR42: 10.6 | AS42: 11.005 | AT42: 11.006 | AU42: 10.862 | AV42: 11.656 | AW42: 11.289
A43: F5 | B43: Actions et parts de fonds d’investissement | T43: 657.747 | U43: 703.686 | V43: 733.313 | W43: 797.539 | X43: 976.446 | Y43: 982.231 | Z43: 844.942 | AA43: 774.896 | AB43: 858.671 | AC43: 921.235 | AD43: 995.607 | AE43: 1197.463 | AF43: 1239.899 | AG43: 887.278 | AH43: 964.384 | AI43: 1028.548 | AJ43: 963.725 | AK43: 1076.394 | AL43: 1132.675 | AM43: 1214.945 | AN43: 1329.665 | AO43: 1398.176 | AP43: 1534.772 | AQ43: 1447.947 | AR43: 1658.202 | AS43: 1711.723 | AT43: 2036.19 | AU43: 1886.689 | AV43: 2106.629 | AW43: 2136.859 | AY43: =(AW43-AT43)/AT43*100 -> 4.9439885
A44: F511 | B44: dont Actions cotées | T44: 94.076 | U44: 111.575 | V44: 117.566 | W44: 146.796 | X44: 180.564 | Y44: 196.99 | Z44: 157.18 | AA44: 110.997 | AB44: 130.292 | AC44: 138.891 | AD44: 180.702 | AE44: 211.958 | AF44: 204.237 | AG44: 110.667 | AH44: 141.992 | AI44: 161.552 | AJ44: 132.484 | AK44: 150.733 | AL44: 175.623 | AM44: 184.091 | AN44: 212.715 | AO44: 217.493 | AP44: 240.007 | AQ44: 215.191 | AR44: 265.463 | AS44: 274.713 | AT44: 329.96 | AU44: 286.355 | AV44: 321.651 | AW44: 317.695
A45: F6 | B45: Systèmes d’assurance, de pension et de garanties standard | T45: 378.764 | U45: 442.279 | V45: 517.246 | W45: 574.403 | X45: 650.14 | Y45: 711.372 | Z45: 756.783 | AA45: 790.369 | AB45: 856.291 | AC45: 945.314 | AD45: 1051.26 | AE45: 1200.382 | AF45: 1296.254 | AG45: 1299.29 | AH45: 1407.437 | AI45: 1511.217 | AJ45: 1534.6 | AK45: 1587.97 | AL45: 1654.397 | AM45: 1733.12 | AN45: 1798.915 | AO45: 2022.219 | AP45: 2058.118 | AQ45: 2030.94 | AR45: 2208.708 | AS45: 2269.341 | AT45: 2302.803 | AU45: 2011.467 | AV45: 2113.422 | AW45: 2195.394 | AY45: =(AW45-AT45)/AT45*100 -> -4.6642722
A46: F7 | B46: Produits financiers dérivés et options sur titres des salariés | T46: 0 | U46: 0 | V46: 0 | W46: 0 | X46: 0 | Y46: 0 | Z46: 0 | AA46: 0 | AB46: 0 | AC46: 0 | AD46: 0 | AE46: 0 | AF46: 0 | AG46: 0 | AH46: 0 | AI46: 0 | AJ46: 0 | AK46: 0 | AL46: 0 | AM46: 0.004 | AN46: 0.004 | AO46: 0.038 | AP46: 0.036 | AQ46: 0.13 | AR46: 0.187 | AS46: 0.292 | AT46: 0.319 | AU46: 0.296 | AV46: 0.138 | AW46: 0.06
A47: F8 | B47: Autres comptes à recevoir / à payer | T47: 80.719 | U47: 84.211 | V47: 89.468 | W47: 89.474 | X47: 119.445 | Y47: 133.035 | Z47: 134.529 | AA47: 151.98 | AB47: 155.946 | AC47: 137.066 | AD47: 151.784 | AE47: 154.505 | AF47: 177.46 | AG47: 198.166 | AH47: 257.829 | AI47: 324.567 | AJ47: 348.924 | AK47: 288.296 | AL47: 317.251 | AM47: 348.773 | AN47: 361.567 | AO47: 379.458 | AP47: 395.637 | AQ47: 406.011 | AR47: 435.432 | AS47: 467.697 | AT47: 502.38 | AU47: 519.417 | AV47: 547.6 | AW47: 571.026
A49: FN | B49: Total des actifs | T49: 4080.46 | U49: 4265.775 | V49: 4451.132 | W49: 4723.731 | X49: 5275.403 | Y49: 5640.09 | Z49: 5858.806 | AA49: 6282.392 | AB49: 7012.325 | AC49: 7903.927 | AD49: 8942.447 | AE49: 9941.194 | AF49: 10588.258 | AG49: 10033.819 | AH49: 10261.867 | AI49: 11090.761 | AJ49: 11403.986 | AK49: 11509.824 | AL49: 11649.426 | AM49: 11769.966 | AN49: 12056.421 | AO49: 12625.638 | AP49: 13194.813 | AQ49: 13488.12 | AR49: 14402.515 | AS49: 15251.393 | AT49: 16465.049 | AU49: 16628.814 | AV49: 16738.395 | AW49: 16844.934
A52: F | B52: Total des passifs financiers | T52: 516.783 | U52: 542.616 | V52: 577.153 | W52: 598.538 | X52: 644.732 | Y52: 668.519 | Z52: 711.263 | AA52: 770.375 | AB52: 823.35 | AC52: 859.461 | AD52: 956.508 | AE52: 1060.033 | AF52: 1171.897 | AG52: 1226.437 | AH52: 1317.183 | AI52: 1404.344 | AJ52: 1450.502 | AK52: 1419.812 | AL52: 1445.495 | AM52: 1478.924 | AN52: 1530.124 | AO52: 1576.75 | AP52: 1658.802 | AQ52: 1733.905 | AR52: 1797.089 | AS52: 1878.82 | AT52: 1968.324 | AU52: 2058.677 | AV52: 2086.383 | AW52: 2091.417
A53: F1 | B53: Or monétaire et droits de tirage spéciaux (DTS)
A54: F2 | B54: Numéraire et dépôts | T54: 0 | U54: 0 | V54: 0 | W54: 0.002 | X54: 0 | Y54: 0 | Z54: 0 | AA54: 0 | AB54: 0 | AC54: 0 | AD54: 0 | AE54: 0 | AF54: 0 | AG54: 0 | AH54: 0 | AI54: 0 | AJ54: 0 | AK54: 0 | AL54: 0 | AM54: 0 | AN54: 0 | AO54: 0 | AP54: 0 | AQ54: 0 | AR54: 0 | AS54: 0 | AT54: 0 | AU54: 0 | AV54: 0 | AW54: 0
A55: F3 | B55: Titres de créance
A56: F4 | B56: Crédits | T56: 410.651 | U56: 423.24 | V56: 439.797 | W56: 446.932 | X56: 476.061 | Y56: 505.455 | Z56: 531.679 | AA56: 561.67 | AB56: 600.384 | AC56: 655.771 | AD56: 730.999 | AE56: 812.593 | AF56: 901.222 | AG56: 968.74 | AH56: 1015.389 | AI56: 1066.821 | AJ56: 1124.295 | AK56: 1147.971 | AL56: 1169.634 | AM56: 1197.928 | AN56: 1233.426 | AO56: 1277.98 | AP56: 1342.024 | AQ56: 1414.081 | AR56: 1496.558 | AS56: 1559.774 | AT56: 1645.555 | AU56: 1728.037 | AV56: 1747.765 | AW56: 1748.562
A57: F5 | B57: Actions et parts de fonds d’investissement
A58: F511 | B58: dont Actions cotées
A59: F6 | B59: Systèmes d’assurance, de pension et de garanties standard
A60: F7 | B60: Produits financiers dérivés et options sur titres des salariés | T60: 0 | U60: 0 | V60: 0 | W60: 0 | X60: 0 | Y60: 0 | Z60: 0 | AA60: 0 | AB60: 0 | AC60: 0 | AD60: 0 | AE60: 0 | AF60: 0 | AG60: 0 | AH60: 0 | AI60: 0 | AJ60: 0 | AK60: 0 | AL60: 0 | AM60: 0.011 | AN60: 0.009 | AO60: 0.051 | AP60: 0.056 | AQ60: 0.198 | AR60: 0.213 | AS60: 0.305 | AT60: 0.354 | AU60: 0.653 | AV60: 0.282 | AW60: 0.504
A61: F8 | B61: Autres comptes à recevoir / à payer | T61: 106.132 | U61: 119.376 | V61: 137.356 | W61: 151.605 | X61: 168.671 | Y61: 163.064 | Z61: 179.584 | AA61: 208.705 | AB61: 222.966 | AC61: 203.69 | AD61: 225.51 | AE61: 247.44 | AF61: 270.675 | AG61: 257.697 | AH61: 301.794 | AI61: 337.524 | AJ61: 326.206 | AK61: 271.841 | AL61: 275.861 | AM61: 280.985 | AN61: 296.689 | AO61: 298.719 | AP61: 316.723 | AQ61: 319.627 | AR61: 300.317 | AS61: 318.74 | AT61: 322.415 | AU61: 329.988 | AV61: 338.336 | AW61: 342.351
A63: B90 | B63: Valeur nette | T63: 3563.677 | U63: 3723.159 | V63: 3873.979 | W63: 4125.193 | X63: 4630.671 | Y63: 4971.572 | Z63: 5147.543 | AA63: 5512.017 | AB63: 6188.975 | AC63: 7044.466 | AD63: 7985.939 | AE63: 8881.161 | AF63: 9416.361 | AG63: 8807.382 | AH63: 8944.684 | AI63: 9686.417 | AJ63: 9953.485 | AK63: 10090.013 | AL63: 10203.931 | AM63: 10291.042 | AN63: 10526.296 | AO63: 11048.888 | AP63: 11536.01 | AQ63: 11754.215 | AR63: 12605.426 | AS63: 13372.573 | AT63: 14496.725 | AU63: 14570.136 | AV63: 14652.012 | AW63: 14753.517
A65: Source : Comptes nationaux annuels (base 2020) | B65: Actifs net non financiers | T65: =T6-T52 -> 1665.086 | U65: =U6-U52 -> 1688.069 | V65: =V6-V52 -> 1693.846 | W65: =W6-W52 -> 1801.861 | X65: =X6-X52 -> 2010.608 | Y65: =Y6-Y52 -> 2261.125 | Z65: =Z6-Z52 -> 2504.353 | AA65: =AA6-AA52 -> 2853.355 | ... AW65: =AW6-AW52 -> 7776.361
B66: Actifs financiers | T66: =T38 -> 1898.591 | U66: =U38 -> 2035.09 | V66: =V38 -> 2180.133 | W66: =W38 -> 2323.332 | X66: =X38 -> 2620.063 | Y66: =Y38 -> 2710.446 | Z66: =Z38 -> 2643.19 | AA66: =AA38 -> 2658.662 | ... AW66: =AW38 -> 6977.156
B68: En % du RDB
B69: Actifs net non financiers | T69: =T65/T72 -> 2.2406992 | U69: =U65/U72 -> 2.2138349 | V69: =V65/V72 -> 2.1614028 | W69: =W65/W72 -> 2.225836 | X69: =X65/X72 -> 2.4181424 | Y69: =Y65/Y72 -> 2.5643781 | Z69: =Z65/Z72 -> 2.7014159 | AA69: =AA65/AA72 -> 2.9532089 | ... AW69: =AW65/AW72 -> 4.1783951
B70: Actifs financiers | T70: =T66/T72 -> 2.5549259 | U70: =U66/U72 -> 2.668939 | V70: =V66/V72 -> 2.7819209 | W70: =W66/W72 -> 2.8700083 | X70: =X66/X72 -> 3.1511291 | Y70: =Y66/Y72 -> 3.0739602 | Z70: =Z66/Z72 -> 2.8511777 | AA70: =AA66/AA72 -> 2.7517026 | ... AW70: =AW66/AW72 -> 3.7489662
B72: RDB | C72: 223.681 | D72: 249.841 | E72: 283.779 | F72: 327.33 | G72: 373.165 | H72: 408.996 | I72: 437.228 | J72: 468.874 | K72: 496.607 | L72: 520.65 | M72: 553.09 | N72: 593.353 | O72: 634.505 | P72: 660.275 | Q72: 693.118 | R72: 707.974 | S72: 718.584 | T72: 743.11 | U72: 762.509 | V72: 783.679 | W72: 809.521 | X72: 831.468 | Y72: 881.744 | Z72: 927.052 | AA72: 966.188 | AB72: 992.894 | AC72: 1035.68 | AD72: 1071.148 | AE72: 1128.433 | AF72: 1186.758 | AG72: 1225.524 | AH72: 1227.942 | AI72: 1260.979 | AJ72: 1288.225 | AK72: 1301.809 | AL72: 1296.566 | AM72: 1315.37 | AN72: 1330.905 | AO72: 1353.53 | AP72: 1387.38 | AQ72: 1427.117 | AR72: 1475.704 | AS72: 1490.321 | AT72: 1562.529 | AU72: 1646.103 | AV72: 1775.835 | AW72: 1861.088
T73: =(T72-S72)/S72*100 -> 3.4131013
T76: =SUM(T69:T70) -> 4.7956251 | U76: =SUM(U69:U70) -> 4.8827738 | V76: =SUM(V69:V70) -> 4.9433237 | W76: =SUM(W69:W70) -> 5.0958443 | X76: =SUM(X69:X70) -> 5.5692715

Sheet Variations
A1: 8.220 – Comptes de patrimoine et de variation de patrimoine des ménages (S14)
A2: Unité : Milliard d'euros
B4: Annuel | C4: 1978 | D4: 1979 | E4: 1979 | F4: 1979 | G4: 1979 | H4: 1979 | I4: 1980 | J4: 1980 | K4: 1980 | L4: 1980 | M4: 1980 | N4: 1981 | O4: 1981 | P4: 1981 | Q4: 1981 | R4: 1981 | S4: 1982 | T4: 1982 | U4: 1982 | V4: 1982 | W4: 1982 | X4: 1983 | Y4: 1983 | Z4: 1983 | AA4: 1983 | AB4: 1983 | AC4: 1984 | AD4: 1984 | AE4: 1984 | AF4: 1984 | AG4: 1984 | AH4: 1985 | AI4: 1985 | AJ4: 1985 | AK4: 1985 | AL4: 1985 | AM4: 1986 | AN4: 1986 | AO4: 1986 | AP4: 1986 | AQ4: 1986 | AR4: 1987 | AS4: 1987 | AT4: 1987 | AU4: 1987 | AV4: 1987 | AW4: 1988 | AX4: 1988 | AY4: 1988 | AZ4: 1988 | BA4: 1988 | BB4: 1989 | BC4: 1989 | BD4: 1989 | BE4: 1989 | BF4: 1989 | BG4: 1990 | BH4: 1990 | BI4: 1990 | BJ4: 1990 | BK4: 1990 | BL4: 1991 | BM4: 1991 | BN4: 1991 | BO4: 1991 | BP4: 1991 | BQ4: 1992 | BR4: 1992 | BS4: 1992 | BT4: 1992 | BU4: 1992 | BV4: 1993 | BW4: 1993 | BX4: 1993 | BY4: 1993 | BZ4: 1993 | CA4: 1994 | CB4: 1994 | CC4: 1994 | CD4: 1994 | CE4: 1994 | CF4: 1995 | CG4: 1995 | CH4: 1995 | CI4: 1995 | CJ4: 1995 | CK4: 1996 | CL4: 1996 | CM4: 1996 | CN4: 1996 | CO4: 1996 | CP4: 1997 | CQ4: 1997 | CR4: 1997 | CS4: 1997 | CT4: 1997 | CU4: 1998 | CV4: 1998 | CW4: 1998 | CX4: 1998 | CY4: 1998 | CZ4: 1999 | DA4: 1999 | DB4: 1999 | DC4: 1999 | DD4: 1999 | DE4: 2000 | DF4: 2000 | DG4: 2000 | DH4: 2000 | DI4: 2000 | DJ4: 2001 | DK4: 2001 | DL4: 2001 | DM4: 2001 | DN4: 2001 | DO4: 2002 | DP4: 2002 | DQ4: 2002 | DR4: 2002 | DS4: 2002 | DT4: 2003 | DU4: 2003 | DV4: 2003 | DW4: 2003 | DX4: 2003 | DY4: 2004 | DZ4: 2004 | EA4: 2004 | EB4: 2004 | EC4: 2004 | ED4: 2005 | EE4: 2005 | EF4: 2005 | EG4: 2005 | EH4: 2005 | EI4: 2006 | EJ4: 2006 | EK4: 2006 | EL4: 2006 | EM4: 2006 | EN4: 2007 | EO4: 2007 | EP4: 2007 | EQ4: 2007 | ER4: 2007 | ES4: 2008 | ET4: 2008 | EU4: 2008 | EV4: 2008 | EW4: 2008 | EX4: 2009 | EY4: 2009 | EZ4: 2009 | FA4: 2009 | FB4: 2009 | FC4: 2010 | FD4: 2010 | FE4: 2010 | FF4: 2010 | FG4: 2010 | FH4: 2011 | FI4: 2011 | FJ4: 2011 | FK4: 2011 | FL4: 2011 | FM4: 2012 | FN4: 2012 | FO4: 2012 | FP4: 2012 | FQ4: 2012 | FR4: 2013 | FS4: 2013 | FT4: 2013 | FU4: 2013 | FV4: 2013 | FW4: 2014 | FX4: 2014 | FY4: 2014 | FZ4: 2014 | GA4: 2014 | GB4: 2015 | GC4: 2015 | GD4: 2015 | GE4: 2015 | GF4: 2015 | GG4: 2016 | GH4: 2016 | GI4: 2016 | GJ4: 2016 | GK4: 2016 | GL4: 2017 | GM4: 2017 | GN4: 2017 | GO4: 2017 | GP4: 2017 | GQ4: 2018 | GR4: 2018 | GS4: 2018 | GT4: 2018 | GU4: 2018 | GV4: 2019 | GW4: 2019 | GX4: 2019 | GY4: 2019 | GZ4: 2019 | HA4: 2020 | HB4: 2020 | HC4: 2020 | HD4: 2020 | HE4: 2020 | HF4: 2021 | HG4: 2021 | HH4: 2021 | HI4: 2021 | HJ4: 2021 | HK4: 2022 | HL4: 2022 | HM4: 2022 | HN4: 2022 | HO4: 2022 | HP4: 2023 | HQ4: 2023 | HR4: 2023 | HS4: 2023 | HT4: 2023 | HU4: 2024 | HV4: 2024 | HW4: 2024 | HX4: 2024 | HY4: 2024
B5: Opération comptable | C5: Patrimoine en fin d'année | D5: Flux d’actifs | E5: Consommation de capital fixe | F5: Réévaluation | G5: Autres changements de volume et ajustements | H5: Patrimoine en fin d'année | I5: Flux d’actifs | J5: Consommation de capital fixe | K5: Réévaluation | L5: Autres changements de volume et ajustements | M5: Patrimoine en fin d'année | N5: Flux d’actifs | O5: Consommation de capital fixe | P5: Réévaluation | Q5: Autres changements de volume et ajustements | R5: Patrimoine en fin d'année | S5: Flux d’actifs | T5: Consommation de capital fixe | U5: Réévaluation | V5: Autres changements de volume et ajustements | W5: Patrimoine en fin d'année | X5: Flux d’actifs | Y5: Consommation de capital fixe | Z5: Réévaluation | AA5: Autres changements de volume et ajustements | AB5: Patrimoine en fin d'année | AC5: Flux d’actifs | AD5: Consommation de capital fixe | AE5: Réévaluation | AF5: Autres changements de volume et ajustements | AG5: Patrimoine en fin d'année | AH5: Flux d’actifs | AI5: Consommation de capital fixe | AJ5: Réévaluation | AK5: Autres changements de volume et ajustements | AL5: Patrimoine en fin d'année | AM5: Flux d’actifs | AN5: Consommation de capital fixe | AO5: Réévaluation | AP5: Autres changements de volume et ajustements | AQ5: Patrimoine en fin d'année | AR5: Flux d’actifs | AS5: Consommation de capital fixe | AT5: Réévaluation | AU5: Autres changements de volume et ajustements | AV5: Patrimoine en fin d'année | AW5: Flux d’actifs | AX5: Consommation de capital fixe | AY5: Réévaluation | AZ5: Autres changements de volume et ajustements | BA5: Patrimoine en fin d'année | BB5: Flux d’actifs | BC5: Consommation de capital fixe | BD5: Réévaluation | BE5: Autres changements de volume et ajustements | BF5: Patrimoine en fin d'année | BG5: Flux d’actifs | BH5: Consommation de capital fixe | BI5: Réévaluation | BJ5: Autres changements de volume et ajustements | BK5: Patrimoine en fin d'année | BL5: Flux d’actifs | BM5: Consommation de capital fixe | BN5: Réévaluation | BO5: Autres changements de volume et ajustements | BP5: Patrimoine en fin d'année | BQ5: Flux d’actifs | BR5: Consommation de capital fixe | BS5: Réévaluation | BT5: Autres changements de volume et ajustements | BU5: Patrimoine en fin d'année | BV5: Flux d’actifs | BW5: Consommation de capital fixe | BX5: Réévaluation | BY5: Autres changements de volume et ajustements | BZ5: Patrimoine en fin d'année | CA5: Flux d’actifs | CB5: Consommation de capital fixe | CC5: Réévaluation | CD5: Autres changements de volume et ajustements | CE5: Patrimoine en fin d'année | CF5: Flux d’actifs | CG5: Consommation de capital fixe | CH5: Réévaluation | CI5: Autres changements de volume et ajustements | CJ5: Patrimoine en fin d'année | CK5: Flux d’actifs | CL5: Consommation de capital fixe | CM5: Réévaluation | CN5: Autres changements de volume et ajustements | CO5: Patrimoine en fin d'année | CP5: Flux d’actifs | CQ5: Consommation de capital fixe | CR5: Réévaluation | CS5: Autres changements de volume et ajustements | CT5: Patrimoine en fin d'année | CU5: Flux d’actifs | CV5: Consommation de capital fixe | CW5: Réévaluation | CX5: Autres changements de volume et ajustements | CY5: Patrimoine en fin d'année | CZ5: Flux d’actifs | DA5: Consommation de capital fixe | DB5: Réévaluation | DC5: Autres changements de volume et ajustements | DD5: Patrimoine en fin d'année | DE5: Flux d’actifs | DF5: Consommation de capital fixe | DG5: Réévaluation | DH5: Autres changements de volume et ajustements | DI5: Patrimoine en fin d'année | DJ5: Flux d’actifs | DK5: Consommation de capital fixe | DL5: Réévaluation | DM5: Autres changements de volume et ajustements | DN5: Patrimoine en fin d'année | DO5: Flux d’actifs | DP5: Consommation de capital fixe | DQ5: Réévaluation | DR5: Autres changements de volume et ajustements | DS5: Patrimoine en fin d'année | DT5: Flux d’actifs | DU5: Consommation de capital fixe | DV5: Réévaluation | DW5: Autres changements de volume et ajustements | DX5: Patrimoine en fin d'année | DY5: Flux d’actifs | DZ5: Consommation de capital fixe | EA5: Réévaluation | EB5: Autres changements de volume et ajustements | EC5: Patrimoine en fin d'année | ED5: Flux d’actifs | EE5: Consommation de capital fixe | EF5: Réévaluation | EG5: Autres changements de volume et ajustements | EH5: Patrimoine en fin d'année | EI5: Flux d’actifs | EJ5: Consommation de capital fixe | EK5: Réévaluation | EL5: Autres changements de volume et ajustements | EM5: Patrimoine en fin d'année | EN5: Flux d’actifs | EO5: Consommation de capital fixe | EP5: Réévaluation | EQ5: Autres changements de volume et ajustements | ER5: Patrimoine en fin d'année | ES5: Flux d’actifs | ET5: Consommation de capital fixe | EU5: Réévaluation | EV5: Autres changements de volume et ajustements | EW5: Patrimoine en fin d'année | EX5: Flux d’actifs | EY5: Consommation de capital fixe | EZ5: Réévaluation | FA5: Autres changements de volume et ajustements | FB5: Patrimoine en fin d'année | FC5: Flux d’actifs | FD5: Consommation de capital fixe | FE5: Réévaluation | FF5: Autres changements de volume et ajustements | FG5: Patrimoine en fin d'année | FH5: Flux d’actifs | FI5: Consommation de capital fixe | FJ5: Réévaluation | FK5: Autres changements de volume et ajustements | FL5: Patrimoine en fin d'année | FM5: Flux d’actifs | FN5: Consommation de capital fixe | FO5: Réévaluation | FP5: Autres changements de volume et ajustements | FQ5: Patrimoine en fin d'année | FR5: Flux d’actifs | FS5: Consommation de capital fixe | FT5: Réévaluation | FU5: Autres changements de volume et ajustements | FV5: Patrimoine en fin d'année | FW5: Flux d’actifs | FX5: Consommation de capital fixe | FY5: Réévaluation | FZ5: Autres changements de volume et ajustements | GA5: Patrimoine en fin d'année | GB5: Flux d’actifs | GC5: Consommation de capital fixe | GD5: Réévaluation | GE5: Autres changements de volume et ajustements | GF5: Patrimoine en fin d'année | GG5: Flux d’actifs | GH5: Consommation de capital fixe | GI5: Réévaluation | GJ5: Autres changements de volume et ajustements | GK5: Patrimoine en fin d'année | GL5: Flux d’actifs | GM5: Consommation de capital fixe | GN5: Réévaluation | GO5: Autres changements de volume et ajustements | GP5: Patrimoine en fin d'année | GQ5: Flux d’actifs | GR5: Consommation de capital fixe | GS5: Réévaluation | GT5: Autres changements de volume et ajustements | GU5: Patrimoine en fin d'année | GV5: Flux d’actifs | GW5: Consommation de capital fixe | GX5: Réévaluation | GY5: Autres changements de volume et ajustements | GZ5: Patrimoine en fin d'année | HA5: Flux d’actifs | HB5: Consommation de capital fixe | HC5: Réévaluation | HD5: Autres changements de volume et ajustements | HE5: Patrimoine en fin d'année | HF5: Flux d’actifs | HG5: Consommation de capital fixe | HH5: Réévaluation | HI5: Autres changements de volume et ajustements | HJ5: Patrimoine en fin d'année | HK5: Flux d’actifs | HL5: Consommation de capital fixe | HM5: Réévaluation | HN5: Autres changements de volume et ajustements | HO5: Patrimoine en fin d'année | HP5: Flux d’actifs | HQ5: Consommation de capital fixe | HR5: Réévaluation | HS5: Autres changements de volume et ajustements | HT5: Patrimoine en fin d'année | HU5: Flux d’actifs | HV5: Consommation de capital fixe | HW5: Réévaluation | HX5: Autres changements de volume et ajustements | HY5: Patrimoine en fin d'année
A6: INSTR_ASSET | B6: Classe d'actifs passifs
A7: N | B7: Total des actifs non financiers | C7: 778.641 | D7: 35.59 | E7: -12.997 | F7: 92.168 | G7: 6.509 | H7: 899.909 | I7: 40.86 | J7: -15.577 | K7: 93.994 | L7: 6.866 | M7: 1026.051 | N7: 42.3 | O7: -17.875 | P7: 99.091 | Q7: 5.032 | R7: 1154.598 | S7: 44.939 | T7: -20.493 | U7: 92.418 | V7: 3.072 | W7: 1274.534 | X7: 46.142 | Y7: -22.4 | Z7: 94.169 | AA7: 6.8 | AB7: 1399.243 | AC7: 47.903 | AD7: -23.945 | AE7: 37.593 | AF7: 5.937 | AG7: 1466.728 | AH7: 47.04 | AI7: -24.901 | AJ7: 43.23 | AK7: 0.229 | AL7: 1532.327 | AM7: 49.945 | AN7: -25.942 | AO7: 64.062 | AP7: 0.381 | AQ7: 1620.772 | AR7: 55.096 | AS7: -27.204 | AT7: 76.676 | AU7: -8.864 | AV7: 1716.474 | AW7: 60.172 | AX7: -28.902 | AY7: 102.356 | AZ7: -1.862 | BA7: 1848.238 | BB7: 66.689 | BC7: -30.882 | BD7: 117.463 | BE7: 4.078 | BF7: 2005.584 | BG7: 67.538 | BH7: -32.977 | BI7: 90.676 | BJ7: 14.952 | BK7: 2145.773 | BL7: 64.255 | BM7: -35.037 | BN7: -5.962 | BO7: 2.088 | BP7: 2171.116 | BQ7: 61.312 | BR7: -35.734 | BS7: -57.999 | BT7: 0.805 | BU7: 2139.5 | BV7: 58.797 | BW7: -36.024 | BX7: -31.442 | BY7: 2.68 | BZ7: 2133.511 | CA7: 62.894 | CB7: -36.485 | CC7: 23.352 | CD7: 3.587 | CE7: 2186.859 | CF7: 63.817 | CG7: -36.397 | CH7: -35.813 | CI7: 3.403 | CJ7: 2181.869 | CK7: 63.947 | CL7: -36.801 | CM7: 18.331 | CN7: 3.338 | CO7: 2230.685 | CP7: 66.139 | CQ7: -37.839 | CR7: 11.028 | CS7: 0.986 | CT7: 2270.999 | CU7: 70.728 | CV7: -38.753 | CW7: 94.181 | CX7: 3.243 | CY7: 2400.399 | CZ7: 76.511 | DA7: -39.723 | DB7: 213.941 | DC7: 4.213 | DD7: 2655.34 | DE7: 78.565 | DF7: -41.404 | DG7: 226.749 | DH7: 10.394 | DI7: 2929.644 | DJ7: 82.84 | DK7: -43.332 | DL7: 232.292 | DM7: 14.174 | DN7: 3215.616 | DO7: 86.34 | DP7: -45.262 | DQ7: 348.102 | DR7: 18.936 | DS7: 3623.73 | DT7: 90.962 | DU7: -47.459 | DV7: 484.647 | DW7: 18.898 | DX7: 4170.775 | DY7: 101.039 | DZ7: -50.563 | EA7: 646.311 | EB7: 30.21 | EC7: 4897.774 | ED7: 105.096 | EE7: -53.725 | EF7: 718.75 | EG7: 32.863 | EH7: 5700.758 | EI7: 115.884 | EJ7: -57.561 | EK7: 535.714 | EL7: 33.489 | EM7: 6328.283 | EN7: 123.662 | EO7: -61.479 | EP7: 284.832 | EQ7: 93.928 | ER7: 6769.226 | ES7: 126.926 | ET7: -65.844 | EU7: -379.007 | EV7: 37.753 | EW7: 6489.052 | EX7: 108.429 | EY7: -65.454 | EZ7: -68.761 | FA7: -18.126 | FB7: 6445.14 | FC7: 112.626 | FD7: -67.435 | FE7: 514.399 | FF7: 8.169 | FG7: 7012.899 | FH7: 117.727 | FI7: -69.454 | FJ7: 185.511 | FK7: 39.609 | FL7: 7286.289 | FM7: 116.564 | FN7: -70.356 | FO7: -143.008 | FP7: 41.397 | FQ7: 7230.886 | FR7: 116.684 | FS7: -70.446 | FT7: -146.945 | FU7: 55.48 | FV7: 7185.659 | FW7: 115.841 | FX7: -72.278 | FY7: -160.488 | FZ7: 37.632 | GA7: 7106.361 | GB7: 116.111 | GC7: -73.151 | GD7: -17.823 | GE7: 36.214 | GF7: 7167.711 | GG7: 120.115 | GH7: -74.181 | GI7: 148.089 | GJ7: 35.243 | GK7: 7396.974 | GL7: 129.622 | GM7: -77.468 | GN7: 225.227 | GO7: 51.034 | GP7: 7725.384 | GQ7: 136.075 | GR7: -81.211 | GS7: 226.325 | GT7: 53.105 | GU7: 8059.674 | GV7: 142.519 | GW7: -85.765 | GX7: 282.598 | GY7: 76.795 | GZ7: 8475.817 | HA7: 136.937 | HB7: -89.973 | HC7: 432.481 | HD7: 72.782 | HE7: 9028.041 | HF7: 163.6 | HG7: -96.946 | HH7: 558.704 | HI7: 82.941 | HJ7: 9736.338 | HK7: 170.879 | HL7: -106.424 | HM7: 346.933 | HN7: 87.294 | HO7: 10235.023 | HP7: 160.34 | HQ7: -109.65 | HR7: -425.358 | HS7: 71.133 | HT7: 9931.491 | HU7: 150.69 | HV7: -108.746 | HW7: -183.907 | HX7: 78.249 | HY7: 9867.778
A8: N1 | B8: Actifs non financiers produits | C8: 486.393 | D8: 36.035 | E8: -12.997 | F8: 62.352 | H8: 571.783 | I8: 41.352 | J8: -15.577 | K8: 66.971 | M8: 664.528 | N8: 42.791 | O8: -17.875 | P8: 68.281 | R8: 757.724 | S8: 45.449 | T8: -20.493 | U8: 77.691 | W8: 860.371 | X8: 46.666 | Y8: -22.4 | Z8: 68.811 | AB8: 953.445 | AC8: 48.472 | AD8: -23.945 | AE8: 43.179 | AG8: 1021.148 | AH8: 47.493 | AI8: -24.901 | AJ8: 30.129 | AL8: 1073.869 | AM8: 50.407 | AN8: -25.942 | AO8: 35.182 | AQ8: 1133.516 | AR8: 55.567 | AS8: -27.204 | AT8: 40.57 | AV8: 1202.445 | AW8: 60.749 | AX8: -28.902 | AY8: 36.943 | BA8: 1271.235 | BB8: 67.686 | BC8: -30.882 | BD8: 34.648 | BF8: 1342.686 | BG8: 68.551 | BH8: -32.977 | BI8: 44.301 | BK8: 1422.561 | BL8: 65.381 | BM8: -35.037 | BN8: 31.393 | BP8: 1484.298 | BQ8: 62.218 | BR8: -35.734 | BS8: 13.166 | BU8: 1523.948 | BV8: 59.565 | BW8: -36.024 | BX8: 13.324 | BZ8: 1560.813 | CA8: 63.369 | CB8: -36.485 | CC8: 9.782 | CE8: 1597.478 | CF8: 64.825 | CG8: -36.397 | CH8: 20.186 | CJ8: 1646.091 | CK8: 64.715 | CL8: -36.801 | CM8: 30.497 | CO8: 1704.501 | CP8: 67.828 | CQ8: -37.839 | CR8: 23.442 | CT8: 1757.932 | CU8: 72.381 | CV8: -38.753 | CW8: 15.817 | CY8: 1807.379 | CZ8: 78.152 | DA8: -39.723 | DB8: 26.196 | DC8: -0.837 | DD8: 1871.167 | DE8: 81.241 | DF8: -41.404 | DG8: 48.597 | DH8: 0 | DI8: 1959.601 | DJ8: 84.652 | DK8: -43.332 | DL8: 68.812 | DM8: 0 | DN8: 2069.731 | DO8: 88.516 | DP8: -45.262 | DQ8: 63.642 | DR8: 0 | DS8: 2176.625 | DT8: 93.087 | DU8: -47.459 | DV8: 77.416 | DW8: 0 | DX8: 2299.668 | DY8: 103.619 | DZ8: -50.563 | EA8: 97.994 | EB8: 0 | EC8: 2450.719 | ED8: 107.981 | EE8: -53.725 | EF8: 106.23 | EG8: 0 | EH8: 2611.205 | EI8: 119.303 | EJ8: -57.561 | EK8: 108.834 | EL8: 0 | EM8: 2781.78 | EN8: 127.655 | EO8: -61.479 | EP8: 112.024 | EQ8: 0 | ER8: 2959.98 | ES8: 129.829 | ET8: -65.844 | EU8: 59.683 | EV8: 0 | EW8: 3083.646 | EX8: 111.99 | EY8: -65.454 | EZ8: 35.999 | FA8: -0.173 | FB8: 3166.008 | FC8: 115.78 | FD8: -67.435 | FE8: 87.028 | FG8: 3301.381 | FH8: 121.61 | FI8: -69.454 | FJ8: 72.019 | FL8: 3425.553 | FM8: 120.515 | FN8: -70.356 | FO8: 25.964 | FQ8: 3501.676 | FR8: 120.093 | FS8: -70.446 | FT8: 29.36 | FV8: 3580.683 | FW8: 119.506 | FX8: -72.278 | FY8: 25.385 | GA8: 3653.291 | GB8: 119.455 | GC8: -73.151 | GD8: -2.441 | GF8: 3697.152 | GG8: 123.278 | GH8: -74.181 | GI8: 38.112 | GK8: 3784.357 | GL8: 133.084 | GM8: -77.468 | GN8: 70.364 | GP8: 3910.332 | GQ8: 139.536 | GR8: -81.211 | GS8: 66.701 | GU8: 4035.352 | GV8: 146.24 | GW8: -85.765 | GX8: 50.654 | GZ8: 4146.477 | HA8: 139.783 | HB8: -89.973 | HC8: 117.289 | HE8: 4313.572 | HF8: 166.664 | HG8: -96.946 | HH8: 318.258 | HJ8: 4701.545 | HK8: 173.702 | HL8: -106.424 | HM8: 298.299 | HO8: 5067.126 | HP8: 163.832 | HQ8: -109.65 | HR8: 84.755 | HT8: 5206.065 | HU8: 154.683 | HV8: -108.746 | HW8: 9.813 | HY8: 5261.817
A9: N11 | B9: Actifs fixes par type d’actifs | C9: 434.729 | D9: 34.882 | E9: -12.997 | F9: 56.013 | H9: 512.626 | I9: 40.117 | J9: -15.577 | K9: 64.026 | M9: 601.191 | N9: 42.884 | O9: -17.875 | P9: 69.224 | R9: 695.424 | S9: 45.21 | T9: -20.493 | U9: 71.675 | W9: 791.815 | X9: 46.871 | Y9: -22.4 | Z9: 57.49 | AB9: 873.774 | AC9: 48.151 | AD9: -23.945 | AE9: 45.857 | AG9: 943.834 | AH9: 48.187 | AI9: -24.901 | AJ9: 34.927 | AL9: 1002.048 | AM9: 50.59 | AN9: -25.942 | AO9: 35.353 | AQ9: 1062.048 | AR9: 54.313 | AS9: -27.204 | AT9: 40.278 | AV9: 1129.432 | AW9: 59.393 | AX9: -28.902 | AY9: 40.732 | BA9: 1200.655 | BB9: 66.141 | BC9: -30.882 | BD9: 40.971 | BF9: 1276.883 | BG9: 67.084 | BH9: -32.977 | BI9: 49.665 | BK9: 1360.656 | BL9: 64.256 | BM9: -35.037 | BN9: 35.307 | BP9: 1425.182 | BQ9: 61.626 | BR9: -35.734 | BS9: 15.379 | BU9: 1466.453 | BV9: 59.08 | BW9: -36.024 | BX9: 12.724 | BZ9: 1502.232 | CA9: 62.421 | CB9: -36.485 | CC9: 11.528 | CE9: 1539.694 | CF9: 63.583 | CG9: -36.397 | CH9: 20.728 | CJ9: 1587.608 | CK9: 63.714 | CL9: -36.801 | CM9: 30.765 | CO9: 1645.286 | CP9: 67.097 | CQ9: -37.839 | CR9: 25.695 | CT9: 1700.239 | CU9: 71.043 | CV9: -38.753 | CW9: 15.494 | CY9: 1748.024 | CZ9: 76.503 | DA9: -39.723 | DB9: 18.663 | DD9: 1803.467 | DE9: 79.713 | DF9: -41.404 | DG9: 40.625 | DI9: 1882.4 | DJ9: 82.439 | DK9: -43.332 | DL9: 56.513 | DN9: 1978.018 | DO9: 86.718 | DP9: -45.262 | DQ9: 56.952 | DS9: 2076.425 | DT9: 91.506 | DU9: -47.459 | DV9: 78.459 | DX9: 2198.93 | DY9: 99.044 | DZ9: -50.563 | EA9: 94.85 | EC9: 2342.262 | ED9: 106.658 | EE9: -53.725 | EF9: 92.386 | EH9: 2487.58 | EI9: 117.744 | EJ9: -57.561 | EK9: 98.544 | EM9: 2646.307 | EN9: 125.968 | EO9: -61.479 | EP9: 113.172 | ER9: 2823.968 | ES9: 128.577 | ET9: -65.844 | EU9: 71.105 | EW9: 2957.804 | EX9: 111.746 | EY9: -65.454 | EZ9: 34.134 | FB9: 3038.231 | FC9: 115.104 | FD9: -67.435 | FE9: 68.019 | FG9: 3153.919 | FH9: 120.322 | FI9: -69.454 | FJ9: 68.437 | FL9: 3273.221 | FM9: 120.238 | FN9: -70.356 | FO9: 30.9 | FQ9: 3354.002 | FR9: 119.683 | FS9: -70.446 | FT9: 31.274 | FV9: 3434.513 | FW9: 118.852 | FX9: -72.278 | FY9: 23.691 | GA9: 3504.772 | GB9: 118.08 | GC9: -73.151 | GD9: 0.722 | GF9: 3550.421 | GG9: 122.315 | GH9: -74.181 | GI9: 37.503 | GK9: 3636.054 | GL9: 131.853 | GM9: -77.468 | GN9: 63.48 | GP9: 3753.914 | GQ9: 137.356 | GR9: -81.211 | GS9: 68.052 | GU9: 3878.106 | GV9: 145.017 | GW9: -85.765 | GX9: 54.321 | GZ9: 3991.675 | HA9: 138.644 | HB9: -89.973 | HC9: 108.038 | HE9: 4148.38 | HF9: 164.487 | HG9: -96.946 | HH9: 284.639 | HJ9: 4500.558 | HK9: 170.437 | HL9: -106.424 | HM9: 278.668 | HO9: 4843.242 | HP9: 161.766 | HQ9: -109.65 | HR9: 91.364 | HT9: 4986.725 | HU9: 153.122 | HV9: -108.746 | HW9: 11.5 | HY9: 5042.603
A10: N11K | B10: Constructions | C10: 411.214 | D10: 31.625 | E10: -10.377 | F10: 53.915 | H10: 486.378 | I10: 36.337 | J10: -12.487 | K10: 60.887 | M10: 571.114 | N10: 38.654 | O10: -14.3 | P10: 65.683 | R10: 661.152 | S10: 40.536 | T10: -16.365 | U10: 67.439 | W10: 752.762 | X10: 42.122 | Y10: -17.939 | Z10: 55.566 | AB10: 832.511 | AC10: 43.091 | AD10: -19.194 | AE10: 44.539 | AG10: 900.946 | AH10: 42.813 | AI10: -19.95 | AJ10: 33.981 | AL10: 957.791 | AM10: 44.865 | AN10: -20.729 | AO10: 35.253 | AQ10: 1017.179 | AR10: 48.14 | AS10: -21.78 | AT10: 40.099 | AV10: 1083.637 | AW10: 52.674 | AX10: -23.241 | AY10: 38.798 | BA10: 1151.866 | BB10: 58.615 | BC10: -24.885 | BD10: 39.531 | BF10: 1225.126 | BG10: 59.594 | BH10: -26.762 | BI10: 49.594 | BK10: 1307.552 | BL10: 57.85 | BM10: -28.578 | BN10: 35.813 | BP10: 1372.637 | BQ10: 55.81 | BR10: -29.365 | BS10: 16.564 | BU10: 1415.647 | BV10: 53.741 | BW10: -29.859 | BX10: 13.821 | BZ10: 1453.348 | CA10: 56.292 | CB10: -30.347 | CC10: 12.203 | CE10: 1491.495 | CF10: 57.183 | CG10: -30.33 | CH10: 22.482 | CJ10: 1540.829 | CK10: 57.799 | CL10: -30.738 | CM10: 32.089 | CO10: 1599.979 | CP10: 61.211 | CQ10: -31.846 | CR10: 26.095 | CT10: 1655.439 | CU10: 65.003 | CV10: -32.82 | CW10: 15.915 | CY10: 1703.537 | CZ10: 70.717 | DA10: -33.84 | DB10: 18.916 | DD10: 1759.329 | DE10: 73.832 | DF10: -35.325 | DG10: 39.991 | DI10: 1837.827 | DJ10: 76.758 | DK10: -37.179 | DL10: 56.494 | DN10: 1933.9 | DO10: 81.11 | DP10: -39.117 | DQ10: 56.968 | DS10: 2032.861 | DT10: 85.678 | DU10: -41.299 | DV10: 78.301 | DX10: 2155.541 | DY10: 93.458 | DZ10: -44.398 | EA10: 94.56 | EC10: 2299.161 | ED10: 101.01 | EE10: -47.42 | EF10: 92.055 | EH10: 2444.805 | EI10: 112.143 | EJ10: -51.237 | EK10: 98.314 | EM10: 2604.025 | EN10: 119.986 | EO10: -55.089 | EP10: 112.815 | ER10: 2781.737 | ES10: 122.872 | ET10: -59.541 | EU10: 71.372 | EW10: 2916.439 | EX10: 106.736 | EY10: -59.222 | EZ10: 33.752 | FB10: 2997.704 | FC10: 110.406 | FD10: -61.415 | FE10: 68.022 | FG10: 3114.717 | FH10: 115.104 | FI10: -63.492 | FJ10: 67.994 | FL10: 3234.321 | FM10: 114.64 | FN10: -64.404 | FO10: 30.628 | FQ10: 3315.185 | FR10: 114.285 | FS10: -64.559 | FT10: 31.162 | FV10: 3396.072 | FW10: 113.638 | FX10: -66.466 | FY10: 24.016 | GA10: 3467.257 | GB10: 112.833 | GC10: -67.458 | GD10: 1.33 | GF10: 3513.96 | GG10: 117.133 | GH10: -68.594 | GI10: 37.818 | GK10: 3600.314 | GL10: 126.322 | GM10: -71.862 | GN10: 63.413 | GP10: 3718.184 | GQ10: 131.591 | GR10: -75.471 | GS10: 67.753 | GU10: 3842.055 | GV10: 138.797 | GW10: -79.863 | GX10: 53.59 | GZ10: 3954.577 | HA10: 132.237 | HB10: -83.882 | HC10: 107.612 | HE10: 4110.54 | HF10: 157.546 | HG10: -90.529 | HH10: 283.72 | HJ10: 4461.275 | HK10: 164.075 | HL10: -99.735 | HM10: 276.586 | HO10: 4802.204 | HP10: 154.843 | HQ10: -102.469 | HR10: 90.551 | HT10: 4945.131 | HU10: 146.534 | HV10: -101.449 | HW10: 10.933 | HY10: 5001.149
A11: N111 | B11: Logements | C11: 366.873 | D11: 29.037 | E11: -7.845 | F11: 46.731 | H11: 434.796 | I11: 33.356 | J11: -9.506 | K11: 52.753 | M11: 511.398 | N11: 35.499 | O11: -10.938 | P11: 57.621 | R11: 593.579 | S11: 37.202 | T11: -12.562 | U11: 59.705 | W11: 677.924 | X11: 38.682 | Y11: -13.821 | Z11: 49.538 | AB11: 752.323 | AC11: 39.48 | AD11: -14.806 | AE11: 40.124 | AG11: 817.121 | AH11: 39.347 | AI11: -15.407 | AJ11: 30.75 | AL11: 871.811 | AM11: 41.086 | AN11: -16.051 | AO11: 31.606 | AQ11: 928.451 | AR11: 43.994 | AS11: -16.924 | AT11: 35.615 | AV11: 991.136 | AW11: 48.297 | AX11: -18.163 | AY11: 33.96 | BA11: 1055.23 | BB11: 53.761 | BC11: -19.588 | BD11: 35.479 | BF11: 1124.882 | BG11: 55.053 | BH11: -21.33 | BI11: 46.635 | BK11: 1205.24 | BL11: 53.502 | BM11: -23.018 | BN11: 34.546 | BP11: 1270.27 | BQ11: 51.402 | BR11: -23.827 | BS11: 16.669 | BU11: 1314.513 | BV11: 49.524 | BW11: -24.377 | BX11: 12.868 | BZ11: 1352.529 | CA11: 51.897 | CB11: -24.828 | CC11: 10.35 | CE11: 1389.948 | CF11: 52.777 | CG11: -24.787 | CH11: 20.682 | CJ11: 1438.619 | CK11: 53.695 | CL11: -25.166 | CM11: 29.275 | CO11: 1496.424 | CP11: 56.946 | CQ11: -26.156 | CR11: 22.687 | CT11: 1549.9 | CU11: 60.377 | CV11: -26.99 | CW11: 12.328 | CY11: 1595.614 | CZ11: 65.475 | DA11: -27.845 | DB11: 14.252 | DD11: 1647.497 | DE11: 68.763 | DF11: -29.062 | DG11: 36.331 | DI11: 1723.53 | DJ11: 71.611 | DK11: -30.819 | DL11: 54.079 | DN11: 1818.4 | DO11: 75.751 | DP11: -32.661 | DQ11: 53.257 | DS11: 1914.747 | DT11: 80.187 | DU11: -34.692 | DV11: 73.968 | DX11: 2034.21 | DY11: 87.899 | DZ11: -37.649 | EA11: 90.355 | EC11: 2174.815 | ED11: 95.314 | EE11: -40.516 | EF11: 87.546 | EH11: 2317.159 | EI11: 106.175 | EJ11: -44.149 | EK11: 93.405 | EM11: 2472.589 | EN11: 113.479 | EO11: -47.751 | EP11: 106.654 | ER11: 2644.971 | ES11: 115.823 | ET11: -51.806 | EU11: 67.266 | EW11: 2776.254 | EX11: 100.362 | EY11: -51.42 | EZ11: 30.138 | FB11: 2855.334 | FC11: 103.585 | FD11: -53.4 | FE11: 61.667 | FG11: 2967.187 | FH11: 108.322 | FI11: -55.213 | FJ11: 62.678 | FL11: 3082.974 | FM11: 107.719 | FN11: -55.95 | FO11: 28.315 | FQ11: 3163.058 | FR11: 106.909 | FS11: -56.121 | FT11: 31.408 | FV11: 3245.254 | FW11: 105.986 | FX11: -58.061 | FY11: 26.721 | GA11: 3319.9 | GB11: 104.814 | GC11: -59.12 | GD11: 4.01 | GF11: 3369.604 | GG11: 108.142 | GH11: -60.07 | GI11: 36.853 | GK11: 3454.529 | GL11: 116.718 | GM11: -63.013 | GN11: 60.094 | GP11: 3568.328 | GQ11: 121.034 | GR11: -66.166 | GS11: 64.662 | GU11: 3687.858 | GV11: 127.185 | GW11: -70.058 | GX11: 52.36 | GZ11: 3797.345 | HA11: 120.183 | HB11: -73.68 | HC11: 104.234 | HE11: 3948.081 | HF11: 144.722 | HG11: -79.677 | HH11: 271.706 | HJ11: 4284.832 | HK11: 151.887 | HL11: -87.918 | HM11: 264.647 | HO11: 4613.448 | HP11: 143.032 | HQ11: -90.214 | HR11: 86.422 | HT11: 4752.687 | HU11: 134.912 | HV11: -89.115 | HW11: 8.927 | HY11: 4807.411
A12: N112 | B12: Autres bâtiments et ouvrages de génie civil | C12: 44.341 | D12: 2.589 | E12: -2.532 | F12: 7.184 | H12: 51.582 | I12: 2.981 | J12: -2.981 | K12: 8.134 | M12: 59.716 | N12: 3.156 | O12: -3.361 | P12: 8.063 | R12: 67.572 | S12: 3.334 | T12: -3.803 | U12: 7.734 | W12: 74.839 | X12: 3.44 | Y12: -4.118 | Z12: 6.028 | AB12: 80.188 | AC12: 3.611 | AD12: -4.388 | AE12: 4.415 | AG12: 83.825 | AH12: 3.467 | AI12: -4.542 | AJ12: 3.23 | AL12: 85.98 | AM12: 3.779 | AN12: -4.677 | AO12: 3.647 | AQ12: 88.728 | AR12: 4.146 | AS12: -4.856 | AT12: 4.484 | AV12: 92.501 | AW12: 4.376 | AX12: -5.078 | AY12: 4.838 | BA12: 96.636 | BB12: 4.854 | BC12: -5.297 | BD12: 4.051 | BF12: 100.244 | BG12: 4.541 | BH12: -5.432 | BI12: 2.959 | BK12: 102.313 | BL12: 4.348 | BM12: -5.56 | BN12: 1.267 | BP12: 102.368 | BQ12: 4.408 | BR12: -5.538 | BS12: -0.104 | BU12: 101.133 | BV12: 4.216 | BW12: -5.482 | BX12: 0.952 | BZ12: 100.819 | CA12: 4.394 | CB12: -5.519 | CC12: 1.853 | CE12: 101.546 | CF12: 4.406 | CG12: -5.543 | CH12: 1.8 | CJ12: 102.21 | CK12: 4.104 | CL12: -5.572 | CM12: 2.814 | CO12: 103.555 | CP12: 4.265 | CQ12: -5.689 | CR12: 3.408 | CT12: 105.539 | CU12: 4.626 | CV12: -5.83 | CW12: 3.587 | CY12: 107.922 | CZ12: 5.242 | DA12: -5.995 | DB12: 4.663 | DD12: 111.832 | DE12: 5.069 | DF12: -6.263 | DG12: 3.661 | DI12: 114.298 | DJ12: 5.148 | DK12: -6.36 | DL12: 2.415 | DN12: 115.499 | DO12: 5.359 | DP12: -6.456 | DQ12: 3.711 | DS12: 118.113 | DT12: 5.491 | DU12: -6.607 | DV12: 4.333 | DX12: 121.331 | DY12: 5.56 | DZ12: -6.749 | EA12: 4.205 | EC12: 124.347 | ED12: 5.696 | EE12: -6.904 | EF12: 4.508 | EH12: 127.646 | EI12: 5.969 | EJ12: -7.087 | EK12: 4.909 | EM12: 131.435 | EN12: 6.507 | EO12: -7.337 | EP12: 6.162 | ER12: 136.766 | ES12: 7.049 | ET12: -7.735 | EU12: 4.106 | EW12: 140.184 | EX12: 6.374 | EY12: -7.802 | EZ12: 3.615 | FB12: 142.37 | FC12: 6.821 | FD12: -8.015 | FE12: 6.355 | FG12: 147.53 | FH12: 6.782 | FI12: -8.279 | FJ12: 5.316 | FL12: 151.347 | FM12: 6.921 | FN12: -8.453 | FO12: 2.314 | FQ12: 152.127 | FR12: 7.376 | FS12: -8.439 | FT12: -0.246 | FV12: 150.818 | FW12: 7.652 | FX12: -8.405 | FY12: -2.705 | GA12: 147.357 | GB12: 8.019 | GC12: -8.338 | GD12: -2.681 | GF12: 144.356 | GG12: 8.991 | GH12: -8.523 | GI12: 0.965 | GK12: 145.785 | GL12: 9.603 | GM12: -8.849 | GN12: 3.318 | GP12: 149.856 | GQ12: 10.557 | GR12: -9.305 | GS12: 3.091 | GU12: 154.197 | GV12: 11.613 | GW12: -9.805 | GX12: 1.23 | GZ12: 157.232 | HA12: 12.054 | HB12: -10.202 | HC12: 3.378 | HE12: 162.459 | HF12: 12.824 | HG12: -10.852 | HH12: 12.015 | HJ12: 176.444 | HK12: 12.188 | HL12: -11.817 | HM12: 11.939 | HO12: 188.756 | HP12: 11.811 | HQ12: -12.255 | HR12: 4.13 | HT12: 192.444 | HU12: 11.622 | HV12: -12.334 | HW12: 2.006 | HY12: 193.738
A13: N1121 | B13: Bâtiments non résidentiels | C13: 20.119 | D13: 1.623 | E13: -1.748 | F13: 2.589 | H13: 22.581 | I13: 1.865 | J13: -2.021 | K13: 2.989 | M13: 25.415 | N13: 1.962 | O13: -2.256 | P13: 2.98 | R13: 28.102 | S13: 2.076 | T13: -2.518 | U13: 2.798 | W13: 30.458 | X13: 2.133 | Y13: -2.703 | Z13: 2.198 | AB13: 32.086 | AC13: 2.254 | AD13: -2.86 | AE13: 1.743 | AG13: 33.223 | AH13: 2.122 | AI13: -2.956 | AJ13: 1.116 | AL13: 33.504 | AM13: 2.358 | AN13: -3.009 | AO13: 0.876 | AQ13: 33.729 | AR13: 2.619 | AS13: -3.088 | AT13: 1.015 | AV13: 34.274 | AW13: 2.725 | AX13: -3.182 | AY13: 0.935 | BA13: 34.752 | BB13: 3.039 | BC13: -3.271 | BD13: 0.799 | BF13: 35.318 | BG13: 2.732 | BH13: -3.321 | BI13: 1.029 | BK13: 35.758 | BL13: 2.65 | BM13: -3.409 | BN13: 0.84 | BP13: 35.838 | BQ13: 2.724 | BR13: -3.403 | BS13: 0.323 | BU13: 35.482 | BV13: 2.561 | BW13: -3.364 | BX13: 0.183 | BZ13: 34.863 | CA13: 2.652 | CB13: -3.338 | CC13: 0.099 | CE13: 34.275 | CF13: 2.666 | CG13: -3.314 | CH13: 0.168 | CJ13: 33.796 | CK13: 2.466 | CL13: -3.294 | CM13: 0.363 | CO13: 33.331 | CP13: 2.531 | CQ13: -3.311 | CR13: 0.643 | CT13: 33.195 | CU13: 2.776 | CV13: -3.382 | CW13: 0.61 | CY13: 33.199 | CZ13: 3.136 | DA13: -3.428 | DB13: 1.146 | DD13: 34.054 | DE13: 2.92 | DF13: -3.593 | DG13: 1.548 | DI13: 34.928 | DJ13: 2.962 | DK13: -3.669 | DL13: 0.903 | DN13: 35.124 | DO13: 3.067 | DP13: -3.7 | DQ13: 0.718 | DS13: 35.209 | DT13: 3.058 | DU13: -3.727 | DV13: 0.959 | DX13: 35.499 | DY13: 2.946 | DZ13: -3.78 | EA13: 1.182 | EC13: 35.846 | ED13: 2.922 | EE13: -3.833 | EF13: 1.118 | EH13: 36.053 | EI13: 3.004 | EJ13: -3.901 | EK13: 1.164 | EM13: 36.319 | EN13: 3.348 | EO13: -4.022 | EP13: 1.371 | ER13: 37.016 | ES13: 3.771 | ET13: -4.231 | EU13: 1.073 | EW13: 37.629 | EX13: 3.409 | EY13: -4.304 | EZ13: 0.489 | FB13: 37.224 | FC13: 3.472 | FD13: -4.317 | FE13: 0.621 | FG13: 37 | FH13: 3.491 | FI13: -4.413 | FJ13: 0.908 | FL13: 36.985 | FM13: 3.679 | FN13: -4.49 | FO13: 0.363 | FQ13: 36.538 | FR13: 3.835 | FS13: -4.473 | FT13: -0.079 | FV13: 35.82 | FW13: 3.968 | FX13: -4.479 | FY13: -0.129 | GA13: 35.18 | GB13: 4.382 | GC13: -4.569 | GD13: -0.207 | GF13: 34.785 | GG13: 5.183 | GH13: -4.784 | GI13: -0.095 | GK13: 35.089 | GL13: 5.415 | GM13: -5.01 | GN13: 0.335 | GP13: 35.828 | GQ13: 6.046 | GR13: -5.353 | GS13: 0.49 | GU13: 37.011 | GV13: 6.838 | GW13: -5.773 | GX13: 0.257 | GZ13: 38.332 | HA13: 7.373 | HB13: -6.167 | HC13: 0.675 | HE13: 40.212 | HF13: 7.511 | HG13: -6.609 | HH13: 2.117 | HJ13: 43.232 | HK13: 7.134 | HL13: -7.088 | HM13: 2.315 | HO13: 45.595 | HP13: 6.823 | HQ13: -7.379 | HR13: 1.123 | HT13: 46.162 | HU13: 6.667 | HV13: -7.409 | HW13: 0.496 | HY13: 45.917
A14: N1122 | B14: Autres ouvrages de génie civil | C14: 24.223 | D14: 0.966 | E14: -0.783 | F14: 4.595 | H14: 29.001 | I14: 1.115 | J14: -0.96 | K14: 5.145 | M14: 34.301 | N14: 1.193 | O14: -1.106 | P14: 5.082 | R14: 39.471 | S14: 1.258 | T14: -1.284 | U14: 4.936 | W14: 44.381 | X14: 1.307 | Y14: -1.415 | Z14: 3.83 | AB14: 48.103 | AC14: 1.356 | AD14: -1.529 | AE14: 2.673 | AG14: 50.603 | AH14: 1.345 | AI14: -1.587 | AJ14: 2.115 | AL14: 52.476 | AM14: 1.421 | AN14: -1.668 | AO14: 2.771 | AQ14: 54.999 | AR14: 1.527 | AS14: -1.769 | AT14: 3.469 | AV14: 58.227 | AW14: 1.651 | AX14: -1.896 | AY14: 3.903 | BA14: 61.885 | BB14: 1.816 | BC14: -2.026 | BD14: 3.252 | BF14: 64.926 | BG14: 1.809 | BH14: -2.111 | BI14: 1.93 | BK14: 66.555 | BL14: 1.699 | BM14: -2.151 | BN14: 0.427 | BP14: 66.529 | BQ14: 1.685 | BR14: -2.135 | BS14: -0.428 | BU14: 65.651 | BV14: 1.655 | BW14: -2.119 | BX14: 0.769 | BZ14: 65.956 | CA14: 1.742 | CB14: -2.181 | CC14: 1.754 | CE14: 67.271 | CF14: 1.74 | CG14: -2.229 | CH14: 1.632 | CJ14: 68.414 | CK14: 1.638 | CL14: -2.278 | CM14: 2.451 | CO14: 70.224 | CP14: 1.733 | CQ14: -2.379 | CR14: 2.765 | CT14: 72.344 | CU14: 1.85 | CV14: -2.448 | CW14: 2.978 | CY14: 74.723 | CZ14: 2.105 | DA14: -2.568 | DB14: 3.517 | DD14: 77.778 | DE14: 2.149 | DF14: -2.67 | DG14: 2.113 | DI14: 79.37 | DJ14: 2.186 | DK14: -2.691 | DL14: 1.512 | DN14: 80.376 | DO14: 2.292 | DP14: -2.756 | DQ14: 2.993 | DS14: 82.904 | DT14: 2.433 | DU14: -2.879 | DV14: 3.374 | DX14: 85.832 | DY14: 2.614 | DZ14: -2.969 | EA14: 3.023 | EC14: 88.5 | ED14: 2.774 | EE14: -3.071 | EF14: 3.39 | EH14: 91.593 | EI14: 2.965 | EJ14: -3.187 | EK14: 3.746 | EM14: 95.116 | EN14: 3.158 | EO14: -3.316 | EP14: 4.79 | ER14: 99.749 | ES14: 3.278 | ET14: -3.504 | EU14: 3.033 | EW14: 102.555 | EX14: 2.965 | EY14: -3.499 | EZ14: 3.126 | FB14: 105.146 | FC14: 3.348 | FD14: -3.698 | FE14: 5.734 | FG14: 110.53 | FH14: 3.291 | FI14: -3.867 | FJ14: 4.408 | FL14: 114.362 | FM14: 3.242 | FN14: -3.964 | FO14: 1.951 | FQ14: 115.59 | FR14: 3.541 | FS14: -3.966 | FT14: -0.167 | FV14: 114.997 | FW14: 3.684 | FX14: -3.926 | FY14: -2.577 | GA14: 112.177 | GB14: 3.637 | GC14: -3.769 | GD14: -2.474 | GF14: 109.571 | GG14: 3.808 | GH14: -3.74 | GI14: 1.059 | GK14: 110.697 | GL14: 4.188 | GM14: -3.839 | GN14: 2.983 | GP14: 114.027 | GQ14: 4.512 | GR14: -3.953 | GS14: 2.601 | GU14: 117.186 | GV14: 4.775 | GW14: -4.032 | GX14: 0.973 | GZ14: 118.901 | HA14: 4.681 | HB14: -4.035 | HC14: 2.703 | HE14: 122.246 | HF14: 5.313 | HG14: -4.243 | HH14: 9.898 | HJ14: 133.212 | HK14: 5.054 | HL14: -4.729 | HM14: 9.623 | HO14: 143.161 | HP14: 4.989 | HQ14: -4.876 | HR14: 3.006 | HT14: 146.281 | HU14: 4.954 | HV14: -4.925 | HW14: 1.51 | HY14: 147.821
A15: N113 | B15: Machines et équipements | C15: 12.78 | D15: 2.542 | E15: -2.131 | F15: 1.59 | H15: 14.78 | I15: 3.008 | J15: -2.52 | K15: 2.248 | M15: 17.515 | N15: 3.312 | O15: -2.947 | P15: 2.597 | R15: 20.476 | S15: 3.65 | T15: -3.419 | U15: 2.225 | W15: 22.932 | X15: 3.697 | Y15: -3.697 | Z15: 1.422 | AB15: 24.353 | AC15: 4.102 | AD15: -3.925 | AE15: 0.968 | AG15: 25.496 | AH15: 4.267 | AI15: -4.076 | AJ15: 0.715 | AL15: 26.402 | AM15: 4.628 | AN15: -4.266 | AO15: 0.624 | AQ15: 27.388 | AR15: 5.036 | AS15: -4.438 | AT15: 0.478 | AV15: 28.462 | AW15: 5.451 | AX15: -4.628 | AY15: 0.577 | BA15: 29.862 | BB15: 6.103 | BC15: -4.908 | BD15: 0.693 | BF15: 31.749 | BG15: 5.845 | BH15: -5.138 | BI15: 0.892 | BK15: 33.347 | BL15: 5.08 | BM15: -5.317 | BN15: 0.582 | BP15: 33.693 | BQ15: 4.433 | BR15: -5.249 | BS15: -0.277 | BU15: 32.601 | BV15: 4.114 | BW15: -5.059 | BX15: -0.261 | BZ15: 31.396 | CA15: 4.791 | CB15: -5.035 | CC15: -0.169 | CE15: 30.982 | CF15: 5.019 | CG15: -4.965 | CH15: -0.054 | CJ15: 30.982 | CK15: 4.69 | CL15: -4.956 | CM15: 0.071 | CO15: 30.786 | CP15: 4.721 | CQ15: -4.878 | CR15: -0.225 | CT15: 30.404 | CU15: 4.779 | CV15: -4.808 | CW15: -0.116 | CY15: 30.261 | CZ15: 4.484 | DA15: -4.772 | DB15: 0.732 | DD15: 30.705 | DE15: 4.469 | DF15: -4.924 | DG15: 1.072 | DI15: 31.322 | DJ15: 4.25 | DK15: -4.951 | DL15: 0.428 | DN15: 31.048 | DO15: 4.337 | DP15: -4.899 | DQ15: 0.146 | DS15: 30.632 | DT15: 4.601 | DU15: -4.904 | DV15: 0.318 | DX15: 30.646 | DY15: 4.314 | DZ15: -4.924 | EA15: 0.813 | EC15: 30.852 | ED15: 4.309 | EE15: -5.038 | EF15: 0.76 | EH15: 30.883 | EI15: 4.244 | EJ15: -5.028 | EK15: 0.513 | EM15: 30.612 | EN15: 4.479 | EO15: -5.049 | EP15: 0.492 | ER15: 30.534 | ES15: 4.383 | ET15: -4.993 | EU15: 0.527 | EW15: 30.449 | EX15: 3.893 | EY15: -4.935 | EZ15: 0.401 | FB15: 29.807 | FC15: 3.567 | FD15: -4.763 | FE15: 0.27 | FG15: 28.881 | FH15: 4.048 | FI15: -4.712 | FJ15: 0.599 | FL15: 28.814 | FM15: 4.314 | FN15: -4.719 | FO15: 0.539 | FQ15: 28.946 | FR15: 4.077 | FS15: -4.658 | FT15: 0.313 | FV15: 28.678 | FW15: 3.859 | FX15: -4.587 | FY15: 0.039 | GA15: 27.988 | GB15: 3.875 | GC15: -4.469 | GD15: -0.208 | GF15: 27.185 | GG15: 3.808 | GH15: -4.36 | GI15: -0.009 | GK15: 26.624 | GL15: 4.114 | GM15: -4.357 | GN15: 0.401 | GP15: 26.781 | GQ15: 4.25 | GR15: -4.432 | GS15: 0.529 | GU15: 27.127 | GV15: 4.587 | GW15: -4.511 | GX15: 0.539 | GZ15: 27.741 | HA15: 4.662 | HB15: -4.629 | HC15: 0.753 | HE15: 28.527 | HF15: 4.698 | HG15: -4.793 | HH15: 1.151 | HJ15: 29.582 | HK15: 3.859 | HL15: -4.833 | HM15: 1.685 | HO15: 30.295 | HP15: 4.143 | HQ15: -5.065 | HR15: 1.427 | HT15: 30.801 | HU15: 3.603 | HV15: -4.941 | HW15: 0.337 | HY15: 29.8
A16: N1131 | B16: Matériels de transport | C16: 1.443 | D16: 0.44 | E16: -0.411 | F16: 0.154 | H16: 1.626 | I16: 0.499 | J16: -0.469 | K16: 0.194 | M16: 1.85 | N16: 0.525 | O16: -0.524 | P16: 0.212 | R16: 2.063 | S16: 0.602 | T16: -0.588 | U16: 0.204 | W16: 2.28 | X16: 0.621 | Y16: -0.635 | Z16: 0.141 | AB16: 2.407 | AC16: 0.642 | AD16: -0.659 | AE16: 0.1 | AG16: 2.49 | AH16: 0.682 | AI16: -0.685 | AJ16: 0.129 | AL16: 2.617 | AM16: 0.782 | AN16: -0.732 | AO16: 0.119 | AQ16: 2.785 | AR16: 0.849 | AS16: -0.77 | AT16: 0.075 | AV16: 2.94 | AW16: 0.909 | AX16: -0.807 | AY16: 0.09 | BA16: 3.132 | BB16: 1.039 | BC16: -0.873 | BD16: 0.126 | BF16: 3.423 | BG16: 1.025 | BH16: -0.934 | BI16: 0.109 | BK16: 3.623 | BL16: 0.85 | BM16: -0.952 | BN16: 0.014 | BP16: 3.535 | BQ16: 0.734 | BR16: -0.911 | BS16: -0.051 | BU16: 3.307 | BV16: 0.694 | BW16: -0.866 | BX16: -0.015 | BZ16: 3.12 | CA16: 0.858 | CB16: -0.856 | CC16: 0.001 | CE16: 3.123 | CF16: 0.941 | CG16: -0.856 | CH16: -0.012 | CJ16: 3.197 | CK16: 0.761 | CL16: -0.838 | CM16: -0.1 | CO16: 3.02 | CP16: 0.756 | CQ16: -0.781 | CR16: -0.147 | CT16: 2.847 | CU16: 0.839 | CV16: -0.766 | CW16: -0.07 | CY16: 2.85 | CZ16: 0.787 | DA16: -0.759 | DB16: -0.01 | DD16: 2.867 | DE16: 0.914 | DF16: -0.788 | DG16: 0.03 | DI16: 3.023 | DJ16: 0.958 | DK16: -0.826 | DL16: 0.022 | DN16: 3.178 | DO16: 1.009 | DP16: -0.86 | DQ16: 0.024 | DS16: 3.35 | DT16: 1.269 | DU16: -0.938 | DV16: 0.05 | DX16: 3.731 | DY16: 1.191 | DZ16: -1.001 | EA16: 0.132 | EC16: 4.053 | ED16: 1.119 | EE16: -1.084 | EF16: 0.171 | EH16: 4.259 | EI16: 1.219 | EJ16: -1.144 | EK16: 0.1 | EM16: 4.434 | EN16: 1.288 | EO16: -1.19 | EP16: 0.087 | ER16: 4.619 | ES16: 0.894 | ET16: -1.177 | EU16: 0.055 | EW16: 4.391 | EX16: 0.795 | EY16: -1.121 | EZ16: 0.012 | FB16: 4.077 | FC16: 0.766 | FD16: -1.059 | FE16: 0.043 | FG16: 3.828 | FH16: 0.897 | FI16: -1.03 | FJ16: 0.07 | FL16: 3.764 | FM16: 0.789 | FN16: -0.991 | FO16: 0.036 | FQ16: 3.599 | FR16: 0.732 | FS16: -0.937 | FT16: 0.032 | FV16: 3.427 | FW16: 0.789 | FX16: -0.915 | FY16: 0.055 | GA16: 3.356 | GB16: 0.78 | GC16: -0.889 | GD16: 0.03 | GF16: 3.278 | GG16: 0.785 | GH16: -0.867 | GI16: 0.021 | GK16: 3.217 | GL16: 0.979 | GM16: -0.877 | GN16: 0.023 | GP16: 3.342 | GQ16: 0.909 | GR16: -0.887 | GS16: 0.053 | GU16: 3.417 | GV16: 1.102 | GW16: -0.935 | GX16: 0.084 | GZ16: 3.669 | HA16: 1.03 | HB16: -0.979 | HC16: 0.162 | HE16: 3.883 | HF16: 1.073 | HG16: -1.052 | HH16: 0.283 | HJ16: 4.187 | HK16: 0.59 | HL16: -1.036 | HM16: 0.172 | HO16: 3.913 | HP16: 0.755 | HQ16: -1.027 | HR16: 0.085 | HT16: 3.726 | HU16: 0.771 | HV16: -0.977 | HW16: 0.013 | HY16: 3.532
A17: N1132 | B17: Équipements TIC | C17: 0.158 | D17: 0.07 | E17: -0.06 | F17: 0.018 | H17: 0.185 | I17: 0.09 | J17: -0.074 | K17: 0.028 | M17: 0.229 | N17: 0.092 | O17: -0.087 | P17: 0.033 | R17: 0.267 | S17: 0.112 | T17: -0.103 | U17: 0.036 | W17: 0.311 | X17: 0.126 | Y17: -0.12 | Z17: 0.024 | AB17: 0.34 | AC17: 0.162 | AD17: -0.131 | AE17: 0.019 | AG17: 0.388 | AH17: 0.177 | AI17: -0.149 | AJ17: 0.028 | AL17: 0.443 | AM17: 0.214 | AN17: -0.171 | AO17: 0.021 | AQ17: 0.507 | AR17: 0.239 | AS17: -0.194 | AT17: 0.013 | AV17: 0.564 | AW17: 0.282 | AX17: -0.213 | AY17: -0.004 | BA17: 0.628 | BB17: 0.274 | BC17: -0.231 | BD17: -0.016 | BF17: 0.654 | BG17: 0.27 | BH17: -0.235 | BI17: -0.02 | BK17: 0.668 | BL17: 0.228 | BM17: -0.237 | BN17: -0.01 | BP17: 0.649 | BQ17: 0.222 | BR17: -0.233 | BS17: -0.012 | BU17: 0.626 | BV17: 0.198 | BW17: -0.226 | BX17: 0.01 | BZ17: 0.608 | CA17: 0.247 | CB17: -0.234 | CC17: -0.015 | CE17: 0.606 | CF17: 0.225 | CG17: -0.217 | CH17: -0.021 | CJ17: 0.592 | CK17: 0.199 | CL17: -0.213 | CM17: -0.014 | CO17: 0.564 | CP17: 0.19 | CQ17: -0.203 | CR17: -0.011 | CT17: 0.54 | CU17: 0.194 | CV17: -0.198 | CW17: -0.018 | CY17: 0.519 | CZ17: 0.209 | DA17: -0.193 | DB17: -0.006 | DD17: 0.529 | DE17: 0.194 | DF17: -0.194 | DG17: -0.025 | DI17: 0.504 | DJ17: 0.177 | DK17: -0.177 | DL17: -0.054 | DN17: 0.45 | DO17: 0.147 | DP17: -0.152 | DQ17: -0.041 | DS17: 0.404 | DT17: 0.147 | DU17: -0.142 | DV17: -0.011 | DX17: 0.399 | DY17: 0.124 | DZ17: -0.142 | EA17: 0.008 | EC17: 0.39 | ED17: 0.105 | EE17: -0.134 | EF17: 0.024 | EH17: 0.385 | EI17: 0.108 | EJ17: -0.144 | EK17: 0.015 | EM17: 0.364 | EN17: 0.095 | EO17: -0.122 | EP17: -0.016 | ER17: 0.321 | ES17: 0.098 | ET17: -0.11 | EU17: -0.011 | EW17: 0.297 | EX17: 0.082 | EY17: -0.098 | EZ17: -0.012 | FB17: 0.268 | FC17: 0.096 | FD17: -0.09 | FE17: -0.008 | FG17: 0.266 | FH17: 0.095 | FI17: -0.084 | FJ17: -0.007 | FL17: 0.269 | FM17: 0.095 | FN17: -0.083 | FO17: -0.011 | FQ17: 0.27 | FR17: 0.098 | FS17: -0.083 | FT17: -0.013 | FV17: 0.272 | FW17: 0.106 | FX17: -0.084 | FY17: -0.011 | GA17: 0.283 | GB17: 0.108 | GC17: -0.086 | GD17: -0.009 | GF17: 0.296 | GG17: 0.154 | GH17: -0.099 | GI17: -0.006 | GK17: 0.345 | GL17: 0.136 | GM17: -0.107 | GN17: -0.002 | GP17: 0.371 | GQ17: 0.214 | GR17: -0.129 | GS17: -0.045 | GU17: 0.41 | GV17: 0.131 | GW17: -0.114 | GX17: -0.017 | GZ17: 0.409 | HA17: 0.14 | HB17: -0.124 | HC17: 0.008 | HE17: 0.433 | HF17: 0.143 | HG17: -0.128 | HH17: 0.003 | HJ17: 0.45 | HK17: 0.104 | HL17: -0.128 | HM17: 0.002 | HO17: 0.43 | HP17: 0.095 | HQ17: -0.121 | HR17: -0.002 | HT17: 0.404 | HU17: 0.102 | HV17: -0.117 | HW17: 0.002 | HY17: 0.391
A18: N1139 | B18: Autres machines et équipements | C18: 11.179 | D18: 2.033 | E18: -1.66 | F18: 1.418 | H18: 12.969 | I18: 2.419 | J18: -1.978 | K18: 2.026 | M18: 15.436 | N18: 2.695 | O18: -2.336 | P18: 2.351 | R18: 18.146 | S18: 2.936 | T18: -2.727 | U18: 1.985 | W18: 20.341 | X18: 2.95 | Y18: -2.942 | Z18: 1.258 | AB18: 21.606 | AC18: 3.298 | AD18: -3.135 | AE18: 0.849 | AG18: 22.618 | AH18: 3.408 | AI18: -3.242 | AJ18: 0.558 | AL18: 23.343 | AM18: 3.632 | AN18: -3.362 | AO18: 0.484 | AQ18: 24.096 | AR18: 3.947 | AS18: -3.475 | AT18: 0.39 | AV18: 24.959 | AW18: 4.26 | AX18: -3.608 | AY18: 0.491 | BA18: 26.102 | BB18: 4.79 | BC18: -3.804 | BD18: 0.584 | BF18: 27.672 | BG18: 4.55 | BH18: -3.969 | BI18: 0.803 | BK18: 29.056 | BL18: 4.003 | BM18: -4.128 | BN18: 0.579 | BP18: 29.51 | BQ18: 3.478 | BR18: -4.105 | BS18: -0.215 | BU18: 28.668 | BV18: 3.223 | BW18: -3.967 | BX18: -0.256 | BZ18: 27.668 | CA18: 3.686 | CB18: -3.945 | CC18: -0.155 | CE18: 27.253 | CF18: 3.853 | CG18: -3.892 | CH18: -0.021 | CJ18: 27.193 | CK18: 3.73 | CL18: -3.906 | CM18: 0.185 | CO18: 27.203 | CP18: 3.775 | CQ18: -3.894 | CR18: -0.067 | CT18: 27.017 | CU18: 3.746 | CV18: -3.845 | CW18: -0.027 | CY18: 26.891 | CZ18: 3.488 | DA18: -3.819 | DB18: 0.748 | DD18: 27.309 | DE18: 3.361 | DF18: -3.942 | DG18: 1.067 | DI18: 27.795 | DJ18: 3.115 | DK18: -3.949 | DL18: 0.459 | DN18: 27.42 | DO18: 3.181 | DP18: -3.887 | DQ18: 0.163 | DS18: 26.878 | DT18: 3.185 | DU18: -3.825 | DV18: 0.279 | DX18: 26.517 | DY18: 3 | DZ18: -3.782 | EA18: 0.673 | EC18: 26.408 | ED18: 3.085 | EE18: -3.82 | EF18: 0.565 | EH18: 26.239 | EI18: 2.918 | EJ18: -3.74 | EK18: 0.398 | EM18: 25.814 | EN18: 3.096 | EO18: -3.737 | EP18: 0.42 | ER18: 25.593 | ES18: 3.391 | ET18: -3.706 | EU18: 0.484 | EW18: 25.762 | EX18: 3.016 | EY18: -3.717 | EZ18: 0.401 | FB18: 25.462 | FC18: 2.705 | FD18: -3.615 | FE18: 0.234 | FG18: 24.787 | FH18: 3.056 | FI18: -3.598 | FJ18: 0.536 | FL18: 24.781 | FM18: 3.429 | FN18: -3.646 | FO18: 0.514 | FQ18: 25.077 | FR18: 3.247 | FS18: -3.639 | FT18: 0.294 | FV18: 24.979 | FW18: 2.964 | FX18: -3.589 | FY18: -0.006 | GA18: 24.349 | GB18: 2.986 | GC18: -3.495 | GD18: -0.229 | GF18: 23.611 | GG18: 2.87 | GH18: -3.394 | GI18: -0.025 | GK18: 23.062 | GL18: 2.999 | GM18: -3.373 | GN18: 0.38 | GP18: 23.068 | GQ18: 3.127 | GR18: -3.415 | GS18: 0.52 | GU18: 23.3 | GV18: 3.354 | GW18: -3.462 | GX18: 0.472 | GZ18: 23.663 | HA18: 3.491 | HB18: -3.526 | HC18: 0.583 | HE18: 24.211 | HF18: 3.482 | HG18: -3.613 | HH18: 0.865 | HJ18: 24.945 | HK18: 3.165 | HL18: -3.669 | HM18: 1.512 | HO18: 25.953 | HP18: 3.293 | HQ18: -3.918 | HR18: 1.344 | HT18: 26.671 | HU18: 2.73 | HV18: -3.846 | HW18: 0.322 | HY18: 25.877
A19: N114 | B19: Systèmes d’armes
A20: N115 | B20: Ressources biologiques cultivées | C20: 9.542 | D20: 0.391 | E20: -0.172 | F20: 0.378 | H20: 10.139 | I20: 0.404 | J20: -0.212 | K20: 0.727 | M20: 11.057 | N20: 0.523 | O20: -0.223 | P20: 0.749 | R20: 12.106 | S20: 0.595 | T20: -0.258 | U20: 1.846 | W20: 14.289 | X20: 0.605 | Y20: -0.284 | Z20: 0.376 | AB20: 14.986 | AC20: 0.461 | AD20: -0.317 | AE20: 0.246 | AG20: 15.377 | AH20: 0.57 | AI20: -0.34 | AJ20: 0.154 | AL20: 15.76 | AM20: 0.47 | AN20: -0.376 | AO20: -0.591 | AQ20: 15.262 | AR20: 0.475 | AS20: -0.379 | AT20: -0.357 | AV20: 15.001 | AW20: 0.568 | AX20: -0.385 | AY20: 1.294 | BA20: 16.478 | BB20: 0.593 | BC20: -0.386 | BD20: 0.716 | BF20: 17.401 | BG20: 0.828 | BH20: -0.345 | BI20: -0.874 | BK20: 17.011 | BL20: 0.577 | BM20: -0.37 | BN20: -1.15 | BP20: 16.068 | BQ20: 0.6 | BR20: -0.333 | BS20: -0.907 | BU20: 15.428 | BV20: 0.505 | BW20: -0.326 | BX20: -0.839 | BZ20: 14.768 | CA20: 0.508 | CB20: -0.303 | CC20: -0.513 | CE20: 14.461 | CF20: 0.538 | CG20: -0.289 | CH20: -1.705 | CJ20: 13.004 | CK20: 0.457 | CL20: -0.291 | CM20: -1.423 | CO20: 11.747 | CP20: 0.396 | CQ20: -0.292 | CR20: -0.214 | CT20: 11.637 | CU20: 0.419 | CV20: -0.291 | CW20: -0.332 | CY20: 11.434 | CZ20: 0.456 | DA20: -0.27 | DB20: -1.068 | DD20: 10.552 | DE20: 0.483 | DF20: -0.26 | DG20: -0.558 | DI20: 10.217 | DJ20: 0.413 | DK20: -0.256 | DL20: -0.484 | DN20: 9.891 | DO20: 0.283 | DP20: -0.27 | DQ20: -0.157 | DS20: 9.746 | DT20: 0.233 | DU20: -0.284 | DV20: -0.137 | DX20: 9.559 | DY20: 0.274 | DZ20: -0.257 | EA20: -0.568 | EC20: 9.008 | ED20: 0.323 | EE20: -0.246 | EF20: -0.505 | EH20: 8.58 | EI20: 0.304 | EJ20: -0.244 | EK20: -0.339 | EM20: 8.301 | EN20: 0.331 | EO20: -0.246 | EP20: -0.179 | ER20: 8.207 | ES20: 0.252 | ET20: -0.201 | EU20: -0.823 | EW20: 7.434 | EX20: 0.242 | EY20: -0.219 | EZ20: -0.025 | FB20: 7.432 | FC20: 0.236 | FD20: -0.213 | FE20: -0.297 | FG20: 7.158 | FH20: 0.22 | FI20: -0.218 | FJ20: -0.206 | FL20: 6.954 | FM20: 0.266 | FN20: -0.206 | FO20: -0.311 | FQ20: 6.704 | FR20: 0.303 | FS20: -0.197 | FT20: -0.219 | FV20: 6.591 | FW20: 0.315 | FX20: -0.187 | FY20: -0.363 | GA20: 6.357 | GB20: 0.316 | GC20: -0.177 | GD20: -0.389 | GF20: 6.108 | GG20: 0.273 | GH20: -0.164 | GI20: -0.297 | GK20: 5.919 | GL20: 0.243 | GM20: -0.156 | GN20: -0.353 | GP20: 5.653 | GQ20: 0.205 | GR20: -0.154 | GS20: -0.255 | GU20: 5.449 | GV20: 0.216 | GW20: -0.165 | GX20: 0.179 | GZ20: 5.679 | HA20: 0.229 | HB20: -0.153 | HC20: -0.33 | HE20: 5.425 | HF20: 0.25 | HG20: -0.155 | HH20: -0.291 | HJ20: 5.229 | HK20: 0.267 | HL20: -0.167 | HM20: 0.286 | HO20: 5.614 | HP20: 0.285 | HQ20: -0.177 | HR20: -0.732 | HT20: 4.99 | HU20: 0.286 | HV20: -0.161 | HW20: 0.1 | HY20: 5.215
A21: N117 | B21: Droits de propriété intellectuelle | C21: 1.193 | D21: 0.324 | E21: -0.317 | F21: 0.131 | H21: 1.33 | I21: 0.369 | J21: -0.358 | K21: 0.164 | M21: 1.504 | N21: 0.394 | O21: -0.405 | P21: 0.196 | R21: 1.69 | S21: 0.429 | T21: -0.452 | U21: 0.165 | W21: 1.832 | X21: 0.447 | Y21: -0.48 | Z21: 0.125 | AB21: 1.924 | AC21: 0.497 | AD21: -0.509 | AE21: 0.104 | AG21: 2.015 | AH21: 0.538 | AI21: -0.535 | AJ21: 0.077 | AL21: 2.095 | AM21: 0.627 | AN21: -0.572 | AO21: 0.068 | AQ21: 2.218 | AR21: 0.662 | AS21: -0.608 | AT21: 0.059 | AV21: 2.332 | AW21: 0.7 | AX21: -0.647 | AY21: 0.064 | BA21: 2.449 | BB21: 0.829 | BC21: -0.702 | BD21: 0.031 | BF21: 2.607 | BG21: 0.818 | BH21: -0.732 | BI21: 0.053 | BK21: 2.746 | BL21: 0.749 | BM21: -0.772 | BN21: 0.062 | BP21: 2.784 | BQ21: 0.782 | BR21: -0.788 | BS21: -0.001 | BU21: 2.777 | BV21: 0.72 | BW21: -0.781 | BX21: 0.004 | BZ21: 2.719 | CA21: 0.831 | CB21: -0.8 | CC21: 0.007 | CE21: 2.757 | CF21: 0.843 | CG21: -0.813 | CH21: 0.005 | CJ21: 2.792 | CK21: 0.769 | CL21: -0.816 | CM21: 0.029 | CO21: 2.774 | CP21: 0.771 | CQ21: -0.824 | CR21: 0.038 | CT21: 2.759 | CU21: 0.843 | CV21: -0.835 | CW21: 0.027 | CY21: 2.793 | CZ21: 0.846 | DA21: -0.841 | DB21: 0.084 | DD21: 2.882 | DE21: 0.929 | DF21: -0.895 | DG21: 0.119 | DI21: 3.034 | DJ21: 1.017 | DK21: -0.945 | DL21: 0.074 | DN21: 3.179 | DO21: 0.989 | DP21: -0.977 | DQ21: -0.005 | DS21: 3.186 | DT21: 0.993 | DU21: -0.973 | DV21: -0.023 | DX21: 3.184 | DY21: 0.997 | DZ21: -0.985 | EA21: 0.044 | EC21: 3.241 | ED21: 1.016 | EE21: -1.021 | EF21: 0.076 | EH21: 3.312 | EI21: 1.054 | EJ21: -1.053 | EK21: 0.057 | EM21: 3.369 | EN21: 1.173 | EO21: -1.095 | EP21: 0.044 | ER21: 3.491 | ES21: 1.07 | ET21: -1.108 | EU21: 0.029 | EW21: 3.482 | EX21: 0.877 | EY21: -1.077 | EZ21: 0.005 | FB21: 3.287 | FC21: 0.896 | FD21: -1.044 | FE21: 0.025 | FG21: 3.164 | FH21: 0.949 | FI21: -1.031 | FJ21: 0.05 | FL21: 3.132 | FM21: 1.019 | FN21: -1.027 | FO21: 0.044 | FQ21: 3.167 | FR21: 1.019 | FS21: -1.031 | FT21: 0.018 | FV21: 3.173 | FW21: 1.037 | FX21: -1.038 | FY21: -0.001 | GA21: 3.171 | GB21: 1.056 | GC21: -1.047 | GD21: -0.011 | GF21: 3.169 | GG21: 1.1 | GH21: -1.064 | GI21: -0.009 | GK21: 3.197 | GL21: 1.173 | GM21: -1.094 | GN21: 0.02 | GP21: 3.296 | GQ21: 1.308 | GR21: -1.155 | GS21: 0.025 | GU21: 3.474 | GV21: 1.417 | GW21: -1.226 | GX21: 0.014 | GZ21: 3.678 | HA21: 1.516 | HB21: -1.309 | HC21: 0.004 | HE21: 3.888 | HF21: 1.993 | HG21: -1.469 | HH21: 0.059 | HJ21: 4.472 | HK21: 2.236 | HL21: -1.69 | HM21: 0.111 | HO21: 5.129 | HP21: 2.495 | HQ21: -1.939 | HR21: 0.118 | HT21: 5.803 | HU21: 2.7 | HV21: -2.196 | HW21: 0.132 | HY21: 6.439
A22: N1171 | B22: Recherche et développement | C22: 0.889 | D22: 0.178 | E22: -0.186 | F22: 0.086 | H22: 0.967 | I22: 0.202 | J22: -0.205 | K22: 0.123 | M22: 1.087 | N22: 0.226 | O22: -0.234 | P22: 0.152 | R22: 1.232 | S22: 0.255 | T22: -0.263 | U22: 0.124 | W22: 1.348 | X22: 0.252 | Y22: -0.278 | Z22: 0.09 | AB22: 1.413 | AC22: 0.258 | AD22: -0.29 | AE22: 0.069 | AG22: 1.449 | AH22: 0.263 | AI22: -0.296 | AJ22: 0.048 | AL22: 1.465 | AM22: 0.271 | AN22: -0.3 | AO22: 0.036 | AQ22: 1.472 | AR22: 0.292 | AS22: -0.302 | AT22: 0.025 | AV22: 1.488 | AW22: 0.306 | AX22: -0.305 | AY22: 0.028 | BA22: 1.517 | BB22: 0.343 | BC22: -0.313 | BD22: 0.019 | BF22: 1.566 | BG22: 0.336 | BH22: -0.316 | BI22: 0.025 | BK22: 1.611 | BL22: 0.307 | BM22: -0.323 | BN22: 0.034 | BP22: 1.629 | BQ22: 0.283 | BR22: -0.323 | BS22: 0.007 | BU22: 1.596 | BV22: 0.253 | BW22: -0.313 | BX22: 0.001 | BZ22: 1.536 | CA22: 0.264 | CB22: -0.309 | CC22: -0.004 | CE22: 1.488 | CF22: 0.273 | CG22: -0.299 | CH22: -0.008 | CJ22: 1.454 | CK22: 0.282 | CL22: -0.296 | CM22: 0.009 | CO22: 1.449 | CP22: 0.275 | CQ22: -0.294 | CR22: 0.01 | CT22: 1.44 | CU22: 0.282 | CV22: -0.292 | CW22: 0.007 | CY22: 1.437 | CZ22: 0.282 | DA22: -0.291 | DB22: 0.037 | DD22: 1.466 | DE22: 0.275 | DF22: -0.3 | DG22: 0.057 | DI22: 1.498 | DJ22: 0.268 | DK22: -0.304 | DL22: 0.033 | DN22: 1.495 | DO22: 0.252 | DP22: -0.3 | DQ22: 0.024 | DS22: 1.471 | DT22: 0.235 | DU22: -0.297 | DV22: 0.037 | DX22: 1.447 | DY22: 0.244 | DZ22: -0.296 | EA22: 0.054 | EC22: 1.449 | ED22: 0.23 | EE22: -0.298 | EF22: 0.054 | EH22: 1.434 | EI22: 0.234 | EJ22: -0.295 | EK22: 0.039 | EM22: 1.412 | EN22: 0.254 | EO22: -0.293 | EP22: 0.044 | ER22: 1.417 | ES22: 0.255 | ET22: -0.295 | EU22: 0.037 | EW22: 1.414 | EX22: 0.212 | EY22: -0.286 | EZ22: 0.013 | FB22: 1.353 | FC22: 0.197 | FD22: -0.273 | FE22: 0.02 | FG22: 1.297 | FH22: 0.223 | FI22: -0.27 | FJ22: 0.041 | FL22: 1.291 | FM22: 0.225 | FN22: -0.27 | FO22: 0.03 | FQ22: 1.277 | FR22: 0.208 | FS22: -0.262 | FT22: 0.008 | FV22: 1.232 | FW22: 0.186 | FX22: -0.25 | FY22: -0.006 | GA22: 1.162 | GB22: 0.177 | GC22: -0.235 | GD22: -0.015 | GF22: 1.088 | GG22: 0.171 | GH22: -0.221 | GI22: -0.006 | GK22: 1.032 | GL22: 0.142 | GM22: -0.21 | GN22: 0.014 | GP22: 0.979 | GQ22: 0.159 | GR22: -0.204 | GS22: 0.02 | GU22: 0.953 | GV22: 0.149 | GW22: -0.197 | GX22: 0.012 | GZ22: 0.917 | HA22: 0.142 | HB22: -0.189 | HC22: 0.004 | HE22: 0.874 | HF22: 0.138 | HG22: -0.18 | HH22: 0.013 | HJ22: 0.845 | HK22: 0.134 | HL22: -0.176 | HM22: 0.019 | HO22: 0.822 | HP22: 0.136 | HQ22: -0.171 | HR22: 0.017 | HT22: 0.805 | HU22: 0.13 | HV22: -0.167 | HW22: 0.02 | HY22: 0.788
A23: N1173 | B23: Logiciels et bases de données | C23: 0.304 | D23: 0.146 | E23: -0.131 | F23: 0.044 | H23: 0.363 | I23: 0.166 | J23: -0.153 | K23: 0.041 | M23: 0.417 | N23: 0.169 | O23: -0.171 | P23: 0.043 | R23: 0.458 | S23: 0.174 | T23: -0.189 | U23: 0.041 | W23: 0.484 | X23: 0.195 | Y23: -0.202 | Z23: 0.035 | AB23: 0.511 | AC23: 0.239 | AD23: -0.219 | AE23: 0.035 | AG23: 0.566 | AH23: 0.274 | AI23: -0.239 | AJ23: 0.028 | AL23: 0.629 | AM23: 0.356 | AN23: -0.272 | AO23: 0.032 | AQ23: 0.745 | AR23: 0.37 | AS23: -0.306 | AT23: 0.034 | AV23: 0.843 | AW23: 0.394 | AX23: -0.342 | AY23: 0.036 | BA23: 0.931 | BB23: 0.485 | BC23: -0.389 | BD23: 0.012 | BF23: 1.04 | BG23: 0.48 | BH23: -0.415 | BI23: 0.027 | BK23: 1.133 | BL23: 0.441 | BM23: -0.448 | BN23: 0.028 | BP23: 1.153 | BQ23: 0.497 | BR23: -0.464 | BS23: -0.009 | BU23: 1.178 | BV23: 0.466 | BW23: -0.466 | BX23: 0.003 | BZ23: 1.181 | CA23: 0.565 | CB23: -0.49 | CC23: 0.011 | CE23: 1.267 | CF23: 0.569 | CG23: -0.512 | CH23: 0.013 | CJ23: 1.336 | CK23: 0.485 | CL23: -0.519 | CM23: 0.02 | CO23: 1.323 | CP23: 0.494 | CQ23: -0.528 | CR23: 0.029 | CT23: 1.317 | CU23: 0.56 | CV23: -0.542 | CW23: 0.019 | CY23: 1.354 | CZ23: 0.562 | DA23: -0.549 | DB23: 0.047 | DD23: 1.414 | DE23: 0.65 | DF23: -0.594 | DG23: 0.061 | DI23: 1.532 | DJ23: 0.746 | DK23: -0.639 | DL23: 0.041 | DN23: 1.68 | DO23: 0.732 | DP23: -0.674 | DQ23: -0.028 | DS23: 1.71 | DT23: 0.756 | DU23: -0.673 | DV23: -0.06 | DX23: 1.733 | DY23: 0.751 | DZ23: -0.686 | EA23: -0.011 | EC23: 1.788 | ED23: 0.783 | EE23: -0.72 | EF23: 0.022 | EH23: 1.873 | EI23: 0.816 | EJ23: -0.755 | EK23: 0.018 | EM23: 1.952 | EN23: 0.915 | EO23: -0.798 | EP23: 0 | ER23: 2.069 | ES23: 0.812 | ET23: -0.81 | EU23: -0.008 | EW23: 2.063 | EX23: 0.661 | EY23: -0.788 | EZ23: -0.007 | FB23: 1.929 | FC23: 0.695 | FD23: -0.767 | FE23: 0.004 | FG23: 1.861 | FH23: 0.726 | FI23: -0.758 | FJ23: 0.009 | FL23: 1.838 | FM23: 0.786 | FN23: -0.754 | FO23: 0.013 | FQ23: 1.883 | FR23: 0.808 | FS23: -0.766 | FT23: 0.01 | FV23: 1.935 | FW23: 0.85 | FX23: -0.785 | FY23: 0.005 | GA23: 2.005 | GB23: 0.878 | GC23: -0.809 | GD23: 0.004 | GF23: 2.078 | GG23: 0.927 | GH23: -0.84 | GI23: -0.003 | GK23: 2.162 | GL23: 1.029 | GM23: -0.883 | GN23: 0.005 | GP23: 2.314 | GQ23: 1.147 | GR23: -0.948 | GS23: 0.006 | GU23: 2.518 | GV23: 1.265 | GW23: -1.027 | GX23: 0.002 | GZ23: 2.758 | HA23: 1.371 | HB23: -1.118 | HC23: -0.001 | HE23: 3.01 | HF23: 1.852 | HG23: -1.286 | HH23: 0.046 | HJ23: 3.622 | HK23: 2.097 | HL23: -1.511 | HM23: 0.093 | HO23: 4.301 | HP23: 2.352 | HQ23: -1.764 | HR23: 0.101 | HT23: 4.99 | HU23: 2.562 | HV23: -2.024 | HW23: 0.113 | HY23: 5.642
A24: N1174 | B24: Œuvres récréatives, littéraires ou artistiques originales | C24: 0 | D24: 0 | E24: 0 | F24: 0 | H24: 0 | I24: 0 | J24: 0 | K24: 0 | M24: 0 | N24: 0 | O24: 0 | P24: 0 | R24: 0 | S24: 0 | T24: 0 | U24: 0 | W24: 0 | X24: 0 | Y24: 0 | Z24: 0 | AB24: 0 | AC24: 0 | AD24: 0 | AE24: 0 | AG24: 0 | AH24: 0 | AI24: 0 | AJ24: 0.001 | AL24: 0.001 | AM24: 0 | AN24: 0 | AO24: 0 | AQ24: 0.001 | AR24: 0.001 | AS24: 0 | AT24: 0 | AV24: 0.001 | AW24: 0.001 | AX24: -0.001 | AY24: 0 | BA24: 0.001 | BB24: 0.001 | BC24: -0.001 | BD24: 0 | BF24: 0.001 | BG24: 0.001 | BH24: -0.001 | BI24: 0.001 | BK24: 0.002 | BL24: 0.001 | BM24: -0.001 | BN24: 0 | BP24: 0.002 | BQ24: 0.002 | BR24: -0.001 | BS24: 0.001 | BU24: 0.003 | BV24: 0.001 | BW24: -0.002 | BX24: -0.001 | BZ24: 0.002 | CA24: 0.001 | CB24: -0.002 | CC24: 0 | CE24: 0.002 | CF24: 0.001 | CG24: -0.002 | CH24: 0 | CJ24: 0.002 | CK24: 0.002 | CL24: -0.001 | CM24: 0 | CO24: 0.002 | CP24: 0.002 | CQ24: -0.001 | CR24: 0 | CT24: 0.002 | CU24: 0.001 | CV24: -0.002 | CW24: 0 | CY24: 0.002 | CZ24: 0.001 | DA24: -0.002 | DB24: 0 | DD24: 0.002 | DE24: 0.003 | DF24: -0.002 | DG24: 0.001 | DI24: 0.004 | DJ24: 0.003 | DK24: -0.002 | DL24: 0 | DN24: 0.004 | DO24: 0.004 | DP24: -0.003 | DQ24: 0 | DS24: 0.005 | DT24: 0.002 | DU24: -0.003 | DV24: 0 | DX24: 0.004 | DY24: 0.002 | DZ24: -0.003 | EA24: 0.001 | EC24: 0.004 | ED24: 0.003 | EE24: -0.003 | EF24: 0.001 | EH24: 0.005 | EI24: 0.003 | EJ24: -0.003 | EK24: 0 | EM24: 0.005 | EN24: 0.003 | EO24: -0.003 | EP24: 0 | ER24: 0.005 | ES24: 0.004 | ET24: -0.003 | EU24: 0 | EW24: 0.005 | EX24: 0.004 | EY24: -0.004 | EZ24: 0 | FB24: 0.005 | FC24: 0.004 | FD24: -0.004 | FE24: 0.001 | FG24: 0.006 | FH24: 0.001 | FI24: -0.003 | FJ24: -0.001 | FL24: 0.003 | FM24: 0.008 | FN24: -0.004 | FO24: 0 | FQ24: 0.007 | FR24: 0.003 | FS24: -0.004 | FT24: 0 | FV24: 0.006 | FW24: 0.002 | FX24: -0.004 | FY24: 0 | GA24: 0.004 | GB24: 0.002 | GC24: -0.003 | GD24: 0 | GF24: 0.003 | GG24: 0.002 | GH24: -0.002 | GI24: 0 | GK24: 0.003 | GL24: 0.002 | GM24: -0.002 | GN24: 0 | GP24: 0.003 | GQ24: 0.002 | GR24: -0.002 | GS24: 0 | GU24: 0.003 | GV24: 0.002 | GW24: -0.002 | GX24: 0 | GZ24: 0.003 | HA24: 0.003 | HB24: -0.002 | HC24: 0.001 | HE24: 0.004 | HF24: 0.004 | HG24: -0.003 | HH24: 0 | HJ24: 0.005 | HK24: 0.006 | HL24: -0.003 | HM24: -0.001 | HO24: 0.007 | HP24: 0.007 | HQ24: -0.004 | HR24: 0 | HT24: 0.009 | HU24: 0.007 | HV24: -0.005 | HW24: -0.002 | HY24: 0.009
A25: N12 | B25: Stocks par type de stocks | C25: 8.086 | D25: 0.864 | F25: 0.402 | H25: 9.352 | I25: 0.891 | K25: 0.714 | M25: 10.957 | N25: -0.471 | P25: 1.802 | R25: 12.288 | S25: -0.14 | U25: 0.52 | W25: 12.668 | X25: -0.71 | Z25: 0.975 | AB25: 12.933 | AC25: -0.202 | AE25: -0.042 | AG25: 12.688 | AH25: -1.255 | AJ25: 1.243 | AL25: 12.676 | AM25: -0.768 | AO25: 0.125 | AQ25: 12.034 | AR25: 0.655 | AT25: -1.2 | AV25: 11.489 | AW25: 0.709 | AY25: -0.388 | BA25: 11.81 | BB25: 0.793 | BD25: -0.147 | BF25: 12.457 | BG25: 0.642 | BI25: -0.368 | BK25: 12.731 | BL25: 0.346 | BN25: -0.256 | BP25: 12.821 | BQ25: -0.099 | BS25: -0.025 | BU25: 12.698 | BV25: -0.189 | BX25: -0.246 | BZ25: 12.262 | CA25: 0.275 | CC25: -0.045 | CE25: 12.493 | CF25: 0.541 | CH25: 0.524 | CJ25: 13.558 | CK25: 0.317 | CM25: -0.043 | CO25: 13.832 | CP25: -0.044 | CR25: 0.343 | CT25: 14.131 | CU25: 0.463 | CW25: -0.292 | CY25: 14.302 | CZ25: 0.665 | DB25: 0.495 | DC25: -0.837 | DD25: 14.624 | DE25: 0.507 | DG25: -0.904 | DH25: 0 | DI25: 14.228 | DJ25: 1.194 | DL25: -1.85 | DM25: 0 | DN25: 13.572 | DO25: 0.846 | DQ25: -1.259 | DR25: 0 | DS25: 13.159 | DT25: 0.872 | DV25: -1.388 | DW25: 0 | DX25: 12.642 | DY25: 3.757 | EA25: -3.545 | EB25: 0 | EC25: 12.854 | ED25: 0.376 | EF25: 0.026 | EG25: 0 | EH25: 13.257 | EI25: 0.551 | EK25: 0.569 | EL25: 0 | EM25: 14.376 | EN25: 0.654 | EP25: 1.209 | EQ25: 0 | ER25: 16.239 | ES25: 0.342 | EU25: -0.68 | EV25: 0 | EW25: 15.901 | EX25: -0.27 | EZ25: -2.02 | FA25: -0.173 | FB25: 13.437 | FC25: 0.001 | FE25: 0.087 | FG25: 13.525 | FH25: 0.618 | FJ25: -1.038 | FL25: 13.105 | FM25: -0.433 | FO25: -0.063 | FQ25: 12.609 | FR25: -0.242 | FT25: 0.877 | FV25: 13.244 | FW25: 0.074 | FY25: 1.197 | GA25: 14.515 | GB25: 0.764 | GD25: -0.798 | GF25: 14.481 | GG25: 0.329 | GI25: -0.771 | GK25: 14.038 | GL25: 0.581 | GN25: -1.076 | GP25: 13.543 | GQ25: 1.479 | GS25: -0.862 | GU25: 14.16 | GV25: 0.419 | GX25: -1.265 | GZ25: 13.314 | HA25: 0.474 | HC25: -1.113 | HE25: 12.675 | HF25: 1.327 | HH25: 0.945 | HJ25: 14.947 | HK25: 2.178 | HM25: 1.585 | HO25: 18.71 | HP25: 0.828 | HR25: -1.392 | HT25: 18.146 | HU25: 0.315 | HW25: -0.76 | HY25: 17.7
A26: N13 | B26: Objets de valeur | C26: 43.579 | D26: 0.289 | F26: 5.937 | H26: 49.805 | I26: 0.344 | K26: 2.232 | M26: 52.38 | N26: 0.377 | P26: -2.745 | R26: 50.012 | S26: 0.379 | U26: 5.496 | W26: 55.888 | X26: 0.504 | Z26: 10.347 | AB26: 66.738 | AC26: 0.523 | AE26: -2.636 | AG26: 64.626 | AH26: 0.561 | AJ26: -6.041 | AL26: 59.145 | AM26: 0.585 | AO26: -0.296 | AQ26: 59.435 | AR26: 0.598 | AT26: 1.492 | AV26: 61.525 | AW26: 0.648 | AY26: -3.402 | BA26: 58.771 | BB26: 0.752 | BD26: -6.177 | BF26: 53.346 | BG26: 0.825 | BI26: -4.996 | BK26: 49.174 | BL26: 0.78 | BN26: -3.658 | BP26: 46.296 | BQ26: 0.691 | BS26: -2.189 | BU26: 44.798 | BV26: 0.675 | BX26: 0.846 | BZ26: 46.319 | CA26: 0.673 | CC26: -1.701 | CE26: 45.291 | CF26: 0.7 | CH26: -1.066 | CJ26: 44.925 | CK26: 0.684 | CM26: -0.225 | CO26: 45.384 | CP26: 0.774 | CR26: -2.596 | CT26: 43.562 | CU26: 0.876 | CW26: 0.615 | CY26: 45.052 | CZ26: 0.985 | DB26: 7.038 | DD26: 53.075 | DE26: 1.022 | DG26: 8.877 | DI26: 62.973 | DJ26: 1.019 | DL26: 14.149 | DN26: 78.141 | DO26: 0.952 | DQ26: 7.949 | DS26: 87.042 | DT26: 0.71 | DV26: 0.344 | DX26: 88.096 | DY26: 0.819 | EA26: 6.688 | EC26: 95.603 | ED26: 0.947 | EF26: 13.818 | EH26: 110.368 | EI26: 1.008 | EK26: 9.722 | EM26: 121.097 | EN26: 1.033 | EP26: -2.358 | ER26: 119.772 | ES26: 0.91 | EU26: -10.742 | EW26: 109.941 | EX26: 0.514 | EZ26: 3.886 | FB26: 114.34 | FC26: 0.675 | FE26: 18.922 | FG26: 133.937 | FH26: 0.67 | FJ26: 4.62 | FL26: 139.227 | FM26: 0.71 | FO26: -4.873 | FQ26: 135.065 | FR26: 0.652 | FT26: -2.791 | FV26: 132.926 | FW26: 0.581 | FY26: 0.498 | GA26: 134.004 | GB26: 0.611 | GD26: -2.365 | GF26: 132.25 | GG26: 0.635 | GI26: 1.38 | GK26: 134.265 | GL26: 0.65 | GN26: 7.96 | GP26: 142.875 | GQ26: 0.701 | GS26: -0.489 | GU26: 143.086 | GV26: 0.804 | GX26: -2.403 | GZ26: 141.487 | HA26: 0.666 | HC26: 10.364 | HE26: 152.517 | HF26: 0.85 | HH26: 32.674 | HJ26: 186.041 | HK26: 1.087 | HM26: 18.047 | HO26: 205.174 | HP26: 1.238 | HR26: -5.218 | HT26: 201.194 | HU26: 1.247 | HW26: -0.927 | HY26: 201.514
A27: N2 | B27: Actifs non financiers non produits | C27: 292.247 | D27: -0.445 | F27: 29.815 | G27: 6.509 | H27: 328.127 | I27: -0.492 | K27: 27.023 | L27: 6.866 | M27: 361.523 | N27: -0.491 | P27: 30.809 | Q27: 5.032 | R27: 396.874 | S27: -0.51 | U27: 14.727 | V27: 3.072 | W27: 414.164 | X27: -0.524 | Z27: 25.358 | AA27: 6.8 | AB27: 445.798 | AC27: -0.569 | AE27: -5.586 | AF27: 5.937 | AG27: 445.58 | AH27: -0.453 | AJ27: 13.102 | AK27: 0.229 | AL27: 458.458 | AM27: -0.462 | AO27: 28.88 | AP27: 0.381 | AQ27: 487.256 | AR27: -0.47 | AT27: 36.106 | AU27: -8.864 | AV27: 514.029 | AW27: -0.577 | AY27: 65.413 | AZ27: -1.862 | BA27: 577.002 | BB27: -0.998 | BD27: 82.815 | BE27: 4.078 | BF27: 662.898 | BG27: -1.013 | BI27: 46.375 | BJ27: 14.952 | BK27: 723.212 | BL27: -1.127 | BN27: -37.355 | BO27: 2.088 | BP27: 686.818 | BQ27: -0.906 | BS27: -71.165 | BT27: 0.805 | BU27: 615.552 | BV27: -0.768 | BX27: -44.766 | BY27: 2.68 | BZ27: 572.699 | CA27: -0.475 | CC27: 13.57 | CD27: 3.587 | CE27: 589.381 | CF27: -1.008 | CH27: -55.999 | CI27: 3.403 | CJ27: 535.778 | CK27: -0.768 | CM27: -12.166 | CN27: 3.338 | CO27: 526.183 | CP27: -1.689 | CR27: -12.413 | CS27: 0.986 | CT27: 513.067 | CU27: -1.654 | CW27: 78.364 | CX27: 3.243 | CY27: 593.02 | CZ27: -1.641 | DB27: 187.745 | DC27: 5.049 | DD27: 784.173 | DE27: -2.676 | DG27: 178.152 | DH27: 10.394 | DI27: 970.043 | DJ27: -1.812 | DL27: 163.48 | DM27: 14.174 | DN27: 1145.885 | DO27: -2.176 | DQ27: 284.46 | DR27: 18.936 | DS27: 1447.105 | DT27: -2.125 | DV27: 407.231 | DW27: 18.898 | DX27: 1871.108 | DY27: -2.58 | EA27: 548.317 | EB27: 30.21 | EC27: 2447.055 | ED27: -2.885 | EF27: 612.52 | EG27: 32.863 | EH27: 3089.554 | EI27: -3.419 | EK27: 426.88 | EL27: 33.489 | EM27: 3546.503 | EN27: -3.993 | EP27: 172.808 | EQ27: 93.928 | ER27: 3809.246 | ES27: -2.903 | EU27: -438.689 | EV27: 37.753 | EW27: 3405.406 | EX27: -3.561 | EZ27: -104.76 | FA27: -17.953 | FB27: 3279.131 | FC27: -3.153 | FE27: 427.371 | FF27: 8.169 | FG27: 3711.518 | FH27: -3.883 | FJ27: 113.493 | FK27: 39.609 | FL27: 3860.736 | FM27: -3.951 | FO27: -168.971 | FP27: 41.397 | FQ27: 3729.211 | FR27: -3.409 | FT27: -176.305 | FU27: 55.48 | FV27: 3604.976 | FW27: -3.665 | FY27: -185.873 | FZ27: 37.632 | GA27: 3453.071 | GB27: -3.344 | GD27: -15.383 | GE27: 36.214 | GF27: 3470.559 | GG27: -3.162 | GI27: 109.977 | GJ27: 35.243 | GK27: 3612.616 | GL27: -3.461 | GN27: 154.863 | GO27: 51.034 | GP27: 3815.053 | GQ27: -3.461 | GS27: 159.625 | GT27: 53.105 | GU27: 4024.322 | GV27: -3.721 | GX27: 231.944 | GY27: 76.795 | GZ27: 4329.34 | HA27: -2.847 | HC27: 315.193 | HD27: 72.782 | HE27: 4714.469 | HF27: -3.064 | HH27: 240.447 | HI27: 82.941 | HJ27: 5034.792 | HK27: -2.823 | HM27: 48.634 | HN27: 87.294 | HO27: 5167.898 | HP27: -3.492 | HR27: -510.113 | HS27: 71.133 | HT27: 4725.426 | HU27: -3.994 | HW27: -193.72 | HX27: 78.249 | HY27: 4605.961
A28: N21 | B28: Ressources naturelles | C28: 279.183 | D28: -0.445 | F28: 29.815 | G28: 4.996 | H28: 313.549 | I28: -0.492 | K28: 27.023 | L28: 5.284 | M28: 345.364 | N28: -0.491 | P28: 30.809 | Q28: 3.512 | R28: 379.195 | S28: -0.51 | U28: 14.727 | V28: 1.694 | W28: 395.107 | X28: -0.524 | Z28: 25.358 | AA28: 5.62 | AB28: 425.561 | AC28: -0.569 | AE28: -5.586 | AF28: 5.057 | AG28: 424.463 | AH28: -0.453 | AJ28: 13.102 | AK28: -0.411 | AL28: 436.702 | AM28: -0.462 | AO28: 28.88 | AP28: -0.077 | AQ28: 465.043 | AR28: -0.47 | AT28: 36.106 | AU28: -9.279 | AV28: 491.4 | AW28: -0.577 | AY28: 65.413 | AZ28: -2.812 | BA28: 553.424 | BB28: -0.998 | BD28: 82.815 | BE28: 2.726 | BF28: 637.967 | BG28: -1.013 | BI28: 46.375 | BJ28: 14.414 | BK28: 697.744 | BL28: -1.127 | BN28: -37.355 | BO28: 2.476 | BP28: 661.738 | BQ28: -0.906 | BS28: -71.165 | BT28: 1.484 | BU28: 591.151 | BV28: -0.768 | BX28: -44.766 | BY28: 3.198 | BZ28: 548.815 | CA28: -0.475 | CC28: 13.57 | CD28: 3.434 | CE28: 565.345 | CF28: -1.008 | CH28: -55.999 | CI28: 2.946 | CJ28: 511.284 | CK28: -0.768 | CM28: -12.166 | CN28: 2.995 | CO28: 501.346 | CP28: -1.689 | CR28: -12.413 | CS28: 0.635 | CT28: 487.878 | CU28: -1.654 | CW28: 78.364 | CX28: 2.822 | CY28: 567.411 | CZ28: -1.641 | DB28: 187.745 | DC28: 4.535 | DD28: 758.05 | DE28: -2.676 | DG28: 178.152 | DH28: 9.82 | DI28: 943.345 | DJ28: -1.812 | DL28: 163.48 | DM28: 13.567 | DN28: 1118.58 | DO28: -2.176 | DQ28: 284.46 | DR28: 17.621 | DS28: 1418.485 | DT28: -2.125 | DV28: 407.231 | DW28: 18.12 | DX28: 1841.711 | DY28: -2.58 | EA28: 548.317 | EB28: 28.597 | EC28: 2416.045 | ED28: -2.885 | EF28: 612.52 | EG28: 33.436 | EH28: 3059.116 | EI28: -3.419 | EK28: 426.88 | EL28: 43.404 | EM28: 3525.981 | EN28: -3.993 | EP28: 172.808 | EQ28: 93.917 | ER28: 3788.713 | ES28: -2.903 | EU28: -438.689 | EV28: 39.267 | EW28: 3386.388 | EX28: -3.561 | EZ28: -104.76 | FA28: -16.564 | FB28: 3261.502 | FC28: -3.153 | FE28: 427.371 | FF28: 9.435 | FG28: 3695.155 | FH28: -3.883 | FJ28: 113.493 | FK28: 40.773 | FL28: 3845.538 | FM28: -3.951 | FO28: -168.971 | FP28: 41.688 | FQ28: 3714.303 | FR28: -3.409 | FT28: -176.305 | FU28: 55.761 | FV28: 3590.349 | FW28: -3.665 | FY28: -185.873 | FZ28: 37.351 | GA28: 3438.163 | GB28: -3.344 | GD28: -15.383 | GE28: 37.191 | GF28: 3456.628 | GG28: -3.162 | GI28: 109.977 | GJ28: 35.827 | GK28: 3599.27 | GL28: -3.461 | GN28: 154.863 | GO28: 51.586 | GP28: 3802.258 | GQ28: -3.461 | GS28: 159.625 | GT28: 53.815 | GU28: 4012.237 | GV28: -3.721 | GX28: 231.944 | GY28: 77.185 | GZ28: 4317.645 | HA28: -2.847 | HC28: 315.193 | HD28: 73.212 | HE28: 4703.203 | HF28: -3.064 | HH28: 240.447 | HI28: 83.162 | HJ28: 5023.748 | HK28: -2.823 | HM28: 48.634 | HN28: 87.71 | HO28: 5157.269 | HP28: -3.492 | HR28: -510.113 | HS28: 71.479 | HT28: 4715.143 | HU28: -3.994 | HW28: -193.72 | HX28: 78.583 | HY28: 4596.012
A29: N211 | B29: Terrains | C29: 279.183 | D29: -0.445 | F29: 29.815 | G29: 4.996 | H29: 313.549 | I29: -0.492 | K29: 27.023 | L29: 5.284 | M29: 345.364 | N29: -0.491 | P29: 30.809 | Q29: 3.512 | R29: 379.195 | S29: -0.51 | U29: 14.727 | V29: 1.694 | W29: 395.107 | X29: -0.524 | Z29: 25.358 | AA29: 5.62 | AB29: 425.561 | AC29: -0.569 | AE29: -5.586 | AF29: 5.057 | AG29: 424.463 | AH29: -0.453 | AJ29: 13.102 | AK29: -0.411 | AL29: 436.702 | AM29: -0.462 | AO29: 28.88 | AP29: -0.077 | AQ29: 465.043 | AR29: -0.47 | AT29: 36.106 | AU29: -9.279 | AV29: 491.4 | AW29: -0.577 | AY29: 65.413 | AZ29: -2.812 | BA29: 553.424 | BB29: -0.998 | BD29: 82.815 | BE29: 2.726 | BF29: 637.967 | BG29: -1.013 | BI29: 46.375 | BJ29: 14.414 | BK29: 697.744 | BL29: -1.127 | BN29: -37.355 | BO29: 2.476 | BP29: 661.738 | BQ29: -0.906 | BS29: -71.165 | BT29: 1.484 | BU29: 591.151 | BV29: -0.768 | BX29: -44.766 | BY29: 3.198 | BZ29: 548.815 | CA29: -0.475 | CC29: 13.57 | CD29: 3.434 | CE29: 565.345 | CF29: -1.008 | CH29: -55.999 | CI29: 2.946 | CJ29: 511.284 | CK29: -0.768 | CM29: -12.166 | CN29: 2.995 | CO29: 501.346 | CP29: -1.689 | CR29: -12.413 | CS29: 0.635 | CT29: 487.878 | CU29: -1.654 | CW29: 78.364 | CX29: 2.822 | CY29: 567.411 | CZ29: -1.641 | DB29: 187.745 | DC29: 4.535 | DD29: 758.05 | DE29: -2.676 | DG29: 178.152 | DH29: 9.82 | DI29: 943.345 | DJ29: -1.812 | DL29: 163.48 | DM29: 13.567 | DN29: 1118.58 | DO29: -2.176 | DQ29: 284.46 | DR29: 17.621 | DS29: 1418.485 | DT29: -2.125 | DV29: 407.231 | DW29: 18.12 | DX29: 1841.711 | DY29: -2.58 | EA29: 548.317 | EB29: 28.597 | EC29: 2416.045 | ED29: -2.885 | EF29: 612.52 | EG29: 33.436 | EH29: 3059.116 | EI29: -3.419 | EK29: 426.88 | EL29: 43.404 | EM29: 3525.981 | EN29: -3.993 | EP29: 172.808 | EQ29: 93.917 | ER29: 3788.713 | ES29: -2.903 | EU29: -438.689 | EV29: 39.267 | EW29: 3386.388 | EX29: -3.561 | EZ29: -104.76 | FA29: -16.564 | FB29: 3261.502 | FC29: -3.153 | FE29: 427.371 | FF29: 9.435 | FG29: 3695.155 | FH29: -3.883 | FJ29: 113.493 | FK29: 40.773 | FL29: 3845.538 | FM29: -3.951 | FO29: -168.971 | FP29: 41.688 | FQ29: 3714.303 | FR29: -3.409 | FT29: -176.305 | FU29: 55.761 | FV29: 3590.349 | FW29: -3.665 | FY29: -185.873 | FZ29: 37.351 | GA29: 3438.163 | GB29: -3.344 | GD29: -15.383 | GE29: 37.191 | GF29: 3456.628 | GG29: -3.162 | GI29: 109.977 | GJ29: 35.827 | GK29: 3599.27 | GL29: -3.461 | GN29: 154.863 | GO29: 51.586 | GP29: 3802.258 | GQ29: -3.461 | GS29: 159.625 | GT29: 53.815 | GU29: 4012.237 | GV29: -3.721 | GX29: 231.944 | GY29: 77.185 | GZ29: 4317.645 | HA29: -2.847 | HC29: 315.193 | HD29: 73.212 | HE29: 4703.203 | HF29: -3.064 | HH29: 240.447 | HI29: 83.162 | HJ29: 5023.748 | HK29: -2.823 | HM29: 48.634 | HN29: 87.71 | HO29: 5157.269 | HP29: -3.492 | HR29: -510.113 | HS29: 71.479 | HT29: 4715.143 | HU29: -3.994 | HW29: -193.72 | HX29: 78.583 | HY29: 4596.012
A30: N2111 | B30: Terrains supportant des bâtiments et des ouvrages de génie civil | C30: 128.64 | F30: 14.831 | G30: 7.655 | H30: 151.127 | K30: 15.989 | L30: 8.501 | M30: 175.616 | P30: 19.588 | Q30: 4.25 | R30: 199.454 | U30: 4.517 | V30: 3.644 | W30: 207.615 | Z30: 15.733 | AA30: 7.264 | AB30: 230.612 | AE30: -7.598 | AF30: 6.583 | AG30: 229.598 | AJ30: 15.373 | AK30: 4.662 | AL30: 249.632 | AO30: 27.595 | AP30: 3.942 | AQ30: 281.169 | AT30: 40.384 | AU30: 3.811 | AV30: 325.365 | AY30: 66.853 | AZ30: 5.185 | BA30: 397.403 | BD30: 73.816 | BE30: 6.863 | BF30: 478.081 | BI30: 33.383 | BJ30: 7.403 | BK30: 518.867 | BN30: -28.951 | BO30: 6.445 | BP30: 496.361 | BS30: -60.204 | BT30: 5.312 | BU30: 441.469 | BX30: -38.567 | BY30: 7.011 | BZ30: 409.912 | CC30: 12.655 | CD30: 7.368 | CE30: 429.935 | CH30: -48.76 | CI30: 7.187 | CJ30: 388.362 | CM30: -12.854 | CN30: 6.004 | CO30: 381.513 | CR30: -13.749 | CS30: 4.05 | CT30: 371.815 | CW30: 64.947 | CX30: 5.638 | CY30: 442.4 | DB30: 163.07 | DC30: 8.679 | DD30: 614.149 | DG30: 153.403 | DH30: 12.338 | DI30: 779.89 | DL30: 140.118 | DM30: 20.171 | DN30: 940.179 | DQ30: 249.764 | DR30: 22.031 | DS30: 1211.974 | DV30: 363.76 | DW30: 23.67 | DX30: 1599.404 | EA30: 493.019 | EB30: 39.031 | EC30: 2131.453 | EF30: 552.552 | EG30: 46.236 | EH30: 2730.241 | EK30: 381.85 | EL30: 54.264 | EM30: 3166.355 | EP30: 142.733 | EQ30: 97.345 | ER30: 3406.434 | EU30: -417.286 | EV30: 43.546 | EW30: 3032.693 | EZ30: -127.934 | FA30: 22.567 | FB30: 2927.326 | FE30: 377.48 | FF30: 16.566 | FG30: 3321.371 | FJ30: 86.977 | FK30: 43.011 | FL30: 3451.359 | FO30: -171.195 | FP30: 45.129 | FQ30: 3325.293 | FT30: -172.733 | FU30: 56.127 | FV30: 3208.688 | FY30: -174.802 | FZ30: 27.898 | GA30: 3061.784 | GD30: -27.774 | GE30: 43.726 | GF30: 3077.736 | GI30: 90.124 | GJ30: 31.307 | GK30: 3199.167 | GN30: 137.955 | GO30: 40.019 | GP30: 3377.141 | GS30: 145.12 | GT30: 40.63 | GU30: 3562.891 | GX30: 199.753 | GY30: 49.069 | GZ30: 3811.713 | HC30: 268.981 | HD30: 55.721 | HE30: 4136.415 | HH30: 208.907 | HI30: 64.047 | HJ30: 4409.369 | HM30: 49.935 | HN30: 66.866 | HO30: 4526.17 | HR30: -452.891 | HS30: 52.037 | HT30: 4125.316 | HW30: -183.855 | HX30: 51.344 | HY30: 3992.805
A31: N2112 | B31: Terrains cultivés | C31: 108.161 | D31: 0 | F31: 7.997 | G31: -2.292 | H31: 113.866 | I31: 0 | K31: 4.81 | L31: -2.957 | M31: 115.719 | N31: 0 | P31: 6.644 | Q31: -0.619 | R31: 121.744 | S31: 0 | U31: 6.26 | V31: -0.924 | W31: 127.08 | X31: 0 | Z31: 5.436 | AA31: -1.445 | AB31: 131.072 | AC31: 0 | AE31: 1.407 | AF31: -1.095 | AG31: 131.384 | AH31: 0 | AJ31: -1.847 | AK31: -3.494 | AL31: 126.043 | AM31: 0 | AO31: 0.056 | AP31: -2.574 | AQ31: 123.524 | AR31: 0 | AT31: -4.594 | AU31: -7.98 | AV31: 110.95 | AW31: 0 | AY31: -2.092 | AZ31: -4.796 | BA31: 104.062 | BB31: 0 | BD31: 2.968 | BE31: -2.791 | BF31: 104.239 | BG31: 0 | BI31: 9.482 | BJ31: 3.373 | BK31: 117.094 | BL31: 0 | BN31: -3.956 | BO31: -4.471 | BP31: 108.667 | BQ31: 0 | BS31: -6.133 | BT31: -4.268 | BU31: 98.266 | BV31: 0 | BX31: -3.941 | BY31: -4.086 | BZ31: 90.24 | CA31: 0 | CC31: 1.48 | CD31: -4.093 | CE31: 87.627 | CF31: 0 | CH31: -0.898 | CI31: -4.924 | CJ31: 81.806 | CK31: 0 | CM31: 0.734 | CN31: -3.358 | CO31: 79.182 | CP31: 0 | CR31: 2.103 | CS31: -4.525 | CT31: 76.76 | CU31: 0 | CW31: 7.271 | CX31: -3.745 | CY31: 80.286 | CZ31: 0.121 | DB31: 11.358 | DC31: -5.364 | DD31: 86.401 | DE31: 0.093 | DG31: 10.537 | DH31: -4.754 | DI31: 92.277 | DJ31: 0.115 | DL31: 9.281 | DM31: -5.858 | DN31: 95.815 | DO31: 0.109 | DQ31: 13.353 | DR31: -3.605 | DS31: 105.672 | DT31: 0.056 | DV31: 15.738 | DW31: -4.593 | DX31: 116.873 | DY31: 0.004 | EA31: 19.701 | EB31: -8.412 | EC31: 128.165 | ED31: -0.039 | EF31: 20.25 | EG31: -11.379 | EH31: 136.998 | EI31: -0.073 | EK31: 14.422 | EL31: -12.029 | EM31: 139.318 | EN31: -0.078 | EP31: 15.084 | EQ31: -7.189 | ER31: 147.135 | ES31: -0.08 | EU31: -2.411 | EV31: -5.764 | EW31: 138.88 | EX31: -0.073 | EZ31: 8.097 | FA31: -21.344 | FB31: 125.56 | FC31: -0.066 | FE31: 17.158 | FF31: -8.988 | FG31: 133.664 | FH31: -0.067 | FJ31: 11.72 | FK31: -4.742 | FL31: 140.576 | FM31: -0.054 | FO31: 5.403 | FP31: -6.197 | FQ31: 139.727 | FR31: -0.045 | FT31: 3.699 | FU31: -3.259 | FV31: 140.122 | FW31: -0.065 | FY31: 0.839 | FZ31: -4.041 | GA31: 136.854 | GB31: -0.093 | GD31: 6.32 | GE31: -7.043 | GF31: 136.038 | GG31: 0.037 | GI31: 7.28 | GJ31: -3.048 | GK31: 140.307 | GL31: 0.039 | GN31: 5.144 | GO31: -1.302 | GP31: 144.188 | GQ31: 0.024 | GS31: 4.624 | GT31: -1.791 | GU31: 147.045 | GV31: -0.042 | GX31: 7.985 | GY31: 12.638 | GZ31: 167.626 | HA31: -0.041 | HC31: 12.194 | HD31: 1.041 | HE31: 180.821 | HF31: -0.039 | HH31: 8.868 | HI31: 1.061 | HJ31: 190.711 | HK31: -0.037 | HM31: 2.834 | HN31: 1.301 | HO31: 194.808 | HP31: -0.037 | HR31: -13.831 | HS31: 0.431 | HT31: 181.371 | HU31: -0.038 | HW31: -2.887 | HX31: 7.446 | HY31: 185.892
A32: N2113 | B32: Terrains et plans d’eau de loisirs
A33: N2119 | B33: Autres terrains et plans d’eau | C33: 42.382 | D33: -0.445 | F33: 6.987 | G33: -0.368 | H33: 48.556 | I33: -0.492 | K33: 6.224 | L33: -0.259 | M33: 54.029 | N33: -0.491 | P33: 4.577 | Q33: -0.119 | R33: 57.997 | S33: -0.51 | U33: 3.95 | V33: -1.025 | W33: 60.411 | X33: -0.524 | Z33: 4.189 | AA33: -0.199 | AB33: 63.877 | AC33: -0.569 | AE33: 0.605 | AF33: -0.431 | AG33: 63.482 | AH33: -0.453 | AJ33: -0.424 | AK33: -1.578 | AL33: 61.027 | AM33: -0.462 | AO33: 1.229 | AP33: -1.444 | AQ33: 60.35 | AR33: -0.47 | AT33: 0.317 | AU33: -5.111 | AV33: 55.085 | AW33: -0.577 | AY33: 0.652 | AZ33: -3.2 | BA33: 51.96 | BB33: -0.998 | BD33: 6.031 | BE33: -1.345 | BF33: 55.648 | BG33: -1.013 | BI33: 3.51 | BJ33: 3.638 | BK33: 61.783 | BL33: -1.127 | BN33: -4.448 | BO33: 0.502 | BP33: 56.71 | BQ33: -0.906 | BS33: -4.827 | BT33: 0.44 | BU33: 51.417 | BV33: -0.768 | BX33: -2.258 | BY33: 0.273 | BZ33: 48.664 | CA33: -0.475 | CC33: -0.565 | CD33: 0.159 | CE33: 47.782 | CF33: -1.008 | CH33: -6.341 | CI33: 0.683 | CJ33: 41.116 | CK33: -0.768 | CM33: -0.045 | CN33: 0.348 | CO33: 40.651 | CP33: -1.689 | CR33: -0.767 | CS33: 1.109 | CT33: 39.304 | CU33: -1.654 | CW33: 6.146 | CX33: 0.929 | CY33: 44.726 | CZ33: -1.762 | DB33: 13.317 | DC33: 1.22 | DD33: 57.501 | DE33: -2.77 | DG33: 14.212 | DH33: 2.235 | DI33: 71.178 | DJ33: -1.926 | DL33: 14.081 | DM33: -0.746 | DN33: 82.587 | DO33: -2.285 | DQ33: 21.343 | DR33: -0.805 | DS33: 100.84 | DT33: -2.181 | DV33: 27.733 | DW33: -0.957 | DX33: 125.435 | DY33: -2.584 | EA33: 35.598 | EB33: -2.022 | EC33: 156.427 | ED33: -2.847 | EF33: 39.719 | EG33: -1.422 | EH33: 191.877 | EI33: -3.346 | EK33: 30.608 | EL33: 1.169 | EM33: 220.308 | EN33: -3.915 | EP33: 14.991 | EQ33: 3.762 | ER33: 235.145 | ES33: -2.823 | EU33: -18.993 | EV33: 1.485 | EW33: 214.814 | EX33: -3.489 | EZ33: 15.076 | FA33: -17.786 | FB33: 208.616 | FC33: -3.088 | FE33: 32.734 | FF33: 1.858 | FG33: 240.119 | FH33: -3.817 | FJ33: 14.796 | FK33: 2.505 | FL33: 253.603 | FM33: -3.897 | FO33: -3.179 | FP33: 2.756 | FQ33: 249.283 | FR33: -3.364 | FT33: -7.272 | FU33: 2.892 | FV33: 241.539 | FW33: -3.6 | FY33: -11.909 | FZ33: 13.495 | GA33: 239.525 | GB33: -3.25 | GD33: 6.072 | GE33: 0.508 | GF33: 242.854 | GG33: -3.199 | GI33: 12.574 | GJ33: 7.568 | GK33: 259.797 | GL33: -3.5 | GN33: 11.765 | GO33: 12.868 | GP33: 280.93 | GQ33: -3.485 | GS33: 9.881 | GT33: 14.976 | GU33: 302.302 | GV33: -3.679 | GX33: 24.205 | GY33: 15.478 | GZ33: 338.306 | HA33: -2.806 | HC33: 34.018 | HD33: 16.45 | HE33: 385.968 | HF33: -3.025 | HH33: 22.672 | HI33: 18.054 | HJ33: 423.668 | HK33: -2.786 | HM33: -4.135 | HN33: 19.544 | HO33: 436.292 | HP33: -3.455 | HR33: -43.39 | HS33: 19.011 | HT33: 408.457 | HU33: -3.956 | HW33: -6.979 | HX33: 19.793 | HY33: 417.316
A34: N212 | B34: Réserves de minerais et de produits énergétiques
A35: N214 | B35: Ressources en eau
A36: N22 | B36: Contrats, baux et licences
A37: N23 | B37: Achats moins ventes de fonds commerciaux et d’autres actifs commerciaux | C37: 13.065 | G37: 1.513 | H37: 14.578 | L37: 1.581 | M37: 16.159 | Q37: 1.521 | R37: 17.68 | V37: 1.378 | W37: 19.057 | AA37: 1.18 | AB37: 20.237 | AF37: 0.88 | AG37: 21.116 | AK37: 0.64 | AL37: 21.756 | AP37: 0.457 | AQ37: 22.213 | AU37: 0.415 | AV37: 22.629 | AZ37: 0.949 | BA37: 23.578 | BE37: 1.352 | BF37: 24.93 | BJ37: 0.538 | BK37: 25.468 | BO37: -0.389 | BP37: 25.08 | BT37: -0.679 | BU37: 24.401 | BY37: -0.517 | BZ37: 23.884 | CD37: 0.153 | CE37: 24.037 | CI37: 0.458 | CJ37: 24.494 | CN37: 0.343 | CO37: 24.838 | CS37: 0.351 | CT37: 25.189 | CX37: 0.421 | CY37: 25.61 | DC37: 0.514 | DD37: 26.124 | DH37: 0.575 | DI37: 26.698 | DM37: 0.607 | DN37: 27.305 | DR37: 1.315 | DS37: 28.619 | DW37: 0.778 | DX37: 29.397 | EB37: 1.613 | EC37: 31.01 | EG37: -0.573 | EH37: 30.437 | EL37: -9.915 | EM37: 20.522 | EQ37: 0.01 | ER37: 20.533 | EV37: -1.514 | EW37: 19.019 | FA37: -1.39 | FB37: 17.629 | FF37: -1.266 | FG37: 16.363 | FK37: -1.164 | FL37: 15.199 | FP37: -0.291 | FQ37: 14.907 | FU37: -0.281 | FV37: 14.627 | FZ37: 0.281 | GA37: 14.907 | GE37: -0.977 | GF37: 13.93 | GJ37: -0.584 | GK37: 13.346 | GO37: -0.552 | GP37: 12.795 | GT37: -0.71 | GU37: 12.085 | GY37: -0.39 | GZ37: 11.695 | HD37: -0.43 | HE37: 11.266 | HI37: -0.221 | HJ37: 11.045 | HN37: -0.416 | HO37: 10.629 | HS37: -0.346 | HT37: 10.283 | HX37: -0.334 | HY37: 9.948
A39: F | B39: Total des actifs financiers | CJ39: 1898.591 | CK39: 65.046 | CM39: 79.966 | CN39: -8.513 | CO39: 2035.09 | CP39: 79.167 | CR39: 61.224 | CS39: 4.652 | CT39: 2180.133 | CU39: 59.949 | CW39: 74.7 | CX39: 8.551 | CY39: 2323.332 | CZ39: 83.03 | DB39: 207.093 | DC39: 6.608 | DD39: 2620.063 | DE39: 68.243 | DG39: 24.525 | DH39: -2.385 | DI39: 2710.446 | DJ39: 101.618 | DL39: -163.119 | DM39: -5.755 | DN39: 2643.19 | DO39: 106.948 | DQ39: -107.809 | DR39: 16.333 | DS39: 2658.662 | DT39: 114.434 | DV39: 77.701 | DW39: -9.247 | DX39: 2841.549 | DY39: 82.075 | EA39: 77.293 | EB39: 5.235 | EC39: 3006.153 | ED39: 129.797 | EF39: 109.061 | EG39: -3.322 | EH39: 3241.689 | EI39: 140.974 | EK39: 204.917 | EL39: 25.332 | EM39: 3612.911 | EN39: 155.268 | EP39: 32.057 | EQ39: 18.796 | ER39: 3819.032 | ES39: 117.321 | EU39: -380.157 | EV39: -11.429 | EW39: 3544.767 | EX39: 152.424 | EZ39: 122.718 | FA39: -3.182 | FB39: 3816.727 | FC39: 172.291 | FE39: 81.44 | FF39: 7.405 | FG39: 4077.863 | FH39: 106.569 | FJ39: -74.808 | FK39: 8.074 | FL39: 4117.697 | FM39: 29.192 | FO39: 130.372 | FP39: 1.677 | FQ39: 4278.938 | FR39: 104.787 | FT39: 68.678 | FU39: 11.364 | FV39: 4463.766 | FW39: 89.532 | FY39: 65.756 | FZ39: 44.551 | GA39: 4663.605 | GB39: 116.327 | GD39: 101.233 | GE39: 7.545 | GF39: 4888.71 | GG39: 118.214 | GI39: 54.532 | GJ39: 167.209 | GK39: 5228.665 | GL39: 122.497 | GN39: 115.009 | GO39: 3.258 | GP39: 5469.428 | GQ39: 134.501 | GS39: -146.366 | GT39: -29.116 | GU39: 5428.446 | GV39: 135.487 | GX39: 368.281 | GY39: -5.517 | GZ39: 5926.698 | HA39: 238.646 | HC39: 67.489 | HD39: -9.478 | HE39: 6223.352 | HF39: 195.022 | HH39: 315.363 | HI39: -5.028 | HJ39: 6728.711 | HK39: 188.043 | HM39: -540.292 | HN39: 17.33 | HO39: 6393.79 | HP39: 156.964 | HR39: 265.896 | HS39: -9.747 | HT39: 6806.904 | HU39: 156.558 | HW39: -2.938 | HX39: 16.633 | HY39: 6977.156
A40: F1 | B40: Or monétaire et droits de tirage spéciaux (DTS)
A41: F2 | B41: Numéraire et dépôts | CJ41: 645.421 | CK41: 31.442 | CM41: 0.346 | CN41: -0.505 | CO41: 676.704 | CP41: 39.985 | CR41: 0.733 | CS41: 0.324 | CT41: 717.746 | CU41: 34.579 | CW41: -1.006 | CX41: -1.64 | CY41: 749.68 | CZ41: 28.816 | DB41: 3.489 | DC41: -1.245 | DD41: 780.74 | DE41: -7.09 | DG41: 12.664 | DH41: -13.795 | DI41: 772.519 | DJ41: 21.606 | DL41: 3.294 | DM41: -6.2 | DN41: 791.219 | DO41: 28.442 | DQ41: 5.532 | DR41: 14.685 | DS41: 839.878 | DT41: 39.708 | DV41: 2.551 | DW41: -3.439 | DX41: 878.699 | DY41: 40.908 | EA41: 0.505 | EB41: -5.487 | EC41: 914.625 | ED41: 38.246 | EF41: 2.484 | EG41: -1.608 | EH41: 953.747 | EI41: 20.761 | EK41: 0.428 | EL41: -1.649 | EM41: 973.287 | EN41: 42.902 | EP41: -2.523 | EQ41: 0.857 | ER41: 1014.523 | ES41: 41.169 | EU41: 0.135 | EV41: 0.224 | EW41: 1056.051 | EX41: 21.982 | EZ41: -0.132 | FA41: -0.07 | FB41: 1077.832 | FC41: 31.883 | FE41: -0.001 | FF41: 0.832 | FG41: 1110.547 | FH41: 49.203 | FJ41: 0.914 | FK41: 6.321 | FL41: 1166.983 | FM41: 47.01 | FO41: -0.352 | FP41: 0.071 | FQ41: 1213.712 | FR41: 30.198 | FT41: -0.679 | FU41: 3.751 | FV41: 1246.982 | FW41: 17.992 | FY41: 1.29 | FZ41: -2.322 | GA41: 1263.943 | GB41: 41.229 | GD41: 1.985 | GE41: -0.001 | GF41: 1307.157 | GG41: 57.04 | GI41: 0.031 | GJ41: 0 | GK41: 1364.229 | GL41: 60.967 | GN41: -2.196 | GO41: 0 | GP41: 1423 | GQ41: 67.923 | GS41: 0.796 | GT41: 0.335 | GU41: 1492.054 | GV41: 81.454 | GX41: 0.784 | GY41: -0.066 | GZ41: 1574.227 | HA41: 155.757 | HC41: -1.059 | HD41: 0 | HE41: 1728.925 | HF41: 112.458 | HH41: 1.672 | HI41: 0.009 | HJ41: 1843.063 | HK41: 86.462 | HM41: 0.883 | HN41: 0 | HO41: 1930.408 | HP41: 51.375 | HR41: 0.236 | HS41: 0 | HT41: 1982.019 | HU41: 29.721 | HW41: 0.58 | HX41: 0 | HY41: 2012.321
A42: F3 | B42: Titres de créance | CJ42: 109.351 | CK42: -4.075 | CM42: -3.897 | CN42: 0 | CO42: 101.379 | CP42: -20.679 | CR42: 7.687 | CS42: 0 | CT42: 88.386 | CU42: -14.957 | CW42: 6.742 | CX42: 7.486 | CY42: 87.657 | CZ42: -0.931 | DB42: -10.863 | DC42: -1.75 | DD42: 74.113 | DE42: 1.312 | DG42: 5.091 | DH42: 10.011 | DI42: 90.526 | DJ42: 8.643 | DL42: -3.906 | DM42: 0 | DN42: 95.263 | DO42: -5.364 | DQ42: -7.276 | DR42: 0 | DS42: 82.623 | DT42: -7.934 | DV42: -3.98 | DW42: 0 | DX42: 70.709 | DY42: -0.341 | EA42: -1.958 | EB42: 0 | EC42: 68.41 | ED42: 3.449 | EF42: -2.711 | EG42: 0 | EH42: 69.148 | EI42: 2.094 | EK42: -7.259 | EL42: 0 | EM42: 63.983 | EN42: 4.964 | EP42: -0.9 | EQ42: 0 | ER42: 68.046 | ES42: 1.143 | EU42: 2.468 | EV42: 0 | EW42: 71.658 | EX42: 7.953 | EZ42: 3.812 | FA42: 0 | FB42: 83.423 | FC42: -6.677 | FE42: -0.254 | FF42: 0 | FG42: 76.493 | FH42: 2.108 | FJ42: -2.916 | FK42: 0 | FL42: 75.685 | FM42: 3.973 | FO42: 4.304 | FP42: 0 | FQ42: 83.962 | FR42: -5.336 | FT42: 4.472 | FU42: 0 | FV42: 83.098 | FW42: -15.858 | FY42: 2.903 | FZ42: 2.286 | GA42: 72.428 | GB42: -11.245 | GD42: -1.195 | GE42: 0 | GF42: 59.989 | GG42: -5.142 | GI42: 0.622 | GJ42: -1.16 | GK42: 54.308 | GL42: -6.16 | GN42: -0.814 | GO42: 0 | GP42: 47.334 | GQ42: -4.848 | GS42: -1.76 | GT42: 0 | GU42: 40.726 | GV42: -2.85 | GX42: 1.465 | GY42: 0 | GZ42: 39.341 | HA42: -3.625 | HC42: -1.346 | HD42: 0 | HE42: 34.369 | HF42: -0.485 | HH42: -0.087 | HI42: -0.847 | HJ42: 32.95 | HK42: 5.124 | HM42: -3.508 | HN42: 0.087 | HO42: 34.653 | HP42: 10.02 | HR42: 0.765 | HS42: 0 | HT42: 45.438 | HU42: 3.59 | HW42: 1.18 | HX42: 0 | HY42: 50.208
A43: F4 | B43: Crédits | CJ43: 26.59 | CK43: 0.241 | CM43: 0 | CN43: 0 | CO43: 26.831 | CP43: 7.142 | CR43: 0 | CS43: 0 | CT43: 33.974 | CU43: -9.424 | CW43: 0 | CX43: 0.029 | CY43: 24.579 | CZ43: -5.402 | DB43: 0.001 | DC43: 0.001 | DD43: 19.178 | DE43: 1.586 | DG43: 0 | DH43: 0 | DI43: 20.765 | DJ43: -0.309 | DL43: 0 | DM43: -0.001 | DN43: 20.455 | DO43: -1.54 | DQ43: 0 | DR43: 0 | DS43: 18.915 | DT43: 2.319 | DV43: 0 | DW43: 0.001 | DX43: 21.235 | DY43: -1.732 | EA43: 0 | EB43: 0 | EC43: 19.503 | ED43: 0.641 | EF43: 0 | EG43: 0 | EH43: 20.144 | EI43: 3.147 | EK43: 0 | EL43: 0 | EM43: 23.292 | EN43: -0.442 | EP43: 0 | EQ43: 0 | ER43: 22.85 | ES43: 9.474 | EU43: 0 | EV43: 0 | EW43: 32.324 | EX43: -6.502 | EZ43: 0 | FA43: 0 | FB43: 25.822 | FC43: 0.675 | FE43: 0 | FF43: -0.006 | FG43: 26.49 | FH43: 1.29 | FJ43: 0 | FK43: 0 | FL43: 27.78 | FM43: 0.824 | FO43: 0 | FP43: 0 | FQ43: 28.604 | FR43: 1.2 | FT43: 0 | FU43: -0.442 | FV43: 29.362 | FW43: 0.932 | FY43: 0 | FZ43: 0.098 | GA43: 30.392 | GB43: 1.026 | GD43: 0 | GE43: -0.005 | GF43: 31.413 | GG43: 1.144 | GI43: 0 | GJ43: -22.32 | GK43: 10.238 | GL43: 0.175 | GN43: 0 | GO43: 0.119 | GP43: 10.531 | GQ43: 0.107 | GS43: 0 | GT43: 0 | GU43: 10.638 | GV43: -0.03 | GX43: 0 | GY43: -0.008 | GZ43: 10.6 | HA43: 0.408 | HC43: 0 | HD43: 0 | HE43: 11.005 | HF43: -0.002 | HH43: 0 | HI43: 0 | HJ43: 11.006 | HK43: 0.036 | HM43: 0 | HN43: -0.18 | HO43: 10.862 | HP43: 0.784 | HR43: 0 | HS43: 0.011 | HT43: 11.656 | HU43: -0.365 | HW43: 0 | HX43: -0.003 | HY43: 11.289
A44: F5 | B44: Actions et parts de fonds d’investissement | CJ44: 657.747 | CK44: -29.658 | CM44: 83.606 | CN44: -8.008 | CO44: 703.686 | CP44: -28.124 | CR44: 52.838 | CS44: 4.913 | CT44: 733.313 | CU44: -5.259 | CW44: 65.952 | CX44: 3.534 | CY44: 797.539 | CZ44: -27.283 | DB44: 202.447 | DC44: 3.744 | DD44: 976.446 | DE44: -7.568 | DG44: 12.794 | DH44: 0.558 | DI44: 982.231 | DJ44: 8.446 | DL44: -146.19 | DM44: 0.456 | DN44: 844.942 | DO44: 13.789 | DQ44: -83.004 | DR44: -0.831 | DS44: 774.896 | DT44: 10.922 | DV44: 72.77 | DW44: 0.083 | DX44: 858.671 | DY44: -17.105 | EA44: 68.95 | EB44: 10.719 | EC44: 921.235 | ED44: -16.637 | EF44: 92.733 | EG44: -1.724 | EH44: 995.607 | EI44: 15.405 | EK44: 187.99 | EL44: -1.539 | EM44: 1197.463 | EN44: -1.184 | EP44: 34.39 | EQ44: 9.231 | ER44: 1239.899 | ES44: -8.091 | EU44: -345.953 | EV44: 1.423 | EW44: 887.278 | EX44: -21.177 | EZ44: 91.846 | FA44: 6.437 | FB44: 964.384 | FC44: -9.861 | FE44: 68.433 | FF44: 5.592 | FG44: 1028.548 | FH44: 0.967 | FJ44: -62.926 | FK44: -2.863 | FL44: 963.725 | FM44: 10.255 | FO44: 100.793 | FP44: 1.621 | FQ44: 1076.394 | FR44: 8.546 | FT44: 43.852 | FU44: 3.883 | FV44: 1132.675 | FW44: 0.062 | FY44: 41.294 | FZ44: 40.913 | GA44: 1214.945 | GB44: 20.622 | GD44: 86.552 | GE44: 7.546 | GF44: 1329.665 | GG44: 5.484 | GI44: 44.794 | GJ44: 18.233 | GK44: 1398.176 | GL44: 11.832 | GN44: 122.312 | GO44: 2.452 | GP44: 1534.772 | GQ44: 17.047 | GS44: -81.729 | GT44: -22.144 | GU44: 1447.947 | GV44: -14.799 | GX44: 232.146 | GY44: -7.092 | GZ44: 1658.202 | HA44: 43.694 | HC44: 18.456 | HD44: -8.629 | HE44: 1711.723 | HF44: 10.327 | HH44: 310.416 | HI44: 3.723 | HJ44: 2036.19 | HK44: 43.891 | HM44: -209.813 | HN44: 16.422 | HO44: 1886.689 | HP44: 34.964 | HR44: 195.562 | HS44: -10.585 | HT44: 2106.629 | HU44: 41.348 | HW44: -28.069 | HX44: 16.951 | HY44: 2136.859
A45: F511 | B45: dont : Actions cotées | CJ45: 94.076 | CK45: 1.102 | CM45: 17.716 | CN45: -1.319 | CO45: 111.575 | CP45: -1.958 | CR45: 12.044 | CS45: -4.096 | CT45: 117.566 | CU45: -4.797 | CW45: 27.452 | CX45: 6.575 | CY45: 146.796 | CZ45: -6.33 | DB45: 38.818 | DC45: 1.281 | DD45: 180.564 | DE45: -12.748 | DG45: 13.026 | DH45: 16.148 | DI45: 196.99 | DJ45: 0.487 | DL45: -54.154 | DM45: 13.857 | DN45: 157.18 | DO45: 3.813 | DQ45: -48.352 | DR45: -1.644 | DS45: 110.997 | DT45: 3.146 | DV45: 18.58 | DW45: -2.432 | DX45: 130.292 | DY45: -0.888 | EA45: 4.038 | EB45: 5.45 | EC45: 138.891 | ED45: 4.928 | EF45: 37.47 | EG45: -0.587 | EH45: 180.702 | EI45: -3.537 | EK45: 34.675 | EL45: 0.118 | EM45: 211.958 | EN45: -3.099 | EP45: -6.781 | EQ45: 2.159 | ER45: 204.237 | ES45: -11.287 | EU45: -73.995 | EV45: -8.289 | EW45: 110.667 | EX45: 0.641 | EZ45: 35.544 | FA45: -4.86 | FB45: 141.992 | FC45: 5.248 | FE45: 9.037 | FF45: 5.275 | FG45: 161.552 | FH45: 3.079 | FJ45: -25.208 | FK45: -6.938 | FL45: 132.484 | FM45: -3.742 | FO45: 21.93 | FP45: 0.061 | FQ45: 150.733 | FR45: -9.038 | FT45: 31.173 | FU45: 2.754 | FV45: 175.623 | FW45: 6.351 | FY45: 5.18 | FZ45: -3.063 | GA45: 184.091 | GB45: 7.669 | GD45: 14.651 | GE45: 6.305 | GF45: 212.715 | GG45: -4.604 | GI45: 9.526 | GJ45: -0.145 | GK45: 217.493 | GL45: -1.752 | GN45: 23.778 | GO45: 0.488 | GP45: 240.007 | GQ45: 3.074 | GS45: -27.739 | GT45: -0.15 | GU45: 215.191 | GV45: -3.875 | GX45: 54.08 | GY45: 0.067 | GZ45: 265.463 | HA45: 14.346 | HC45: -6.121 | HD45: 1.025 | HE45: 274.713 | HF45: 1.439 | HH45: 54.338 | HI45: -0.53 | HJ45: 329.96 | HK45: 6.501 | HM45: -49.755 | HN45: -0.351 | HO45: 286.355 | HP45: -10.22 | HR45: 45.564 | HS45: -0.048 | HT45: 321.651 | HU45: 2.741 | HW45: -6.734 | HX45: 0.037 | HY45: 317.695
A46: F6 | B46: Systèmes d’assurance, de pension et de garanties standard | CJ46: 378.764 | CK46: 63.604 | CM46: -0.088 | CN46: 0 | CO46: 442.279 | CP46: 75 | CR46: -0.033 | CS46: 0 | CT46: 517.246 | CU46: 54.146 | CW46: 3.011 | CX46: 0 | CY46: 574.403 | CZ46: 63.717 | DB46: 12.02 | DC46: 0 | DD46: 650.14 | DE46: 67.255 | DG46: -6.024 | DH46: 0 | DI46: 711.372 | DJ46: 61.729 | DL46: -16.317 | DM46: 0 | DN46: 756.783 | DO46: 56.648 | DQ46: -23.062 | DR46: 0 | DS46: 790.369 | DT46: 59.561 | DV46: 6.36 | DW46: 0 | DX46: 856.291 | DY46: 79.227 | EA46: 9.796 | EB46: 0 | EC46: 945.314 | ED46: 89.391 | EF46: 16.555 | EG46: 0 | EH46: 1051.26 | EI46: 96.852 | EK46: 23.758 | EL46: 28.512 | EM46: 1200.382 | EN46: 86.073 | EP46: 1.091 | EQ46: 8.709 | ER46: 1296.254 | ES46: 49.752 | EU46: -36.808 | EV46: -9.908 | EW46: 1299.29 | EX46: 79.865 | EZ46: 27.193 | FA46: 1.089 | FB46: 1407.437 | FC46: 89.38 | FE46: 13.261 | FF46: 1.139 | FG46: 1511.217 | FH46: 30.177 | FJ46: -9.879 | FK46: 3.084 | FL46: 1534.6 | FM46: 25.037 | FO46: 25.627 | FP46: 2.707 | FQ46: 1587.97 | FR46: 42.418 | FT46: 21.032 | FU46: 2.977 | FV46: 1654.397 | FW46: 55.039 | FY46: 20.268 | FZ46: 3.416 | GA46: 1733.12 | GB46: 51.903 | GD46: 13.892 | GE46: 0 | GF46: 1798.915 | GG46: 41.957 | GI46: 9.089 | GJ46: 172.258 | GK46: 2022.219 | GL46: 39.874 | GN46: -4.285 | GO46: 0.31 | GP46: 2058.118 | GQ46: 39.294 | GS46: -63.656 | GT46: -2.815 | GU46: 2030.94 | GV46: 41.855 | GX46: 133.886 | GY46: 2.027 | GZ46: 2208.708 | HA46: 10.151 | HC46: 51.427 | HD46: -0.946 | HE46: 2269.341 | HF46: 33.601 | HH46: 3.418 | HI46: -3.557 | HJ46: 2302.803 | HK46: 37.124 | HM46: -327.866 | HN46: -0.594 | HO46: 2011.467 | HP46: 32.541 | HR46: 69.414 | HS46: 0 | HT46: 2113.422 | HU46: 58.581 | HW46: 23.392 | HX46: 0 | HY46: 2195.394
A47: F7 | B47: Produits financiers dérivés et options sur titres des salariés | CJ47: 0 | CK47: 0 | CM47: 0 | CN47: 0 | CO47: 0 | CP47: 0 | CR47: 0 | CS47: 0 | CT47: 0 | CU47: 0 | CW47: 0 | CX47: 0 | CY47: 0 | CZ47: 0 | DB47: 0 | DC47: 0 | DD47: 0 | DE47: 0 | DG47: 0 | DH47: 0 | DI47: 0 | DJ47: 0 | DL47: 0 | DM47: 0 | DN47: 0 | DO47: 0 | DQ47: 0 | DR47: 0 | DS47: 0 | DT47: 0 | DV47: 0 | DW47: 0 | DX47: 0 | DY47: 0 | EA47: 0 | EB47: 0 | EC47: 0 | ED47: 0 | EF47: 0 | EG47: 0 | EH47: 0 | EI47: 0 | EK47: 0 | EL47: 0 | EM47: 0 | EN47: 0 | EP47: 0 | EQ47: 0 | ER47: 0 | ES47: 0 | EU47: 0 | EV47: 0 | EW47: 0 | EX47: 0 | EZ47: 0 | FA47: 0 | FB47: 0 | FC47: 0 | FE47: 0 | FF47: 0 | FG47: 0 | FH47: 0 | FJ47: 0 | FK47: 0 | FL47: 0 | FM47: 0 | FO47: 0 | FP47: 0 | FQ47: 0 | FR47: 0 | FT47: 0 | FU47: 0 | FV47: 0 | FW47: 0.002 | FY47: 0.001 | FZ47: 0.001 | GA47: 0.004 | GB47: 0.002 | GD47: -0.001 | GE47: 0 | GF47: 0.004 | GG47: 0.038 | GI47: -0.004 | GJ47: 0 | GK47: 0.038 | GL47: 0.005 | GN47: -0.008 | GO47: 0 | GP47: 0.036 | GQ47: 0.113 | GS47: -0.018 | GT47: 0 | GU47: 0.13 | GV47: 0.057 | GX47: 0 | GY47: 0 | GZ47: 0.187 | HA47: 0.093 | HC47: 0.012 | HD47: 0 | HE47: 0.292 | HF47: 0.083 | HH47: -0.057 | HI47: 0 | HJ47: 0.319 | HK47: -0.036 | HM47: 0.012 | HN47: 0 | HO47: 0.296 | HP47: -0.077 | HR47: -0.081 | HS47: 0 | HT47: 0.138 | HU47: -0.058 | HW47: -0.02 | HX47: 0 | HY47: 0.06
A48: F8 | B48: Autres comptes à recevoir / à payer | CJ48: 80.719 | CK48: 3.492 | CN48: 0 | CO48: 84.211 | CP48: 5.843 | CS48: -0.585 | CT48: 89.468 | CU48: 0.864 | CX48: -0.858 | CY48: 89.474 | CZ48: 24.113 | DC48: 5.858 | DD48: 119.445 | DE48: 12.748 | DH48: 0.842 | DI48: 133.035 | DJ48: 1.504 | DM48: -0.01 | DN48: 134.529 | DO48: 14.972 | DR48: 2.479 | DS48: 151.98 | DT48: 9.858 | DW48: -5.893 | DX48: 155.946 | DY48: -18.882 | EB48: 0.003 | EC48: 137.066 | ED48: 14.708 | EG48: 0.01 | EH48: 151.784 | EI48: 2.714 | EL48: 0.007 | EM48: 154.505 | EN48: 22.955 | EQ48: 0 | ER48: 177.46 | ES48: 23.874 | EV48: -3.168 | EW48: 198.166 | EX48: 70.302 | FA48: -10.638 | FB48: 257.829 | FC48: 66.891 | FF48: -0.153 | FG48: 324.567 | FH48: 22.825 | FK48: 1.532 | FL48: 348.924 | FM48: -57.906 | FP48: -2.722 | FQ48: 288.296 | FR48: 27.761 | FU48: 1.194 | FV48: 317.251 | FW48: 31.364 | FZ48: 0.158 | GA48: 348.773 | GB48: 12.79 | GE48: 0.005 | GF48: 361.567 | GG48: 17.692 | GJ48: 0.198 | GK48: 379.458 | GL48: 15.804 | GO48: 0.376 | GP48: 395.637 | GQ48: 14.866 | GT48: -4.492 | GU48: 406.011 | GV48: 29.799 | GY48: -0.377 | GZ48: 435.432 | HA48: 32.169 | HD48: 0.096 | HE48: 467.697 | HF48: 39.039 | HI48: -4.356 | HJ48: 502.38 | HK48: 15.442 | HN48: 1.595 | HO48: 519.417 | HP48: 27.357 | HS48: 0.827 | HT48: 547.6 | HU48: 23.742 | HX48: -0.316 | HY48: 571.026
A50: FN | B50: Total des actifs | CF50: 30.767 | CH50: -26.239 | CI50: 15.697 | CJ50: 4080.46 | CK50: 128.993 | CM50: 98.298 | CN50: -5.175 | CO50: 4265.775 | CP50: 145.305 | CR50: 72.252 | CS50: 5.638 | CT50: 4451.132 | CU50: 130.676 | CW50: 168.881 | CX50: 11.795 | CY50: 4723.731 | CZ50: 159.541 | DB50: 421.034 | DC50: 10.821 | DD50: 5275.403 | DE50: 146.808 | DG50: 251.274 | DH50: 8.01 | DI50: 5640.09 | DJ50: 184.458 | DL50: 69.173 | DM50: 8.419 | DN50: 5858.806 | DO50: 193.287 | DQ50: 240.293 | DR50: 35.269 | DS50: 6282.392 | DT50: 205.396 | DV50: 562.347 | DW50: 9.65 | DX50: 7012.325 | DY50: 183.114 | EA50: 723.604 | EB50: 35.445 | EC50: 7903.927 | ED50: 234.893 | EF50: 827.811 | EG50: 29.542 | EH50: 8942.447 | EI50: 256.858 | EK50: 740.631 | EL50: 58.82 | EM50: 9941.194 | EN50: 278.93 | EP50: 316.889 | EQ50: 112.723 | ER50: 10588.258 | ES50: 244.247 | EU50: -759.164 | EV50: 26.324 | EW50: 10033.819 | EX50: 260.853 | EZ50: 53.957 | FA50: -21.308 | FB50: 10261.867 | FC50: 284.917 | FE50: 595.839 | FF50: 15.574 | FG50: 11090.761 | FH50: 224.296 | FJ50: 110.703 | FK50: 47.683 | FL50: 11403.986 | FM50: 145.756 | FO50: -12.636 | FP50: 43.074 | FQ50: 11509.824 | FR50: 221.471 | FT50: -78.268 | FU50: 66.844 | FV50: 11649.426 | FW50: 205.373 | FY50: -94.732 | FZ50: 82.182 | GA50: 11769.966 | GB50: 232.438 | GD50: 83.41 | GE50: 43.759 | GF50: 12056.421 | GG50: 238.329 | GI50: 202.621 | GJ50: 202.452 | GK50: 12625.638 | GL50: 252.119 | GN50: 340.237 | GO50: 54.292 | GP50: 13194.813 | GQ50: 270.576 | GS50: 79.959 | GT50: 23.989 | GU50: 13488.12 | GV50: 278.006 | GX50: 650.879 | GY50: 71.279 | GZ50: 14402.515 | HA50: 375.583 | HC50: 499.97 | HD50: 63.304 | HE50: 15251.393 | HF50: 358.622 | HH50: 874.067 | HI50: 77.913 | HJ50: 16465.049 | HK50: 358.922 | HM50: -193.36 | HN50: 104.624 | HO50: 16628.814 | HP50: 317.304 | HR50: -159.461 | HS50: 61.386 | HT50: 16738.395 | HU50: 307.248 | HW50: -186.845 | HX50: 94.882 | HY50: 16844.934
A53: F | B53: Total des passifs financiers | CJ53: 516.783 | CK53: 29.846 | CM53: -1 | CN53: -3.013 | CO53: 542.616 | CP53: 39.44 | CR53: -1.939 | CS53: -2.963 | CT53: 577.153 | CU53: 26.209 | CW53: -2.885 | CX53: -1.939 | CY53: 598.538 | CZ53: 43.346 | DB53: -0.366 | DC53: 3.214 | DD53: 644.732 | DE53: 27.079 | DG53: 0.236 | DH53: -3.527 | DI53: 668.519 | DJ53: 48.131 | DL53: -0.586 | DM53: -4.8 | DN53: 711.263 | DO53: 59.346 | DQ53: -2.882 | DR53: 2.649 | DS53: 770.375 | DT53: 60.306 | DV53: -1.132 | DW53: -6.2 | DX53: 823.35 | DY53: 32.853 | EA53: -1.2 | EB53: 4.459 | EC53: 859.461 | ED53: 100.692 | EF53: 0.086 | EG53: -3.731 | EH53: 956.508 | EI53: 98.572 | EK53: -0.707 | EL53: 5.66 | EM53: 1060.033 | EN53: 115.79 | EP53: -0.63 | EQ53: -3.296 | ER53: 1171.897 | ES53: 55.224 | EU53: 1.231 | EV53: -1.915 | EW53: 1226.437 | EX53: 79.81 | EZ53: 0 | FA53: 10.936 | FB53: 1317.183 | FC53: 88.357 | FE53: 0 | FF53: -1.195 | FG53: 1404.344 | FH53: 40.839 | FJ53: 0 | FK53: 5.318 | FL53: 1450.502 | FM53: -32.643 | FO53: 0.981 | FP53: 0.973 | FQ53: 1419.812 | FR53: 21.199 | FT53: -0.877 | FU53: 5.36 | FV53: 1445.495 | FW53: 24.814 | FY53: 1.588 | FZ53: 7.027 | GA53: 1478.924 | GB53: 52.976 | GD53: 2.477 | GE53: -4.253 | GF53: 1530.124 | GG53: 56.799 | GI53: 0.202 | GJ53: -10.376 | GK53: 1576.75 | GL53: 83.799 | GN53: -2.395 | GO53: 0.649 | GP53: 1658.802 | GQ53: 77.177 | GS53: 0.888 | GT53: -2.962 | GU53: 1733.905 | GV53: 66.497 | GX53: 0.682 | GY53: -3.996 | GZ53: 1797.089 | HA53: 86.798 | HC53: -1.056 | HD53: -4.011 | HE53: 1878.82 | HF53: 92.571 | HH53: 1.288 | HI53: -4.354 | HJ53: 1968.324 | HK53: 87.618 | HM53: 0.918 | HN53: 1.819 | HO53: 2058.677 | HP53: 31.049 | HR53: -0.008 | HS53: -3.336 | HT53: 2086.383 | HU53: 0.248 | HW53: 0.438 | HX53: 4.348 | HY53: 2091.417
A54: F1 | B54: Or monétaire et droits de tirage spéciaux (DTS)
A55: F2 | B55: Numéraire et dépôts | CJ55: 0 | CK55: 0 | CN55: 0 | CO55: 0 | CP55: 0 | CS55: 0 | CT55: 0 | CU55: 0 | CX55: 0.002 | CY55: 0.002 | CZ55: -0.002 | DC55: 0 | DD55: 0 | DE55: 0 | DH55: 0 | DI55: 0 | DJ55: 0 | DM55: 0 | DN55: 0 | DO55: 0 | DR55: 0 | DS55: 0 | DT55: 0 | DW55: 0 | DX55: 0 | DY55: 0 | EB55: 0 | EC55: 0 | ED55: 0 | EG55: 0 | EH55: 0 | EI55: 0 | EL55: 0 | EM55: 0 | EN55: 0 | EQ55: 0 | ER55: 0 | ES55: 0 | EV55: 0 | EW55: 0 | EX55: 0 | FA55: 0 | FB55: 0 | FC55: 0 | FF55: 0 | FG55: 0 | FH55: 0 | FK55: 0 | FL55: 0 | FM55: 0 | FP55: 0 | FQ55: 0 | FR55: 0 | FU55: 0 | FV55: 0 | FW55: 0 | FZ55: 0 | GA55: 0 | GB55: 0 | GE55: 0 | GF55: 0 | GG55: 0 | GJ55: 0 | GK55: 0 | GL55: 0 | GO55: 0 | GP55: 0 | GQ55: 0 | GT55: 0 | GU55: 0 | GV55: 0 | GY55: 0 | GZ55: 0 | HA55: 0 | HD55: 0 | HE55: 0 | HF55: 0 | HI55: 0 | HJ55: 0 | HK55: 0 | HN55: 0 | HO55: 0 | HP55: 0 | HS55: 0 | HT55: 0 | HU55: 0 | HX55: 0 | HY55: 0
A56: F3 | B56: Titres de créance
A57: F4 | B57: Crédits | CJ57: 410.651 | CK57: 16.632 | CM57: -1 | CN57: -3.043 | CO57: 423.24 | CP57: 20.481 | CR57: -1.939 | CS57: -1.984 | CT57: 439.797 | CU57: 11.455 | CW57: -2.885 | CX57: -1.436 | CY57: 446.932 | CZ57: 32.685 | DB57: -0.366 | DC57: -3.189 | DD57: 476.061 | DE57: 32.676 | DG57: 0.236 | DH57: -3.518 | DI57: 505.455 | DJ57: 31.517 | DL57: -0.586 | DM57: -4.706 | DN57: 531.679 | DO57: 30.215 | DQ57: -2.882 | DR57: 2.659 | DS57: 561.67 | DT57: 42.603 | DV57: -1.132 | DW57: -2.758 | DX57: 600.384 | DY57: 52.099 | EA57: -1.2 | EB57: 4.489 | EC57: 655.771 | ED57: 78.873 | EF57: 0.086 | EG57: -3.731 | EH57: 730.999 | EI57: 76.092 | EK57: -0.707 | EL57: 6.21 | EM57: 812.593 | EN57: 92.557 | EP57: -0.63 | EQ57: -3.298 | ER57: 901.222 | ES57: 66.016 | EU57: 1.231 | EV57: 0.271 | EW57: 968.74 | EX57: 30.962 | EZ57: 0 | FA57: 15.687 | FB57: 1015.389 | FC57: 53.145 | FE57: 0 | FF57: -1.713 | FG57: 1066.821 | FH57: 51.912 | FJ57: 0 | FK57: 5.563 | FL57: 1124.295 | FM57: 23.918 | FO57: 0.981 | FP57: -1.223 | FQ57: 1147.971 | FR57: 19.953 | FT57: -0.877 | FU57: 2.587 | FV57: 1169.634 | FW57: 22.745 | FY57: 1.584 | FZ57: 3.965 | GA57: 1197.928 | GB57: 36.846 | GD57: 2.48 | GE57: -3.828 | GF57: 1233.426 | GG57: 54.885 | GI57: 0.208 | GJ57: -10.54 | GK57: 1277.98 | GL57: 65.88 | GN57: -2.381 | GO57: 0.546 | GP57: 1342.024 | GQ57: 73.452 | GS57: 0.913 | GT57: -2.307 | GU57: 1414.081 | GV57: 85.357 | GX57: 0.679 | GY57: -3.559 | GZ57: 1496.558 | HA57: 67.628 | HC57: -1.059 | HD57: -3.354 | HE57: 1559.774 | HF57: 89.552 | HH57: 1.355 | HI57: -5.126 | HJ57: 1645.555 | HK57: 84.012 | HM57: 0.918 | HN57: -2.446 | HO57: 1728.037 | HP57: 22.827 | HR57: 0.179 | HS57: -3.278 | HT57: 1747.765 | HU57: 2.978 | HW57: 0.503 | HX57: -2.683 | HY57: 1748.562
A58: F5 | B58: Actions et parts de fonds d’investissement
A59: F511 | B59: dont : Actions cotées
A60: F6 | B60: Systèmes d’assurance, de pension et de garanties standard
A61: F7 | B61: Produits financiers dérivés et options sur titres des salariés | CJ61: 0 | CK61: 0 | CM61: 0 | CN61: 0 | CO61: 0 | CP61: 0 | CR61: 0 | CS61: 0 | CT61: 0 | CU61: 0 | CW61: 0 | CX61: 0 | CY61: 0 | CZ61: 0 | DB61: 0 | DC61: 0 | DD61: 0 | DE61: 0 | DG61: 0 | DH61: 0 | DI61: 0 | DJ61: 0 | DL61: 0 | DM61: 0 | DN61: 0 | DO61: 0 | DQ61: 0 | DR61: 0 | DS61: 0 | DT61: 0 | DV61: 0 | DW61: 0 | DX61: 0 | DY61: 0 | EA61: 0 | EB61: 0 | EC61: 0 | ED61: 0 | EF61: 0 | EG61: 0 | EH61: 0 | EI61: 0 | EK61: 0 | EL61: 0 | EM61: 0 | EN61: 0 | EP61: 0 | EQ61: 0 | ER61: 0 | ES61: 0 | EU61: 0 | EV61: 0 | EW61: 0 | EX61: 0 | EZ61: 0 | FA61: 0 | FB61: 0 | FC61: 0 | FE61: 0 | FF61: 0 | FG61: 0 | FH61: 0 | FJ61: 0 | FK61: 0 | FL61: 0 | FM61: 0 | FO61: 0 | FP61: 0 | FQ61: 0 | FR61: 0 | FT61: 0 | FU61: 0 | FV61: 0 | FW61: -0.014 | FY61: 0.004 | FZ61: 0.021 | GA61: 0.011 | GB61: 0.001 | GD61: -0.003 | GE61: 0 | GF61: 0.009 | GG61: 0.048 | GI61: -0.005 | GJ61: 0 | GK61: 0.051 | GL61: 0.018 | GN61: -0.014 | GO61: 0 | GP61: 0.056 | GQ61: 0.167 | GS61: -0.025 | GT61: 0 | GU61: 0.198 | GV61: 0.013 | GX61: 0.003 | GY61: 0 | GZ61: 0.213 | HA61: 0.089 | HC61: 0.003 | HD61: 0 | HE61: 0.305 | HF61: 0.116 | HH61: -0.067 | HI61: 0 | HJ61: 0.354 | HK61: 0.299 | HM61: 0 | HN61: 0 | HO61: 0.653 | HP61: -0.185 | HR61: -0.187 | HS61: 0 | HT61: 0.282 | HU61: 0.287 | HW61: -0.065 | HX61: 0 | HY61: 0.504
A62: F8 | B62: Autres comptes à recevoir / à payer | CJ62: 106.132 | CK62: 13.214 | CN62: 0.03 | CO62: 119.376 | CP62: 18.96 | CS62: -0.979 | CT62: 137.356 | CU62: 14.754 | CX62: -0.505 | CY62: 151.605 | CZ62: 10.664 | DC62: 6.403 | DD62: 168.671 | DE62: -5.598 | DH62: -0.01 | DI62: 163.064 | DJ62: 16.614 | DM62: -0.094 | DN62: 179.584 | DO62: 29.131 | DR62: -0.01 | DS62: 208.705 | DT62: 17.703 | DW62: -3.442 | DX62: 222.966 | DY62: -19.246 | EB62: -0.03 | EC62: 203.69 | ED62: 21.82 | EG62: 0 | EH62: 225.51 | EI62: 22.48 | EL62: -0.55 | EM62: 247.44 | EN62: 23.233 | EQ62: 0.002 | ER62: 270.675 | ES62: -10.792 | EV62: -2.186 | EW62: 257.697 | EX62: 48.848 | FA62: -4.751 | FB62: 301.794 | FC62: 35.212 | FF62: 0.518 | FG62: 337.524 | FH62: -11.073 | FK62: -0.245 | FL62: 326.206 | FM62: -56.561 | FP62: 2.196 | FQ62: 271.841 | FR62: 1.246 | FU62: 2.774 | FV62: 275.861 | FW62: 2.083 | FZ62: 3.041 | GA62: 280.985 | GB62: 16.129 | GE62: -0.425 | GF62: 296.689 | GG62: 1.867 | GJ62: 0.164 | GK62: 298.719 | GL62: 17.901 | GO62: 0.103 | GP62: 316.723 | GQ62: 3.558 | GT62: -0.655 | GU62: 319.627 | GV62: -18.873 | GY62: -0.437 | GZ62: 300.317 | HA62: 19.08 | HD62: -0.657 | HE62: 318.74 | HF62: 2.903 | HI62: 0.772 | HJ62: 322.415 | HK62: 3.307 | HN62: 4.265 | HO62: 329.988 | HP62: 8.406 | HS62: -0.058 | HT62: 338.336 | HU62: -3.017 | HX62: 7.031 | HY62: 342.351
A64: B90 | B64: Valeur nette | CJ64: 3563.677 | CO64: 3723.159 | CT64: 3873.979 | CY64: 4125.193 | DD64: 4630.671 | DI64: 4971.572 | DN64: 5147.543 | DS64: 5512.017 | DX64: 6188.975 | EC64: 7044.466 | EH64: 7985.939 | EM64: 8881.161 | ER64: 9416.361 | EW64: 8807.382 | FB64: 8944.684 | FG64: 9686.417 | FL64: 9953.485 | FQ64: 10090.013 | FV64: 10203.931 | GA64: 10291.042 | GF64: 10526.296 | GK64: 11048.888 | GP64: 11536.01 | GU64: 11754.215 | GZ64: 12605.426 | HE64: 13372.573 | HJ64: 14496.725 | HO64: 14570.136 | HT64: 14652.012 | HY64: 14753.517
A66: Source : Comptes nationaux annuels (base 2020)
CI67: 1995 | CJ67: 1996 | CK67: =CJ67+1 -> 1997 | CL67: =CK67+1 -> 1998 | CM67: =CL67+1 -> 1999 | CN67: =CM67+1 -> 2000 | CO67: =CN67+1 -> 2001 | CP67: =CO67+1 -> 2002 | CQ67: =CP67+1 -> 2003 | CR67: =CQ67+1 -> 2004 | ... DL67: =DK67+1 -> 2024
A68: Flux | B68: Total des actifs non financiers | CJ68: =CK7 -> 63.947 | CK68: =CP7 -> 66.139 | CL68: =CU7 -> 70.728 | CM68: =CZ7 -> 76.511 | CN68: =DE7 -> 78.565 | CO68: =DJ7 -> 82.84 | CP68: =DO7 -> 86.34 | CQ68: =DT7 -> 90.962 | CR68: =DY7 -> 101.039 | CS68: =ED7 -> 105.096 | CT68: =EI7 -> 115.884 | CU68: =EN7 -> 123.662 | CV68: =ES7 -> 126.926 | CW68: =EX7 -> 108.429 | CX68: =FC7 -> 112.626 | CY68: =FH7 -> 117.727 | CZ68: =FM7 -> 116.564 | DA68: =FR7 -> 116.684 | DB68: =FW7 -> 115.841 | DC68: =GB7 -> 116.111 | DD68: =GG7 -> 120.115 | DE68: =GL7 -> 129.622 | DF68: =GQ7 -> 136.075 | DG68: =GV7 -> 142.519 | DH68: =HA7 -> 136.937 | DI68: =HF7 -> 163.6 | DJ68: =HK7 -> 170.879 | DK68: =HP7 -> 160.34 | DL68: =HU7 -> 150.69
B69: Total des actifs financiers | CJ69: =CK39 -> 65.046 | CK69: =CP39 -> 79.167 | CL69: =CU39 -> 59.949 | CM69: =CZ39 -> 83.03 | CN69: =DE39 -> 68.243 | CO69: =DJ39 -> 101.618 | CP69: =DO39 -> 106.948 | CQ69: =DT39 -> 114.434 | CR69: =DY39 -> 82.075 | CS69: =ED39 -> 129.797 | CT69: =EI39 -> 140.974 | CU69: =EN39 -> 155.268 | CV69: =ES39 -> 117.321 | CW69: =EX39 -> 152.424 | CX69: =FC39 -> 172.291 | CY69: =FH39 -> 106.569 | CZ69: =FM39 -> 29.192 | DA69: =FR39 -> 104.787 | DB69: =FW39 -> 89.532 | DC69: =GB39 -> 116.327 | DD69: =GG39 -> 118.214 | DE69: =GL39 -> 122.497 | DF69: =GQ39 -> 134.501 | DG69: =GV39 -> 135.487 | DH69: =HA39 -> 238.646 | DI69: =HF39 -> 195.022 | DJ69: =HK39 -> 188.043 | DK69: =HP39 -> 156.964 | DL69: =HU39 -> 156.558
B70: Total des passifs financiers | CJ70: =CK53 -> 29.846 | CK70: =CP53 -> 39.44 | CL70: =CU53 -> 26.209 | CM70: =CZ53 -> 43.346 | CN70: =DE53 -> 27.079 | CO70: =DJ53 -> 48.131 | CP70: =DO53 -> 59.346 | CQ70: =DT53 -> 60.306 | CR70: =DY53 -> 32.853 | CS70: =ED53 -> 100.692 | CT70: =EI53 -> 98.572 | CU70: =EN53 -> 115.79 | CV70: =ES53 -> 55.224 | CW70: =EX53 -> 79.81 | CX70: =FC53 -> 88.357 | CY70: =FH53 -> 40.839 | CZ70: =FM53 -> -32.643 | DA70: =FR53 -> 21.199 | DB70: =FW53 -> 24.814 | DC70: =GB53 -> 52.976 | DD70: =GG53 -> 56.799 | DE70: =GL53 -> 83.799 | DF70: =GQ53 -> 77.177 | DG70: =GV53 -> 66.497 | DH70: =HA53 -> 86.798 | DI70: =HF53 -> 92.571 | DJ70: =HK53 -> 87.618 | DK70: =HP53 -> 31.049 | DL70: =HU53 -> 0.248
A72: CCF | B72: Total des actifs non financiers | CJ72: =CL7 -> -36.801 | CK72: =CQ7 -> -37.839 | CL72: =CV7 -> -38.753 | CM72: =DA7 -> -39.723 | CN72: =DF7 -> -41.404 | CO72: =DK7 -> -43.332 | CP72: =DP7 -> -45.262 | CQ72: =DU7 -> -47.459 | CR72: =DZ7 -> -50.563 | CS72: =EE7 -> -53.725 | CT72: =EJ7 -> -57.561 | CU72: =EO7 -> -61.479 | CV72: =ET7 -> -65.844 | CW72: =EY7 -> -65.454 | CX72: =FD7 -> -67.435 | CY72: =FI7 -> -69.454 | CZ72: =FN7 -> -70.356 | DA72: =FS7 -> -70.446 | DB72: =FX7 -> -72.278 | DC72: =GC7 -> -73.151 | DD72: =GH7 -> -74.181 | DE72: =GM7 -> -77.468 | DF72: =GR7 -> -81.211 | DG72: =GW7 -> -85.765 | DH72: =HB7 -> -89.973 | DI72: =HG7 -> -96.946 | DJ72: =HL7 -> -106.424 | DK72: =HQ7 -> -109.65 | DL72: =HV7 -> -108.746
B73: Total des actifs financiers | CJ73: =CL39 -> 0 | CK73: =CQ39 -> 0 | CL73: =CV39 -> 0 | CM73: =DA39 -> 0 | CN73: =DF39 -> 0 | CO73: =DK39 -> 0 | CP73: =DP39 -> 0 | CQ73: =DU39 -> 0 | CR73: =DZ39 -> 0 | CS73: =EE39 -> 0 | CT73: =EJ39 -> 0 | CU73: =EO39 -> 0 | CV73: =ET39 -> 0 | CW73: =EY39 -> 0 | CX73: =FD39 -> 0 | CY73: =FI39 -> 0 | CZ73: =FN39 -> 0 | DA73: =FS39 -> 0 | DB73: =FX39 -> 0 | DC73: =GC39 -> 0 | DD73: =GH39 -> 0 | DE73: =GM39 -> 0 | DF73: =GR39 -> 0 | DG73: =GW39 -> 0 | DH73: =HB39 -> 0 | DI73: =HG39 -> 0 | DJ73: =HL39 -> 0 | DK73: =HQ39 -> 0 | DL73: =HV39 -> 0
B74: Total des passifs financiers | CJ74: =CL53 -> 0 | CK74: =CQ53 -> 0 | CL74: =CV53 -> 0 | CM74: =DA53 -> 0 | CN74: =DF53 -> 0 | CO74: =DK53 -> 0 | CP74: =DP53 -> 0 | CQ74: =DU53 -> 0 | CR74: =DZ53 -> 0 | CS74: =EE53 -> 0 | CT74: =EJ53 -> 0 | CU74: =EO53 -> 0 | CV74: =ET53 -> 0 | CW74: =EY53 -> 0 | CX74: =FD53 -> 0 | CY74: =FI53 -> 0 | CZ74: =FN53 -> 0 | DA74: =FS53 -> 0 | DB74: =FX53 -> 0 | DC74: =GC53 -> 0 | DD74: =GH53 -> 0 | DE74: =GM53 -> 0 | DF74: =GR53 -> 0 | DG74: =GW53 -> 0 | DH74: =HB53 -> 0 | DI74: =HG53 -> 0 | DJ74: =HL53 -> 0 | DK74: =HQ53 -> 0 | DL74: =HV53 -> 0
A76: Prix | B76: Total des actifs non financiers | CJ76: =CM7 -> 18.331 | CK76: =CR7 -> 11.028 | CL76: =CW7 -> 94.181 | CM76: =DB7 -> 213.941 | CN76: =DG7 -> 226.749 | CO76: =DL7 -> 232.292 | CP76: =DQ7 -> 348.102 | CQ76: =DV7 -> 484.647 | CR76: =EA7 -> 646.311 | CS76: =EF7 -> 718.75 | CT76: =EK7 -> 535.714 | CU76: =EP7 -> 284.832 | CV76: =EU7 -> -379.007 | CW76: =EZ7 -> -68.761 | CX76: =FE7 -> 514.399 | CY76: =FJ7 -> 185.511 | CZ76: =FO7 -> -143.008 | DA76: =FT7 -> -146.945 | DB76: =FY7 -> -160.488 | DC76: =GD7 -> -17.823 | DD76: =GI7 -> 148.089 | DE76: =GN7 -> 225.227 | DF76: =GS7 -> 226.325 | DG76: =GX7 -> 282.598 | DH76: =HC7 -> 432.481 | DI76: =HH7 -> 558.704 | DJ76: =HM7 -> 346.933 | DK76: =HR7 -> -425.358 | DL76: =HW7 -> -183.907
B77: Total des actifs financiers | CJ77: =CM39 -> 79.966 | CK77: =CR39 -> 61.224 | CL77: =CW39 -> 74.7 | CM77: =DB39 -> 207.093 | CN77: =DG39 -> 24.525 | CO77: =DL39 -> -163.119 | CP77: =DQ39 -> -107.809 | CQ77: =DV39 -> 77.701 | CR77: =EA39 -> 77.293 | CS77: =EF39 -> 109.061 | CT77: =EK39 -> 204.917 | CU77: =EP39 -> 32.057 | CV77: =EU39 -> -380.157 | CW77: =EZ39 -> 122.718 | CX77: =FE39 -> 81.44 | CY77: =FJ39 -> -74.808 | CZ77: =FO39 -> 130.372 | DA77: =FT39 -> 68.678 | DB77: =FY39 -> 65.756 | DC77: =GD39 -> 101.233 | DD77: =GI39 -> 54.532 | DE77: =GN39 -> 115.009 | DF77: =GS39 -> -146.366 | DG77: =GX39 -> 368.281 | DH77: =HC39 -> 67.489 | DI77: =HH39 -> 315.363 | DJ77: =HM39 -> -540.292 | DK77: =HR39 -> 265.896 | DL77: =HW39 -> -2.938
B78: Total des passifs financiers | CJ78: =CM53 -> -1 | CK78: =CR53 -> -1.939 | CL78: =CW53 -> -2.885 | CM78: =DB53 -> -0.366 | CN78: =DG53 -> 0.236 | CO78: =DL53 -> -0.586 | CP78: =DQ53 -> -2.882 | CQ78: =DV53 -> -1.132 | CR78: =EA53 -> -1.2 | CS78: =EF53 -> 0.086 | CT78: =EK53 -> -0.707 | CU78: =EP53 -> -0.63 | CV78: =EU53 -> 1.231 | CW78: =EZ53 -> 0 | CX78: =FE53 -> 0 | CY78: =FJ53 -> 0 | CZ78: =FO53 -> 0.981 | DA78: =FT53 -> -0.877 | DB78: =FY53 -> 1.588 | DC78: =GD53 -> 2.477 | DD78: =GI53 -> 0.202 | DE78: =GN53 -> -2.395 | DF78: =GS53 -> 0.888 | DG78: =GX53 -> 0.682 | DH78: =HC53 -> -1.056 | DI78: =HH53 -> 1.288 | DJ78: =HM53 -> 0.918 | DK78: =HR53 -> -0.008 | DL78: =HW53 -> 0.438
B81: RDB | C81: 223.681 | D81: 249.841 | E81: 283.779 | F81: 327.33 | G81: 373.165 | H81: 408.996 | I81: 437.228 | J81: 468.874 | K81: 496.607 | L81: 520.65 | M81: 553.09 | N81: 593.353 | O81: 634.505 | P81: 660.275 | Q81: 693.118 | R81: 707.974 | S81: 718.584 | T81: 743.11 | U81: 762.509 | V81: 783.679 | W81: 809.521 | X81: 831.468 | Y81: 881.744 | Z81: 927.052 | AA81: 966.188 | AB81: 992.894 | AC81: 1035.68 | AD81: 1071.148 | AE81: 1128.433 | AF81: 1186.758 | AG81: 1225.524 | AH81: 1227.942 | AI81: 1260.979 | AJ81: 1288.225 | AK81: 1301.809 | AL81: 1296.566 | AM81: 1315.37 | AN81: 1330.905 | AO81: 1353.53 | AP81: 1387.38 | AQ81: 1427.117 | AR81: 1475.704 | AS81: 1490.321 | AT81: 1562.529 | AU81: 1646.103 | AV81: 1775.835 | AW81: 1861.088 | CJ81: 762.509 | CK81: 783.679 | CL81: 809.521 | CM81: 831.468 | CN81: 881.744 | CO81: 927.052 | CP81: 966.188 | CQ81: 992.894 | CR81: 1035.68 | CS81: 1071.148 | CT81: 1128.433 | CU81: 1186.758 | CV81: 1225.524 | CW81: 1227.942 | CX81: 1260.979 | CY81: 1288.225 | CZ81: 1301.809 | DA81: 1296.566 | DB81: 1315.37 | DC81: 1330.905 | DD81: 1353.53 | DE81: 1387.38 | DF81: 1427.117 | DG81: 1475.704 | DH81: 1490.321 | DI81: 1562.529 | DJ81: 1646.103 | DK81: 1775.835 | DL81: 1861.088
B82: En % | CJ82: =Niveau!T73 -> 3.4131013 | CK82: =(CK81-CJ81)/CJ81*100 -> 2.7763607 | CL82: =(CL81-CK81)/CK81*100 -> 3.2975236 | CM82: =(CM81-CL81)/CL81*100 -> 2.7111094 | CN82: =(CN81-CM81)/CM81*100 -> 6.0466548 | CO82: =(CO81-CN81)/CN81*100 -> 5.1384529 | CP82: =(CP81-CO81)/CO81*100 -> 4.2215539 | CQ82: =(CQ81-CP81)/CP81*100 -> 2.7640583 | CR82: =(CR81-CQ81)/CQ81*100 -> 4.3092213 | ... DL82: =(DL81-DK81)/DK81*100 -> 4.8007275
B83: RDB réel (en %) | CJ83: =CJ82-CJ84 -> 1.9301013 | CK83: =CK82-CK84 -> 2.0123607 | CL83: =CL82-CL84 -> 3.1645236 | CM83: =CM82-CM84 -> 3.1861094 | CN83: =CN82-CN84 -> 3.9706548 | CO83: =CO82-CO84 -> 3.3784529 | CP83: =CP82-CP84 -> 3.2375539 | CQ83: =CQ82-CQ84 -> 1.2340583 | ... DL83: =DL82-DL84 -> 2.6137275
B84: Déflateur de la consommation (en %) | CJ84: 1.483 | CK84: 0.764 | CL84: 0.133 | CM84: -0.475 | CN84: 2.076 | CO84: 1.76 | CP84: 0.984 | CQ84: 1.53 | CR84: 2.087 | CS84: 1.792 | CT84: 2.076 | CU84: 1.89 | CV84: 2.837 | CW84: -1.645 | CX84: 1.218 | CY84: 1.803 | CZ84: 1.306 | DA84: 0.59 | DB84: 0.122 | DC84: 0.23 | DD84: 0.198 | DE84: 0.767 | DF84: 1.928 | DG84: 0.791 | DH84: 0.757 | DI84: 1.36 | DJ84: 4.925 | DK84: 7.016 | DL84: 2.187
A86: Patrimoine | B86: Actifs net non financiers | CJ86: =Niveau!T65 -> 1665.086 | CK86: =Niveau!U65 -> 1688.069 | CL86: =Niveau!V65 -> 1693.846 | CM86: =Niveau!W65 -> 1801.861 | CN86: =Niveau!X65 -> 2010.608 | CO86: =Niveau!Y65 -> 2261.125 | CP86: =Niveau!Z65 -> 2504.353 | CQ86: =Niveau!AA65 -> 2853.355 | ... DL86: =Niveau!AV65 -> 7845.108
B87: Actifs financiers | CJ87: =Niveau!T66 -> 1898.591 | CK87: =Niveau!U66 -> 2035.09 | CL87: =Niveau!V66 -> 2180.133 | CM87: =Niveau!W66 -> 2323.332 | CN87: =Niveau!X66 -> 2620.063 | CO87: =Niveau!Y66 -> 2710.446 | CP87: =Niveau!Z66 -> 2643.19 | CQ87: =Niveau!AA66 -> 2658.662 | ... DL87: =Niveau!AV66 -> 6806.904
A89: Flux net des dettes | B89: Total des actifs non financiers | CJ89: =CJ68-CJ70 -> 34.101 | CK89: =CK68-CK70 -> 26.699 | CL89: =CL68-CL70 -> 44.519 | CM89: =CM68-CM70 -> 33.165 | CN89: =CN68-CN70 -> 51.486 | CO89: =CO68-CO70 -> 34.709 | CP89: =CP68-CP70 -> 26.994 | CQ89: =CQ68-CQ70 -> 30.656 | ... DL89: =DL68-DL70 -> 150.442
B90: Total des actifs financiers | CJ90: =CJ69 -> 65.046 | CK90: =CK69 -> 79.167 | CL90: =CL69 -> 59.949 | CM90: =CM69 -> 83.03 | CN90: =CN69 -> 68.243 | CO90: =CO69 -> 101.618 | CP90: =CP69 -> 106.948 | CQ90: =CQ69 -> 114.434 | ... DL90: =DL69 -> 156.558
A92: CCF | B92: Total des actifs non financiers | CJ92: =CJ72/Niveau!T6*100 -> -1.6866732 | CK92: =CK72/Niveau!U6*100 -> -1.6962951 | CL92: =CL72/Niveau!V6*100 -> -1.7064296 | CM92: =CM72/Niveau!W6*100 -> -1.6548499 | CN92: =CN72/Niveau!X6*100 -> -1.559273 | CO92: =CO72/Niveau!Y6*100 -> -1.4790876 | CP92: =CP72/Niveau!Z6*100 -> -1.4075686 | CQ92: =CQ72/Niveau!AA6*100 -> -1.3096726 | ... DL92: =DL72/Niveau!AV6*100 -> -1.0949615
A95: En années de RDB | B95: Actifs net non financiers | CI95: =Niveau!T69 -> 2.2406992 | CJ95: =Niveau!U69 -> 2.2138349 | CK95: =Niveau!V69 -> 2.1614028 | CL95: =Niveau!W69 -> 2.225836 | CM95: =Niveau!X69 -> 2.4181424 | CN95: =Niveau!Y69 -> 2.5643781 | CO95: =Niveau!Z69 -> 2.7014159 | CP95: =Niveau!AA69 -> 2.9532089 | ... DL95: =Niveau!AW69 -> 4.1783951
B96: Actifs financiers | CI96: =Niveau!T70 -> 2.5549259 | CJ96: =Niveau!U70 -> 2.668939 | CK96: =Niveau!V70 -> 2.7819209 | CL96: =Niveau!W70 -> 2.8700083 | CM96: =Niveau!X70 -> 3.1511291 | CN96: =Niveau!Y70 -> 3.0739602 | CO96: =Niveau!Z70 -> 2.8511777 | CP96: =Niveau!AA70 -> 2.7517026 | ... DL96: =Niveau!AW70 -> 3.7489662
A98: Flux net des dettes | B98: Total des actifs non financiers | CJ98: =CJ89/CJ81 -> 0.044722095 | CK98: =CK89/CK81 -> 0.034068796 | CL98: =CL89/CL81 -> 0.05499425 | CM98: =CM89/CM81 -> 0.039887284 | CN98: =CN89/CN81 -> 0.058391098 | CO98: =CO89/CO81 -> 0.037440187 | CP98: =CP89/CP81 -> 0.027938662 | CQ98: =CQ89/CQ81 -> 0.030875401 | ... DL98: =DL89/DL81 -> 0.080835511
B99: Total des actifs financiers | CJ99: =CJ90/CJ81 -> 0.085305223 | CK99: =CK90/CK81 -> 0.10101968 | CL99: =CL90/CL81 -> 0.074054904 | CM99: =CM90/CM81 -> 0.099859526 | CN99: =CN90/CN81 -> 0.07739548 | CO99: =CO90/CO81 -> 0.10961413 | CP99: =CP90/CP81 -> 0.11069067 | CQ99: =CQ90/CQ81 -> 0.11525299 | ... DL99: =DL90/DL81 -> 0.084121761
B100: Total | CJ100: =CJ98+CJ99 -> 0.13002732 | CK100: =CK98+CK99 -> 0.13508847 | CL100: =CL98+CL99 -> 0.12904915 | CM100: =CM98+CM99 -> 0.13974681 | CN100: =CN98+CN99 -> 0.13578658 | CO100: =CO98+CO99 -> 0.14705432 | CP100: =CP98+CP99 -> 0.13862934 | CQ100: =CQ98+CQ99 -> 0.14612839 | ... DL100: =DL98+DL99 -> 0.16495727
A102: CCF | B102: Total des actifs non financiers | CJ102: =CJ72/CJ81 -> -0.048263037 | CK102: =CK72/CK81 -> -0.0482838 | CL102: =CL72/CL81 -> -0.047871519 | CM102: =CM72/CM81 -> -0.047774539 | CN102: =CN72/CN81 -> -0.04695694 | CO102: =CO72/CO81 -> -0.046741715 | CP102: =CP72/CP81 -> -0.046845955 | CQ102: =CQ72/CQ81 -> -0.047798657 | ... DL102: =DL72/DL81 -> -0.058431412
A104: Revalorisation | B104: Total des actifs nets non financiers | CJ104: =(CJ76-CJ78)/CJ81 -> 0.025351832 | CK104: =(CK76-CK78)/CK81 -> 0.016546316 | CL104: =(CL76-CL78)/CL81 -> 0.11990547 | CM104: =(CM76-CM78)/CM81 -> 0.25774534 | CN104: =(CN76-CN78)/CN81 -> 0.25689202 | CO104: =(CO76-CO78)/CO81 -> 0.25120274 | CP104: =(CP76-CP78)/CP81 -> 0.36326678 | CQ104: =(CQ76-CQ78)/CQ81 -> 0.48925565 | ... DL104: =(DL76-DL78)/DL81 -> -0.099052275
B105: Total des actifs financiers | CJ105: =CJ77/CJ81 -> 0.1048722 | CK105: =CK77/CK81 -> 0.078123824 | CL105: =CL77/CL81 -> 0.092276791 | CM105: =CM77/CM81 -> 0.24906912 | CN105: =CN77/CN81 -> 0.027814196 | CO105: =CO77/CO81 -> -0.17595453 | CP105: =CP77/CP81 -> -0.1115818 | CQ105: =CQ77/CQ81 -> 0.078257095 | ... DL105: =DL77/DL81 -> -0.0015786465
B106: Total | CJ106: =CJ104+CJ105 -> 0.13022404 | CK106: =CK104+CK105 -> 0.094670139 | CL106: =CL104+CL105 -> 0.21218227 | CM106: =CM104+CM105 -> 0.50681445 | CN106: =CN104+CN105 -> 0.28470622 | CO106: =CO104+CO105 -> 0.075248206 | CP106: =CP104+CP105 -> 0.25168497 | CQ106: =CQ104+CQ105 -> 0.56751275 | ... DL106: =DL104+DL105 -> -0.10063092
A108: Effet hausse revenu réel | B108: Total des actifs nets non financiers | CJ108: =(-CJ83/100*Niveau!T65)/CJ81 -> -0.042147498 | CK108: =(-CK83/100*Niveau!U65)/CK81 -> -0.043346876 | CL108: =(-CL83/100*Niveau!V65)/CL81 -> -0.066214658 | CM108: =(-CM83/100*Niveau!W65)/CM81 -> -0.069045667 | CN108: =(-CN83/100*Niveau!X65)/CN81 -> -0.090541363 | CO108: =(-CO83/100*Niveau!Y65)/CO81 -> -0.082402112 | CP108: =(-CP83/100*Niveau!Z65)/CP81 -> -0.083917187 | CQ108: =(-CQ83/100*Niveau!AA65)/CQ81 -> -0.035464073 | ... DL108: =(-DL83/100*Niveau!AV65)/DL81 -> -0.11017735
B109: Total des actifs financiers | CJ109: =(-CJ83/100*Niveau!T66)/CJ81 -> -0.048058095 | CK109: =(-CK83/100*Niveau!U66)/CK81 -> -0.052257813 | CL109: =(-CL83/100*Niveau!V66)/CL81 -> -0.085224254 | CM109: =(-CM83/100*Niveau!W66)/CM81 -> -0.08902796 | CN109: =(-CN83/100*Niveau!X66)/CN81 -> -0.11798624 | CO109: =(-CO83/100*Niveau!Y66)/CO81 -> -0.098776704 | CP109: =(-CP83/100*Niveau!Z66)/CP81 -> -0.08856941 | CQ109: =(-CQ83/100*Niveau!AA66)/CQ81 -> -0.033044253 | ... DL109: =(-DL83/100*Niveau!AV66)/DL81 -> -0.095596729
B110: Total | CJ110: =CJ108+CJ109 -> -0.090205593 | CK110: =CK108+CK109 -> -0.09560469 | CL110: =CL108+CL109 -> -0.15143891 | CM110: =CM108+CM109 -> -0.15807363 | CN110: =CN108+CN109 -> -0.2085276 | CO110: =CO108+CO109 -> -0.18117882 | CP110: =CP108+CP109 -> -0.1724866 | CQ110: =CQ108+CQ109 -> -0.068508326 | ... DL110: =DL108+DL109 -> -0.20577408
A112: Effet taxe inflationniste | B112: Total des actifs nets non financiers | CJ112: =(-CJ84/100*Niveau!T65)/CJ81 -> -0.032384176 | CK112: =(-CK84/100*Niveau!U65)/CK81 -> -0.016456798 | CL112: =(-CL84/100*Niveau!V65)/CL81 -> -0.002782899 | CM112: =(-CM84/100*Niveau!W65)/CM81 -> 0.010293649 | CN112: =(-CN84/100*Niveau!X65)/CN81 -> -0.047338255 | CO112: =(-CO84/100*Niveau!Y65)/CO81 -> -0.042927258 | CP112: =(-CP84/100*Niveau!Z65)/CP81 -> -0.025505216 | CQ112: =(-CQ84/100*Niveau!AA65)/CQ81 -> -0.043968774 | ... DL112: =(-DL84/100*Niveau!AV65)/DL81 -> -0.09218936
B113: Total des actifs financiers | CJ113: =(-CJ84/100*Niveau!T66)/CJ81 -> -0.036925603 | CK113: =(-CK84/100*Niveau!U66)/CK81 -> -0.019839868 | CL113: =(-CL84/100*Niveau!V66)/CL81 -> -0.0035818427 | CM113: =(-CM84/100*Niveau!W66)/CM81 -> 0.013272702 | CN113: =(-CN84/100*Niveau!X66)/CN81 -> -0.061687415 | CO113: =(-CO84/100*Niveau!Y66)/CO81 -> -0.051457577 | CP113: =(-CP84/100*Niveau!Z66)/CP81 -> -0.026919181 | CQ113: =(-CQ84/100*Niveau!AA66)/CQ81 -> -0.040968652 | ... DL113: =(-DL84/100*Niveau!AV66)/DL81 -> -0.079989227
B114: Total | CJ114: =CJ112+CJ113 -> -0.069309779 | CK114: =CK112+CK113 -> -0.036296666 | CL114: =CL112+CL113 -> -0.0063647417 | CM114: =CM112+CM113 -> 0.023566351 | CN114: =CN112+CN113 -> -0.10902567 | CO114: =CO112+CO113 -> -0.094384835 | CP114: =CP112+CP113 -> -0.052424397 | CQ114: =CQ112+CQ113 -> -0.084937425 | ... DL114: =DL112+DL113 -> -0.17217859
CI117: =CI121 -> 4.7956251 | CJ117: =CI121 -> 4.7956251 | CK117: =CJ121 -> 4.8827738 | CL117: =CK121 -> 4.9433237 | CM117: =CL121 -> 5.0958443 | CN117: =CM121 -> 5.5692715 | CO117: =CN121 -> 5.6383383 | CP117: =CO121 -> 5.5525936 | CQ117: =CP121 -> 5.7049115 | ... DL117: =DK121 -> 8.2507733
B119: Autre | CJ119: =(CJ121-CI121)-(CJ100+CJ102+CJ106+CJ110+CJ114) -> 0.034675754 | CK119: =(CK121-CJ121)-(CK100+CK102+CK106+CK110+CK114) -> 0.010976433 | CL119: =(CL121-CK121)-(CL100+CL102+CL106+CL110+CL114) -> 0.016964353 | CM119: =(CM121-CL121)-(CM100+CM102+CM106+CM110+CM114) -> 0.0091476762 | CN119: =(CN121-CM121)-(CN100+CN102+CN106+CN110+CN114) -> 0.013084297 | CO119: =(CO121-CN121)-(CO100+CO102+CO106+CO110+CO114) -> 0.0142581 | CP119: =(CP121-CO121)-(CP100+CP102+CP106+CP110+CP114) -> 0.03376051 | CQ119: =(CQ121-CP121)-(CQ100+CQ102+CQ106+CQ110+CQ114) -> 0.015959408 | ... DL119: =(DL121-DK121)-(DL100+DL102+DL106+DL110+DL114) -> 0.048645738
B121: Actif net total | CI121: =CI95+CI96 -> 4.7956251 | CJ121: =CJ95+CJ96 -> 4.8827738 | CK121: =CK95+CK96 -> 4.9433237 | CL121: =CL95+CL96 -> 5.0958443 | CM121: =CM95+CM96 -> 5.5692715 | CN121: =CN95+CN96 -> 5.6383383 | CO121: =CO95+CO96 -> 5.5525936 | CP121: =CP95+CP96 -> 5.7049115 | ... DL121: =DL95+DL96 -> 7.9273613
B123: Autre 2 | CJ123: =CJ119+CJ102+CJ110 -> -0.10379288 | CK123: =CK119+CK102+CK110 -> -0.13291206 | CL123: =CL119+CL102+CL110 -> -0.18234608 | CM123: =CM119+CM102+CM110 -> -0.19670049 | CN123: =CN119+CN102+CN110 -> -0.24240025 | CO123: =CO119+CO102+CO110 -> -0.21366243 | CP123: =CP119+CP102+CP110 -> -0.18557204 | CQ123: =CQ119+CQ102+CQ110 -> -0.10034758 | ... DL123: =DL119+DL102+DL110 -> -0.21555976
B125: Patrimoine 1995 | CI125: =CI121 -> 4.7956251 | CJ125: =CI125 -> 4.7956251 | CK125: =CJ125 -> 4.7956251 | CL125: =CK125 -> 4.7956251 | CM125: =CL125 -> 4.7956251 | CN125: =CM125 -> 4.7956251 | CO125: =CN125 -> 4.7956251 | CP125: =CO125 -> 4.7956251 | CQ125: =CP125 -> 4.7956251 | ... DL125: =DK125 -> 4.7956251
A126: Cumul | B126: Flux net des dettes | CJ126: =CJ100 -> 0.13002732 | CK126: =CJ126+CK100 -> 0.26511579 | CL126: =CK126+CL100 -> 0.39416495 | CM126: =CL126+CM100 -> 0.53391175 | CN126: =CM126+CN100 -> 0.66969833 | CO126: =CN126+CO100 -> 0.81675265 | CP126: =CO126+CP100 -> 0.95538199 | CQ126: =CP126+CQ100 -> 1.1015104 | CR126: =CQ126+CR100 -> 1.2465948 | ... DL126: =DK126+DL100 -> 4.2024909
B127: Revalorisation | CJ127: =CJ106 -> 0.13022404 | CK127: =CJ127+CK106 -> 0.22489418 | CL127: =CK127+CL106 -> 0.43707644 | CM127: =CL127+CM106 -> 0.9438909 | CN127: =CM127+CN106 -> 1.2285971 | CO127: =CN127+CO106 -> 1.3038453 | CP127: =CO127+CP106 -> 1.5555303 | CQ127: =CP127+CQ106 -> 2.123043 | CR127: =CQ127+CR106 -> 2.822877 | ... DL127: =DK127+DL106 -> 5.8983328
...

Sheet Variations 2
A1: Variable | B1: 1995 | C1: 1996 | D1: 1997 | E1: 1998 | F1: 1999 | G1: 2000 | H1: 2001 | I1: 2002 | J1: 2003 | K1: 2004 | L1: 2005 | M1: 2006 | N1: 2007 | O1: 2008 | P1: 2009 | Q1: 2010 | R1: 2011 | S1: 2012 | T1: 2013 | U1: 2014 | V1: 2015 | W1: 2016 | X1: 2017 | Y1: 2018 | Z1: 2019 | AA1: 2020 | AB1: 2021 | AC1: 2022 | AD1: 2023 | AE1: 2024
A2: nw95 | B2: 4.7956251 | C2: 4.7956251 | D2: 4.7956251 | E2: 4.7956251 | F2: 4.7956251 | G2: 4.7956251 | H2: 4.7956251 | I2: 4.7956251 | J2: 4.7956251 | K2: 4.7956251 | L2: 4.7956251 | M2: 4.7956251 | N2: 4.7956251 | O2: 4.7956251 | P2: 4.7956251 | Q2: 4.7956251 | R2: 4.7956251 | S2: 4.7956251 | T2: 4.7956251 | U2: 4.7956251 | V2: 4.7956251 | W2: 4.7956251 | X2: 4.7956251 | Y2: 4.7956251 | Z2: 4.7956251 | AA2: 4.7956251 | AB2: 4.7956251 | AC2: 4.7956251 | AD2: 4.7956251 | AE2: 4.7956251
A3: net_savings | C3: 0.13002732 | D3: 0.26511579 | E3: 0.39416495 | F3: 0.53391175 | G3: 0.66969833 | H3: 0.81675265 | I3: 0.95538199 | J3: 1.1015104 | K3: 1.2465948 | L3: 1.3718818 | M3: 1.5121525 | N3: 1.6496194 | O3: 1.8038579 | P3: 1.951294 | Q3: 2.1071729 | R3: 2.2495836 | S3: 2.3866229 | T3: 2.5410863 | U3: 2.6783549 | V3: 2.813197 | W3: 2.947313 | X3: 3.0686352 | Y3: 3.2041525 | Z3: 3.34748 | AA3: 3.5412537 | AB3: 3.7115231 | AC3: 3.8763391 | AD3: 4.0375337 | AE3: 4.2024909
A4: asset_price | C4: 0.13022404 | D4: 0.22489418 | E4: 0.43707644 | F4: 0.9438909 | G4: 1.2285971 | H4: 1.3038453 | I4: 1.5555303 | J4: 2.123043 | K4: 2.822877 | L4: 3.5956227 | M4: 4.252585 | N4: 4.5201366 | O4: 3.8996714 | P4: 3.9436124 | Q4: 4.4161334 | R4: 4.5020679 | S4: 4.4916078 | T4: 4.4319194 | U4: 4.3586928 | V4: 4.4195033 | W4: 4.5690523 | X4: 4.8160149 | Y4: 4.871421 | Z4: 5.3120223 | AA4: 5.6482089 | AB4: 6.2067771 | AC4: 6.0887547 | AD4: 5.9989637 | AE4: 5.8983328
A5: inflation_tax | C5: -0.069309779 | D5: -0.10560644 | E5: -0.11197119 | F5: -0.088404835 | G5: -0.1974305 | H5: -0.29181534 | I5: -0.34423974 | J5: -0.42917716 | K5: -0.55389125 | L5: -0.67174315 | M5: -0.81866202 | N5: -0.96010108 | O5: -1.1780831 | P5: -1.0600959 | Q5: -1.146494 | R5: -1.2820652 | S5: -1.3819204 | T5: -1.4278348 | U5: -1.437299 | V5: -1.4550834 | W5: -1.4704817 | X5: -1.5315644 | Y5: -1.6874131 | Z5: -1.7504175 | AA5: -1.814446 | AB5: -1.9308387 | AC5: -2.3645684 | AD5: -2.9402079 | AE5: -3.1123865
A6: others | C6: -0.10379288 | D6: -0.23670493 | E6: -0.41905101 | F6: -0.6157515 | G6: -0.85815175 | H6: -1.0718142 | I6: -1.2573862 | J6: -1.3577338 | K6: -1.5094271 | L6: -1.6358911 | M6: -1.8713521 | N6: -2.0707551 | O6: -2.1344459 | P6: -2.346147 | Q6: -2.4907726 | R6: -2.538701 | S6: -2.5411732 | T6: -2.4708302 | U6: -2.5716878 | V6: -2.6641148 | W6: -2.6784913 | X6: -2.8337502 | Y6: -2.9474496 | Z6: -3.1627353 | AA6: -3.1976936 | AB6: -3.5053548 | AC6: -3.5448599 | AD6: -3.6411413 | AE6: -3.8567011
A7: net_wealth | B7: 4.7956251 | C7: 4.8827738 | D7: 4.9433237 | E7: 5.0958443 | F7: 5.5692715 | G7: 5.6383383 | H7: 5.5525936 | I7: 5.7049115 | J7: 6.2332676 | K7: 6.8017785 | L7: 7.4554954 | M7: 7.8703485 | N7: 7.934525 | O7: 7.1866255 | P7: 7.2842887 | Q7: 7.6816648 | R7: 7.7265105 | S7: 7.7507622 | T7: 7.8699657 | U7: 7.8236861 | V7: 7.9091272 | W7: 8.1630174 | X7: 8.3149606 | Y7: 8.2363359 | Z7: 8.5419745 | AA7: 8.9729481 | AB7: 9.2777318 | AC7: 8.8512906 | AD7: 8.2507733 | AE7: 7.9273613
